Workbook

Sheet SUN REALTY-MEM COLL
C1: GRAVITAS
C4: CALCULATION For the month of NOV-25
C6: SHOP MEMBERS COLLECTION BEFORE BU
C7: Flat No. | D7: Name of Owner | E7: CR SIDE | F7: LAND PORTION (One Third) | G7: TAXABLE VALUE (Two Third) | H7: REFUND OF SAME PEROID( WITH GST) | I7: REFUND WITHOUT GST | J7: Receipt of Maintenance Expence | K7: Receipt of refundable /MAINTENANCE Deposit | L7: Payment of refundable /MAINTENANCE Deposit | M7: Refundable deposit repayment | N7: Receipt Stamp Duty /JV (Cr) | O7: Payment Stamp Duty /JV (Dr) | P7: Receipt Registration Fees/JV (Cr) | Q7: Payment of Reg Fees/JV (Dr) | R7: SALES JOURNAL | S7: JV of AEC, AUDA, extra work | T7: Payment of stampduty on behalf of party | U7: Receipt of AEC, AUDA | V7: GST Reversal Entry due to E - Invoice | W7: Refundable Deposite income | X7: Cancellation income | Y7: Cheque Return | Z7: NET RECEIPT
E9: 0 | F9: =+E9/3 | G9: =+E9-F9 | Z9: =E9-P9-K9-J9-U9-N9
F10: =+E10/3 | G10: =+E10-F10 | I10: 0 | Q10: =+P10 | Y10: 0 | Z10: =E10-P10-K10-J10-U10-N10
B11: =+AA11 | F11: =+E11/3 | G11: =+E11-F11 | O11: =N11 | Q11: =+P11 | Z11: =E11-P11-K11-J11-U11-N11 | AA11: =Z11*6/100 | AB11: =+H11+I11+M11+Q11+R11+S11+T11+Y11
B12: =+AA12 | F12: =+E12/3 | G12: =+E12-F12 | Z12: =E12-P12-K12-J12-U12-N12 | AA12: =Z12*6/100 | AB12: =+H12+I12+M12+Q12+R12+S12+T12+Y12
B13: =+AA13 | Z13: =E13-P13-K13-J13-U13-N13 | AA13: =Z13*6/100 | AB13: =+H13+I13+M13+Q13+R13+S13+T13+Y13
B14: =+AA14 | F14: =+E14/3 | G14: =+E14-F14 | O14: =+N14 | Q14: =+P14 | Z14: =E14-P14-K14-J14-U14-N14 | AA14: =(Z14*6/100)+(J14*9/100) | AB14: =+H14+I14+M14+Q14+R14+S14+T14+Y14
B15: =+AA15 | F15: =+E15/3 | G15: =+E15-F15 | O15: 0 | Q15: =+P15 | Z15: =E15-P15-K15-J15-U15-N15 | AA15: =Z15*6/100 | AB15: =+H15+I15+M15+Q15+R15+S15+T15+Y15
B16: =+AA16 | F16: =+E16/3 | G16: =+E16-F16 | O16: =+N16 | Q16: 0 | Z16: =E16-P16-K16-J16-U16-N16 | AA16: =Z16*6/100 | AB16: =+H16+I16+M16+Q16+R16+S16+T16+Y16
B17: =+AA17 | F17: =+E17/3 | G17: =+E17-F17 | O17: =+N17 | Q17: 0 | Z17: =E17-P17-K17-J17-U17-N17 | AA17: =Z17*6/100 | AB17: =+H17+I17+M17+Q17+R17+S17+T17+Y17
B18: =+AA18 | F18: =+E18/3 | G18: =+E18-F18 | O18: =+N18 | Z18: =E18-P18-K18-J18-U18-N18 | AA18: =Z18*6/100 | AB18: =+H18+I18+M18+Q18+R18+S18+T18+Y18
B19: =+AA19 | F19: =+E19/3 | G19: =+E19-F19 | Z19: =E19-P19-K19-J19-U19-N19 | AA19: =Z19*6/100 | AB19: =+H19+I19+M19+Q19+R19+S19+T19+Y19
B20: =+AA20 | F20: =+E20/3 | G20: =+E20-F20 | O20: =+N20 | Q20: =+P20 | Z20: =E20-P20-K20-J20-U20-N20 | AA20: =Z20*6/100 | AB20: =+H20+I20+M20+Q20+R20+S20+T20+Y20
C21: Total | E21: =SUM(E9:E20) | F21: =SUM(F9:F20) | G21: =SUM(G9:G20) | H21: =SUM(H9:H20) | I21: =SUM(I9:I20) | J21: =SUM(J9:J20) | K21: =SUM(K9:K20) | M21: =SUM(M9:M20) | N21: =SUM(N9:N20) | O21: =SUM(O9:O20) | P21: =SUM(P9:P20) | Q21: =SUM(Q9:Q20) | R21: =SUM(R9:R20) | S21: =SUM(S9:S20) | T21: =SUM(T9:T20) | ... Z21: =SUM(Z9:Z20)
Z22: =Y21+T21+S21+R21+Q21+M21+I21+H21
C23: AFTER BU
C24: SHOP MEMBERS COLLECTION AFTER BU
C25: Flat No. | D25: Name of Owner | E25: CR SIDE | F25: LAND PORTION (One Third) | G25: TAXABLE VALUE (Two Third) | H25: REFUND OF SAME PEROID ( WITH GST) | I25: REFUND OF PREVIOUS PEROID ( WITHOUT GST) | J25: Receipt of Maintenance Expence | K25: Receipt of refundable /MAINTENANCE Deposit | L25: Payment of refundable /MAINTENANCE Deposit | M25: Maintenance deposit JV/(DR) | N25: Receipt Stamp Duty /JV (Cr) | O25: Payment Stamp Duty /JV (Dr) | P25: Receipt Registration Fees/JV (Cr) | Q25: Payment of Reg Fees/JV (Dr) | R25: SALES JOURNAL/SALES DEED | S25: JV of AEC, AUDA, extra work | T25: Payment of stampduty on behalf of party | U25: Receipt of AEC, AUDA | V25: GST Reversal Entry due to E - Invoice | W25: Refundable Deposite income | X25: Cancellation income | Y25: Cheque Return | Z25: NET RECEIPT
O27: =N27 | R27: 0 | S27: 0 | T27: 0 | U27: 0 | Z27: =E27-P27-K27-J27-U27-N27
F28: 0 | G28: 0 | O28: =N28 | R28: 0 | Z28: =E28-P28-K28-J28-U28-N28
O29: =N29 | R29: 0 | Z29: =E29-P29-K29-J29-U29-N29
O30: =N30 | R30: 0 | Z30: =E30-P30-K30-J30-U30-N30
O31: =N31 | Z31: =E31-P31-K31-J31-U31-N31
R32: 0 | Z32: =E32-P32-K32-J32-U32-N32
R33: 0
Z34: =E34-P34-K34-J34-U34-N34
L35: =K35 | Q35: =P35 | Z35: =E35-P35-K35-J35-U35-N35
F36: 0 | G36: 0 | O36: =N36 | Q36: =P36 | Z36: =E36-P36-K36-J36-U36-N36
F37: 0 | G37: 0 | O37: =N37 | Q37: =P37 | Z37: =E37-P37-K37-J37-U37-N37
F38: 0 | G38: 0 | O38: =N38 | Q38: =P38 | Z38: =E38-P38-K38-J38-U38-N38
F39: 0 | G39: 0 | Q39: =P39 | Z39: =E39-P39-K39-J39-U39-N39
F40: 0 | G40: 0 | J40: 0 | O40: =N40 | Z40: =E40-P40-K40-J40-U40-N40 | AB40: =+H40+I40+M40+Q40+R40+S40+T40+Y40
Z41: =E41-P41-K41-J41-U41-N41 | AB41: =+H41+I41+M41+Q41+R41+S41+T41+Y41
Z43: =E43-P43-K43-J43-U43-N43
H44: 0 | Z44: =E44-P44-K44-J44-U44-N44
Z45: =E45-P45-K45-J45-U45-N45
Z46: =E46-P46-K46-J46-U46-N46
H47: 0 | Z47: =E47-P47-K47-J47-U47-N47
Z48: =E48-P48-K48-J48-U48-N48
C49: Total | E49: =SUM(E27:E48) | F49: =SUM(F27:F42) | G49: =SUM(G27:G42) | H49: =SUM(H27:H42) | I49: =SUM(I27:I42) | J49: =SUM(J27:J42) | K49: =SUM(K27:K42) | M49: =SUM(M27:M42) | N49: =SUM(N27:N42) | O49: =SUM(O27:O42) | P49: =SUM(P27:P42) | Q49: =SUM(Q27:Q42) | R49: =SUM(R27:R42) | S49: =SUM(S27:S42) | T49: =SUM(T27:T42) | ... Z49: =SUM(Z27:Z42)
Z50: =Y49+T49+S49+R49+Q49+M49+I49+H49
D51: Total CR. | E51: =+E49+E21
D52: Total DR. | E52: =+M21+O21+Q21+R21+S21+T21+Y21+H21+I21
C57: =+CELL("filename")

Sheet SUN REALTY-CALC
A1: Sun Realty
A4: GST PAYABLE ON COMMERCIAL CONSTRUCTION FOR THE MONTH OF AUG-26
A6: Supply | B6: AMOUNT | C6: LAND VALUE (1/3) | D6: TAXABLE VALUE (2/3) | E6: RATE | F6: CGST @ 9% | G6: SGST@ 9% | H6: TOTAL
A8: COMMERCIAL CONSTRUCTION SERVICE | B8: ='SUN REALTY-MEM COLL'!Z21 | C8: =B8/3 | D8: =B8-C8 | E8: 0.18 | F8: =+D8*9% | G8: =+D8*9% | H8: =+F8+G8
A9: Refundable Deposite Income (B2C) | B9: =+'SUN REALTY-MEM COLL'!W21+'SUN REALTY-MEM COLL'!W49 | D9: =B9*100/118 | E9: 0.18 | F9: =+D9*9% | G9: =+D9*9% | H9: =+F9+G9
A10: B2B E- Invoice Effect In Payable | F10: 0 | G10: 0
A11: Less : Refund | B11: =-'SUN REALTY-MEM COLL'!H21 | C11: =+B11/3 | D11: =+B11-C11 | E11: 0.18 | F11: =+D11*9% | G11: =+D11*9% | H11: =+F11+G11
A12: ADD: Maintenance Expence | B12: ='SUN REALTY-MEM COLL'!J21+'SUN REALTY-MEM COLL'!J49 | E12: 0.18 | F12: =B12*9/100 | G12: =F12 | H12: =+F12+G12
A13: ADD: Receipt of AEC, AUDA | B13: ='SUN REALTY-MEM COLL'!U21 | C13: =B13/3 | D13: =B13-C13 | E13: 0.18 | F13: =+D13*9% | G13: =+D13*9% | H13: =+F13+G13
A15: LESS:- Entry of Receipt deleted Back dated hence excess payment shows
D16: 0 | E16: 0.18 | F16: =B16*9/100 | G16: =F16 | H16: =+F16+G16
B17: 0 | C17: =+B17/3 | D17: =B17-C17 | E17: 0.18 | F17: =+D17*9% | G17: =+D17*9% | H17: =+F17+G17
C18: =+B18/3 | D18: =+B18-C18 | E18: 0.18 | F18: =+D18*9% | G18: =+D18*9% | H18: =+F18+G18
A19: TOTAL | B19: =SUM(B8:B18) | C19: =SUM(C8:C18) | D19: =SUM(D8:D18) | F19: =SUM(F8:F18) | G19: =SUM(G8:G18) | H19: =SUM(H8:H18)
A20: B2C
A21: Cancellation Income | B21: 0 | C21: 0 | E21: 0.18 | F21: =+D21*9% | G21: =+D21*9% | H21: =+F21+G21
E22: 0.18 | F22: =+D22*9% | G22: =+D22*9% | H22: =+F22+G22
A23: Advance adjusted for same | D23: =-B23*2/3 | E23: 0.18 | F23: =+D23*9% | G23: =+D23*9% | H23: =+F23+G23
A24: Extra work income (2/3portion only) | B24: =+'SUN REALTY-MEM COLL'!S21 | D24: =B24*2/3 | E24: 0.18 | F24: =+D24*9% | G24: =+D24*9% | H24: =+F24+G24
A25: Advance adjusted for same | B25: =-B24 | D25: =B25*2/3 | E25: 0.18 | F25: =+D25*9% | G25: =+D25*9% | H25: =+F25+G25
A26: COMMERCIAL CONSTRUCTION SERVICE (AFTER BU) | B26: =+'SUN REALTY-MEM COLL'!R49+'SUN REALTY-MEM COLL'!S49
A27: COMMERCIAL CONSTRUCTION SERVICE (AFTER BU) BACK DATED ENTRY in Jan-26 (838, Zahabiya After Bu) | B27: 0
A29: TOTAL | B29: =SUM(B22:B27)+B19 | C29: =SUM(C22:C27)+C19 | D29: =SUM(D22:D27)+D19 | F29: =SUM(F22:F27)+F19 | G29: =SUM(G22:G27)+G19 | H29: =SUM(H22:H27)
A30: B2C SALE & Advance adjustment (as per sale deed sheet) | E30: 0.18 | F30: =+D30*9% | G30: =+D30*9% | H30: =+F30+G30
A33: Supply | B33: GSTIN | D33: AMOUNT | E33: RATE | F33: CGST | G33: SGST | H33: TOTAL
A36: Rent income-Meglyn Technologies Pvt Ltd (SAC-)] ( To be Confirm is there any income ) | B36: 24AAJCM9952F1Z6 | E36: 0.18 | F36: =+D36*E36/2 | G36: =+D36*E36/2 | H36: =+SUM(F36:G36)
A38: TOTAL | D38: =+SUM(D35:D37) | F38: =+SUM(F35:F37) | G38: =+SUM(G35:G37) | H38: =+SUM(H35:H37)
A41: GST PAYABLE UNDER RCM FOR THE MONTH OF AUG-26
A42: .
A43: Service | B43: AMOUNT | C43: RATE | D43: CGST | E43: SGST | F43: TOTAL
A45: SUN GRAVITAS
A46: Advocate fees | B46: 0 | C46: 0.18 | D46: =+B46*9/100 | E46: =+D46 | F46: =+D46+E46
A47: Carting and Transportation (Gayatri Sales Corp) | C47: 0.05 | D47: =+B47*0.025 | E47: =+D47 | F47: =+D47+E47
A48: Security Services | C48: 0.18 | D48: =+B48*9% | E48: =+B48*9% | F48: =SUM(D48:E48)
A49: Sponsharship Services | C49: 0.18 | D49: =+B49*9% | E49: =+B49*9% | F49: =SUM(D49:E49)
A51: SUN OFFICE
A52: Freight Charges(Gayatri Sales Corporation) | C52: 0.05 | D52: =+B52*2.5/100 | E52: =+D52 | F52: =+D52+E52
A53: Security Expense | B53: 0 | C53: 0.18 | D53: =+B53*9/100 | E53: =+D53 | F53: =+D53+E53
A55: TOTAL | B55: =SUM(B45:B54) | D55: =SUM(D45:D54) | E55: =SUM(E45:E54) | F55: =SUM(F45:F54)
A57: INPUT TAX CREDIT FOR THE MONTH OF AUG-26
A59: PARTICULARS | B59: CGST | C59: SGST | D59: IGST
A61: Opening Balance | C61: =+B61 | D61: 0
A62: Add : ITC FOR THE AUG-26 | B62: 0 | C62: =B62 | D62: 0
A63: Add : ITC of RCM of NOV-25 | B63: =SUM(D46:D49) | C63: =+B63 | D63: =+G55
C64: =B64
C65: =+B65
A66: Add : ITC of Previous Month (Now reflacting in GSTR-2B) | B66: 0 | C66: =B66 | D66: 0
A67: Less: Credit Note In GSTR-2B but not in Book | C67: =+B67
A68: Add:ITC of Bills which are in GSTR-2B but not in Books (DEC) | C68: =B68
A69: Add:ITC of Bills which are in GSTR-2B but not in Books (Decil) | C69: =B69
A70: Total CENVAT available | B70: =SUM(B61:B69) | C70: =SUM(C61:C69) | D70: =SUM(D61:D69)
A71: Less : ITC OF IGST Utilized for NOV-25 | B71: 0 | C71: =B71
A72: Less : ITC REVERSED FOR THE NOV-25 | B72: =-B102 | C72: =-C102 | D72: =-D102
A73: Net ITC Available for Utilisation | B73: =B70+B72 | C73: =C70+C72 | D73: =D70+D72
A74: Less : ITC Utilised FOR THE NOV-25 | B74: =+B83 | C74: =+B74 | D74: =+B82+C82
A75: Closing Balance | B75: =SUM(B73:B74) | C75: =SUM(C73:C74) | D75: =SUM(D73:D74)
A77: GST Payable for the month of AUG-26
A79: PARTICULARS | B79: CGST | C79: SGST | D79: TOTAL
A81: =+A8 | B81: =+F29 | C81: =+G29 | D81: =SUM(B81:C81)
A82: LESS.: CENVAT IGST CREDIT UTILIZED | B82: =-D101/2 | C82: =+B82 | D82: =SUM(B82:C82)
A83: LESS.: CENVAT CREDIT UTILIZED | D83: =SUM(B83:C83)
A84: TOTAL PAYABLE FOR RESIDENTIAL INCLUDING IGST | B84: =SUM(B81:B83) | C84: =SUM(C81:C83) | D84: =SUM(D81:D83)
A86: GST Paid on RENT Income | B86: =+F38 | C86: =+G38 | D86: =+H38
A88: GST UNDER RCM
A89: SUN GRAVITAS | B89: =SUM(D47:D49) | C89: =B89 | D89: =+B89+C89
A90: SUN OFFICE | B90: =D53 | C90: =E53 | D90: =+B90+C90
A91: GST Payable | B91: =+B84+B89+B90+B86 | C91: =B91 | D91: =+D84+D89+D90+D86
A92: GST Late Fees | C92: =B92 | D92: =SUM(B92:C92)
A93: Net GST Payable | B93: =+B88+B91+B92 | C93: =B93 | D93: =+D91+D92
A97: CREDIT REVERSAL DUE TO BU | F97: Particulars | G97: Ratio
A98: PARTICULARS | B98: CGST | C98: SGST | D98: IGST | E98: TOTAL | F98: Sold Units Ratio | G98: 45.752705
A99: Total Input Tax Credit Available for the AUG-26 | B99: =SUM(B62:B69) | C99: =SUM(C62:C69) | D99: =SUM(D62:D69) | E99: =SUM(B99:D99) | F99: Unsold Units Ratio | G99: 54.247295
F100: Total | G100: =SUM(G98:G99)
A101: Credit Available for Units Sold Before BU | B101: =+B99*$G$98/100 | C101: =+C99*$G$98/100 | D101: =+D99*$G$98/100 | E101: =SUM(B101:D101)
A102: Credit Not Available for Units Sold after BU ( Rule 42 & 43 Credit Reversal ) | B102: =+B99*$G$99/100 | C102: =+C99*$G$99/100 | D102: =+D99*$G$99/100 | E102: =+E99*$G$99/100
A103: Total Input Tax Credit for the AUG-26 | B103: =SUM(B101:B102) | C103: =SUM(C101:C102) | D103: =SUM(D101:D102) | E103: =SUM(E101:E102)
A119: =+'SUN REALTY-MEM COLL'!C57

Sheet SUN REALTY ATMOS-MEMBERS COLL
B1: Sun Realty
B4: CALCULATION For the month of AUG-26
B6: MEMBERS COLLECTION
B7: Flat No | C7: Name of Owner | D7: CR SIDE | E7: Receipt of Registration Fees/JV (Cr) | F7: Payment of Reg Fees on Behalf of Client / JV (Dr) | G7: Receipt of stamp/ registartion duty/JV (Cr) | H7: Payment of stamp duty on Behalf of Client / JV (Dr) | I7: REFUND OF SAME PEROID | J7: REFUNDABLE DEPOSIT | K7: REFUNDABLE DEPOSIT JV(Dr.) | L7: REFUND WITHOUT GST | M7: Cheque Return Amount | N7: Sale Deed JV | O7: PLC JV | P7: PLC Income | Q7: AEC,AUDA JV | R7: KASAR | S7: Loan transfer to new person ( credit side) | T7: Loan transfer from old person ( Debit side) | U7: GST PAID @1% INSTEAD OF 18% | V7: NET RECEIPT | W7: GST
F8: =+E8 | H8: =+G8 | O8: 0 | P8: 0 | Q8: 0 | V8: =D8-E8-G8-J8-U8-R8-P8 | W8: =V8*0.5/100
F9: =E9 | H9: =G9 | K9: =J9 | V9: =D9-E9-G9-J9-U9-R9-P9 | W9: =V9*0.5/100
F10: =E10 | H10: =G10 | K10: =J10 | V10: =D10-E10-G10-J10-U10-R10-P10 | W10: =V10*0.5/100
F11: =E11 | H11: =G11 | K11: =J11 | V11: =D11-E11-G11-J11-U11-R11-P11 | W11: =V11*0.5/100
F12: =E12 | H12: =G12 | K12: =J12 | V12: =D12-E12-G12-J12-U12-R12-P12 | W12: =V12*0.5/100
F13: =E13 | H13: =G13 | K13: =J13 | V13: =D13-E13-G13-J13-U13-R13-P13 | W13: =V13*0.5/100
F14: =E14 | H14: =G14 | K14: =J14 | V14: =D14-E14-G14-J14-U14-R14-P14 | W14: =V14*0.5/100
F15: =E15 | H15: =G15 | K15: =J15 | V15: =D15-E15-G15-J15-U15-R15-P15 | W15: =V15*0.5/100
F16: =+E16 | H16: =G16 | K16: =J16 | V16: =D16-E16-G16-J16-U16-R16-P16 | W16: =V16*0.5/100
F17: =+E17 | H17: =G17 | K17: =J17 | V17: =D17-E17-G17-J17-U17-R17-P17 | W17: =V17*0.5/100
F18: =E18 | H18: 0 | K18: =J18 | V18: =D18-E18-G18-J18-U18-R18-P18 | W18: =V18*0.5/100
F19: =E19 | H19: =G19 | K19: =J19 | V19: =D19-E19-G19-J19-U19-R19-P19 | W19: =V19*0.5/100
F20: =E20 | H20: =G20 | K20: =J20 | V20: =D20-E20-G20-J20-U20-R20-P20 | W20: =V20*0.5/100 | AA20: =2553+26+163
F21: =E21 | H21: =G21 | K21: =J21 | V21: =D21-E21-G21-J21-U21-R21-P21 | W21: =V21*0.5/100
F22: =E22 | H22: =G22 | K22: =J22 | V22: =D22-E22-G22-J22-U22-R22-P22 | W22: =V22*0.5/100
F23: =E23 | H23: =G23 | K23: =J23 | V23: =D23-E23-G23-J23-U23-R23-P23 | W23: =V23*0.5/100
F24: =E24 | H24: =G24 | K24: =J24 | V24: =D24-E24-G24-J24-U24-R24-P24 | W24: =V24*0.5/100
F25: =E25 | H25: =G25 | V25: =D25-E25-G25-J25-U25-R25-P25 | W25: =V25*0.5/100
F26: =E26 | H26: =G26 | K26: =J26 | V26: =D26-E26-G26-J26-U26-R26-P26 | W26: =V26*0.5/100
F27: =E27 | H27: =G27 | K27: =J27 | V27: =D27-E27-G27-J27-U27-R27-P27 | W27: =V27*0.5/100
F28: =E28 | H28: =G28 | K28: =J28 | V28: =D28-E28-G28-J28-U28-R28-P28 | W28: =V28*0.5/100
F29: =E29 | H29: =G29 | K29: =J29 | V29: =D29-E29-G29-J29-U29-R29-P29 | W29: =V29*0.5/100 | X29: =IFERROR(VLOOKUP(C29,DATA!$U$2:$V$32,2,FALSE),0) | Y29: =+X29+G29 | Z29: =-Y29
F30: =E30 | H30: =G30 | K30: =J30 | V30: =D30-E30-G30-J30-U30-R30-P30 | W30: =V30*0.5/100 | X30: =IFERROR(VLOOKUP(C30,DATA!$U$2:$V$32,2,FALSE),0) | Y30: =+X30+G30 | Z30: =-Y30 | AD30: =138+821
F31: =E31 | H31: =G31 | K31: =J31 | V31: =D31-E31-G31-J31-U31-R31-P31 | W31: =V31*0.5/100 | X31: =IFERROR(VLOOKUP(C31,DATA!$U$2:$V$32,2,FALSE),0) | Y31: =+X31+G31 | Z31: =-Y31
F32: =E32 | H32: =G32 | K32: =J32 | V32: =D32-E32-G32-J32-U32-R32-P32 | W32: =V32*0.5/100 | X32: =IFERROR(VLOOKUP(C32,DATA!$U$2:$V$32,2,FALSE),0) | Y32: =+X32+G32 | Z32: =-Y32
F33: =E33 | H33: =G33 | K33: =J33 | V33: =D33-E33-G33-J33-U33-R33-P33 | W33: =V33*0.5/100 | X33: =IFERROR(VLOOKUP(C33,DATA!$U$2:$V$32,2,FALSE),0) | Y33: =+X33+G33 | Z33: =-Y33
F34: =E34 | H34: =G34 | V34: =D34-E34-G34-J34-U34-R34-P34 | W34: =V34*0.5/100 | X34: =IFERROR(VLOOKUP(C34,DATA!$U$2:$V$32,2,FALSE),0) | Y34: =+X34+G34 | Z34: =-Y34
F35: =E35 | H35: =G35 | K35: =J35 | V35: =D35-E35-G35-J35-U35-R35-P35 | W35: =V35*0.5/100 | X35: =IFERROR(VLOOKUP(C35,DATA!$U$2:$V$32,2,FALSE),0) | Y35: =+X35+G35 | Z35: =-Y35
F36: =E36 | H36: =G36 | K36: =J36 | V36: =D36-E36-G36-J36-U36-R36-P36 | W36: =V36*0.5/100
F37: =E37 | H37: =G37 | K37: =J37 | V37: =D37-E37-G37-J37-U37-R37-P37 | W37: =V37*0.5/100 | X37: =IFERROR(VLOOKUP(C37,DATA!$U$2:$V$32,2,FALSE),0) | Y37: =+X37+G37 | Z37: =-Y37
F38: =E38 | H38: =G38 | K38: =J38 | V38: =D38-E38-G38-J38-U38-R38-P38 | W38: =V38*0.5/100
F39: =E39 | H39: =G39 | K39: =J39 | V39: =D39-E39-G39-J39-U39-R39-P39 | W39: =V39*0.5/100
F40: =E40 | H40: =G40 | K40: =J40 | V40: =D40-E40-G40-J40-U40-R40-P40 | W40: =V40*0.5/100
F41: =E41 | H41: =G41 | K41: =J41 | V41: =D41-E41-G41-J41-U41-R41-P41 | W41: =V41*0.5/100
F42: =E42 | H42: =G42 | K42: =J42 | V42: =D42-E42-G42-J42-U42-R42-P42 | W42: =V42*0.5/100
F43: =E43 | H43: =G43 | K43: =J43 | V43: =D43-E43-G43-J43-U43-R43-P43 | W43: =V43*0.5/100 | X43: =IFERROR(VLOOKUP(C43,DATA!$U$2:$V$32,2,FALSE),0) | Y43: =+X43+G43 | Z43: =-Y43
F44: =E44 | H44: =G44 | K44: =J44 | V44: =D44-E44-G44-J44-U44-R44-P44 | W44: =V44*0.5/100 | X44: =IFERROR(VLOOKUP(C44,DATA!$U$2:$V$32,2,FALSE),0) | Y44: =+X44+G44 | Z44: =-Y44
F45: =E45 | H45: =G45 | K45: =J45 | V45: =D45-E45-G45-J45-U45-R45-P45 | W45: =V45*0.5/100
F46: =E46 | H46: =G46 | K46: =J46 | V46: =D46-E46-G46-J46-U46-R46-P46 | W46: =V46*0.5/100 | X46: =IFERROR(VLOOKUP(C46,DATA!$U$2:$V$32,2,FALSE),0) | Y46: =+X46+G46
F47: =E47 | H47: =G47 | K47: =J47 | V47: =D47-E47-G47-J47-U47-R47-P47 | W47: =V47*0.5/100
F48: =E48 | H48: =G48 | K48: =J48 | V48: =D48-E48-G48-J48-U48-R48-P48 | W48: =V48*0.5/100 | X48: =IFERROR(VLOOKUP(C48,DATA!$U$2:$V$32,2,FALSE),0) | Y48: =+X48+G48
F49: =E49 | H49: =G49 | K49: =J49 | V49: =D49-E49-G49-J49-U49-R49-P49 | W49: =V49*0.5/100 | X49: =IFERROR(VLOOKUP(C49,DATA!$U$2:$V$32,2,FALSE),0) | Y49: =+X49+G49
F50: =E50 | H50: =G50 | K50: =J50 | V50: =D50-E50-G50-J50-U50-R50-P50 | W50: =V50*0.5/100 | X50: =IFERROR(VLOOKUP(C50,DATA!$U$2:$V$32,2,FALSE),0) | Y50: =+X50+G50
F51: =E51 | H51: =G51 | K51: =J51 | V51: =D51-E51-G51-J51-U51-R51-P51 | W51: =V51*0.5/100 | X51: =IFERROR(VLOOKUP(C51,DATA!$U$2:$V$32,2,FALSE),0) | Y51: =+X51+G51
F52: =E52 | H52: =G52 | K52: =J52 | V52: =D52-E52-G52-J52-U52-R52-P52 | W52: =V52*0.5/100 | X52: =IFERROR(VLOOKUP(C52,DATA!$U$2:$V$32,2,FALSE),0) | Y52: =+X52+G52
F53: =E53 | H53: =G53 | K53: =J53 | V53: =D53-E53-G53-J53-U53-R53-P53 | W53: =V53*0.5/100
F54: =E54 | H54: =G54 | K54: =J54 | V54: =D54-E54-G54-J54-U54-R54-P54 | W54: =V54*0.5/100
F55: =E55 | H55: =G55 | K55: =J55 | V55: =D55-E55-G55-J55-U55-R55-P55 | W55: =V55*0.5/100
F56: =E56 | H56: =G56 | K56: =J56 | V56: =D56-E56-G56-J56-U56-R56-P56 | W56: =V56*0.5/100
F57: =E57 | H57: =G57 | K57: =J57 | V57: =D57-E57-G57-J57-U57-R57-P57 | W57: =V57*0.5/100
F58: =E58 | H58: =G58 | K58: =J58 | V58: =D58-E58-G58-J58-U58-R58-P58 | W58: =V58*0.5/100
F59: =E59 | H59: =G59 | K59: =J59 | V59: =D59-E59-G59-J59-U59-R59-P59 | W59: =V59*0.5/100
F60: =E60 | H60: =G60 | K60: =J60 | V60: =D60-E60-G60-J60-U60-R60-P60 | W60: =V60*0.5/100
F61: =E61 | H61: =G61 | K61: =J61 | V61: =D61-E61-G61-J61-U61-R61-P61 | W61: =V61*0.5/100
F62: =E62 | H62: =G62 | K62: =J62 | V62: =D62-E62-G62-J62-U62-R62-P62 | W62: =V62*0.5/100
F63: =E63 | H63: =G63 | K63: =J63 | V63: =D63-E63-G63-J63-U63-R63-P63 | W63: =V63*0.5/100
F64: =E64 | H64: =G64 | K64: =J64 | V64: =D64-E64-G64-J64-U64-R64-P64 | W64: =V64*0.5/100
D66: =SUM(D8:D63) | E66: =SUM(E8:E63) | F66: =SUM(F8:F63) | G66: =SUM(G9:G63) | H66: =SUM(H9:H63) | I66: =SUM(I9:I63) | J66: =SUM(J8:J63) | K66: =SUM(K8:K63) | L66: =SUM(L9:L63) | M66: =SUM(M9:M53) | N66: =SUM(N8:N63) | O66: =SUM(O8:O63) | P66: =SUM(P8:P63) | Q66: =SUM(Q9:Q63) | R66: =SUM(R9:R63) | S66: =SUM(S9:S63) | T66: =SUM(T9:T63) | U66: =SUM(U9:U63) | V66: =SUM(V8:V63)
B69: MEMBERS COLLECTION @5%
B70: Flat No. | C70: Name of Owner | D70: CR SIDE | E70: Receipt of Registration Fees | F70: Payment of Reg Fees on Behalf of Client | G70: Receipt of stamp duty/JV (Cr) | H70: Payment of stamp duty on Behalf of Client / JV (Dr) | I70: REFUND OF SAME PEROID | J70: REFUNDABLE DEPOSIT | K70: REFUNDABLE DEPOSIT JV(Dr.) | L70: REFUND WITHOUT GST | M70: Cheque Return Amount | N70: Sale Deed JV | O70: PLC JV | P70: PLC Income | Q70: AEC,AUDA JV | V70: NET RECEIPT
F72: =+E72 | G72: 0 | H72: =+G72 | M72: 0 | V72: =D72-E72-G72-J72-P72 | W72: =V72*2.5/100 | X72: =IFERROR(VLOOKUP(C72,DATA!$U$2:$V$32,2,FALSE),0) | Y72: =+X72+G72
V73: =D73-E73-G73-J73-P73 | W73: =P73*9/100 | X73: =V73*2.5%
H74: =+G74 | V74: =D74-E74-G74-J74-P74 | X74: =V74*2.5% | Y74: =+P74*9/100
H75: =+G75 | V75: =D75-E75-G75-J75-P75 | X75: =V75*2.5%
F76: =+E76 | H76: =+G76 | V76: =D76-E76-G76-J76-P76 | X76: =V76*2.5%
V77: =D77-E77-G77-J77-P77
B78: Total | D78: =SUM(D72:D77) | E78: =SUM(E72:E77) | F78: =SUM(F72:F77) | G78: =SUM(G72:G77) | H78: =SUM(H72:H77) | I78: =SUM(I72:I77) | J78: =SUM(J72:J77) | K78: =SUM(K72:K77) | ... Q78: =SUM(Q72:Q77) | V78: =SUM(V72:V77) | X78: =+V78*2.5/100
B81: SHOP MEMBERS COLLECTION
B82: Flat No. | C82: Name of Owner | D82: CR SIDE | E82: Receipt of Registration Fees | F82: Payment of Reg Fees on Behalf of Client | G82: Receipt of stamp duty/JV (Cr) | H82: Payment of stamp duty on Behalf of Client / JV (Dr) | I82: REFUND OF SAME PEROID | J82: REFUNDABLE DEPOSIT | K82: REFUNDABLE DEPOSIT JV(Dr.) | L82: REFUND WITHOUT GST | M82: Cheque Return Amount | N82: Sale Deed JV | O82: PLC JV | P82: PLC Income | Q82: AEC,AUDA JV | R82: KASAR | S82: Loan transfer to new person ( credit side) | T82: Loan transfer from old person ( Debit side) | U82: GST PAID @1% INSTEAD OF 18% | V82: NET RECEIPT
B83: Shop No. 412_After Bu | C83: SH-412 Chetak Kaku | F83: =+E83 | H83: =+G83 | K83: =+J83 | L83: 1694177.4 | V83: =D83-E83-G83-J83 | W83: =V83*2.5/100 | X83: =V83*2.5%
F84: =E84 | H84: =G84 | K84: =J84 | V84: =D84-E84-G84-J84 | W84: =V84*2.5/100 | X84: =V84*2.5% | AE84: =3095+3095
F85: =E85 | H85: =G85 | K85: =J85 | V85: =D85-E85-G85-J85 | W85: =V85*2.5/100 | X85: =V85*2.5% | AB85: =+AA85
F86: =E86 | H86: =G86 | K86: =J86 | V86: =D86-E86-G86-J86 | W86: =V86*2.5/100 | X86: =V86*2.5%
F87: =E87 | H87: =G87 | K87: =J87 | V87: =D87-E87-G87-J87 | W87: =V87*2.5/100 | X87: =V87*2.5% | AE87: =6617+3248
F88: =E88 | H88: =G88 | K88: =J88 | V88: =D88-E88-G88-J88 | W88: =V88*2.5/100 | X88: =V88*2.5%
F89: =E89 | H89: =G89 | K89: =J89 | V89: =D89-E89-G89-J89 | W89: =V89*2.5/100 | X89: =V89*2.5%
F90: =E90 | H90: =G90 | K90: =J90 | V90: =D90-E90-G90-J90 | W90: =V90*2.5/100 | X90: =V90*2.5%
F91: =E91 | H91: =G91 | K91: =J91 | V91: =D91-E91-G91-J91 | W91: =V91*2.5/100 | X91: =V91*2.5%
F92: =E92 | H92: =G92 | K92: =J92 | V92: =D92-E92-G92-J92 | W92: =V92*2.5/100 | X92: =V92*2.5%
F93: =E93 | H93: =G93 | K93: =J93 | V93: =D93-E93-G93-J93 | W93: =V93*2.5/100 | X93: =V93*2.5%
F94: =E94 | H94: =G94 | K94: =J94 | V94: =D94-E94-G94-J94 | W94: =V94*2.5/100
F95: =E95 | V95: =D95-E95-G95-J95 | W95: =V95*2.5/100 | X95: =V95*2.5%
V96: =D96-E96-G96-J96 | W96: =V96*2.5/100 | X96: =V96*2.5%
V97: =D97-E97-G97-J97 | W97: =V97*2.5/100 | X97: =V97*2.5%
F98: =+E98 | G98: 0 | H98: =+G98 | K98: =+J98 | V98: =D98-E98-G98-J98 | W98: =V98*2.5/100 | X98: =V98*2.5%
F99: =+E99 | G99: 0 | H99: =+G99 | K99: =+J99 | V99: =D99-E99-G99-J99 | W99: =V99*2.5/100 | X99: =V99*2.5%
F100: =+E100 | G100: 0 | H100: =+G100 | V100: =D100-E100-G100-J100 | W100: =V100*2.5/100
F101: =+E101 | G101: 0 | H101: =+G101 | V101: =D101-E101-G101-J101 | W101: =V101*2.5/100 | X101: =V101*2.5%
F102: =+E102 | G102: 0 | H102: =+G102 | V102: =D102-E102-G102-J102 | W102: =V102*2.5/100 | X102: =V102*2.5%
G103: 0 | H103: =+G103 | V103: =D103-E103-G103-J103 | W103: =V103*2.5/100
B104: Total | D104: =SUM(D83:D103) | E104: =SUM(E84:E103) | F104: =SUM(F84:F103) | G104: =SUM(G84:G103) | H104: =SUM(H84:H103) | I104: =SUM(I84:I103) | J104: =SUM(J84:J103) | K104: =SUM(K84:K103) | L104: =SUM(L84:L103) | ... Q104: =SUM(Q84:Q103) | V104: =SUM(V83:V103) | X104: =+V104*2.5/100
D106: =D104+D66
B112: =+'SUN REALTY-CALC'!A119
C120: Member Collection of Sun Atmosphere Flats
C121: Members'collection of Sun Atmospere Shops

Sheet DATA
B1: DEPOSIT | C1: RS | F1: regis | O1: Reg Fees Axis | R1: Stamp Fees Axis | U1: Reg Fees JV
B2: G-101, Darji Amit Gunvantbhai | C2: 30300 | F2: NAME | G2: DR | H2: CR | I2: NET | K2: A-1102,Dharman Gopalkumar Bhatt | L2: 930692 | O2: I-804,Anish Mahendra Bhatt & Maya A.Bhatt | P2: 32400 | R2: I-804,Anish Mahendra Bhatt & Maya A.Bhatt | S2: 148600 | U2: I-401, Sumara Chitra | V2: 1714.75
B3: G-101, Darji Amit Gunvantbhai | C3: 50000 | F3: E-1104, Priyanka Yadav, Pradeep Yadav | G3: 0 | H3: 171744 | I3: 171744 | K3: A-1301, Aniruddha Dutta | L3: 42100 | O3: A-503; Kantibhai D.Chudasama | P3: 42284 | R3: A-503; Kantibhai D.Chudasama | S3: 197400 | U3: I-201,Ajitbhai Kathi | V3: 1714.75
B4: H/1302,Yogesh Harikrishna Ardeshna | C4: 43000 | F4: I-401, Sumara Chitra | G4: 1714.75 | H4: 0 | I4: -1714.75 | K4: A-1304, Palak Harshadkumar Popat | L4: 460310 | O4: K-501,Vivek Goad / Raksha Sharma | P4: 2200 | R4: K-501,Vivek Goad / Raksha Sharma | S4: 215000 | U4: I-901, Shivam Thakur | V4: 1714.75
B5: H/1302,Yogesh Harikrishna Ardeshna | C5: 50000 | F5: I-201,Ajitbhai Kathi | G5: 1714.75 | H5: 0 | I5: -1714.75 | K5: A-1404, Manisha Umang Chokshi & Raj U. Chokshi | L5: 445544 | O5: P-704; Vishal Rajabhai Barad | P5: 32000 | R5: P-704; Vishal Rajabhai Barad | S5: 149000 | U5: L-803, Haresh Zanzrukia | V5: 1714.75
B6: N-104, Shital Kalpeshbhai Ajmera | C6: 50000 | F6: I-901, Shivam Thakur | G6: 1714.75 | H6: 0 | I6: -1714.75 | K6: A/204,Vipul Mistry | L6: 33976 | O6: L-1002,Nilesh Bhalchandra Yeole | P6: 46000 | R6: L-1002,Nilesh Bhalchandra Yeole | S6: 217000 | U6: D-804, Neha Bhavin Shah / Bhavin Dipakbhai Shah | V6: 708.85
B7: N-104, Shital Kalpeshbhai Ajmera | C7: 139500 | F7: L-803, Haresh Zanzrukia | G7: 1714.75 | H7: 0 | I7: -1714.75 | K7: A-304,Bhoomin Anantbhai Raval / Divya Bhoomin Raval | L7: 396040 | O7: P-304; Rupal Vishal Barad | P7: 2200 | R7: P-304; Rupal Vishal Barad | S7: 149000 | U7: N-503, Yash Satwani / Kiran Satwani | V7: 708.85
B8: N-903, Krunal Pravinkumar Chudasma | C8: 45000 | F8: D-804, Neha Bhavin Shah / Bhavin Dipakbhai Shah | G8: 708.85 | H8: 0 | I8: -708.85 | K8: A-502, Brajesh Kumar / Shalini Bhardwaj | L8: 661480 | O8: P-101, Rahul Ranjan | P8: 36500 | R8: N-903, Krunal Pravinkumar Chudasma | S8: 211000 | U8: A-1404, Manisha Umang Chokshi & Raj U. Chokshi | V8: 1714.75
B9: N-903, Krunal Pravinkumar Chudasma | C9: 50000 | F9: N-503, Yash Satwani / Kiran Satwani | G9: 708.85 | H9: 168400 | I9: 167691.15 | K9: A-503; Kantibhai D.Chudasama | L9: 761074 | O9: G-104, Daksha Rajeshbhai Darji | P9: 32280 | R9: P-101, Rahul Ranjan | S9: 169000 | U9: B-903, Smita Bhavinkumar Dave | V9: 263667.7
B10: A/204,Vipul Mistry | C10: 50000 | F10: A-1404, Manisha Umang Chokshi & Raj U. Chokshi | G10: 1714.75 | H10: 0 | I10: -1714.75 | K10: A-604., Deepakkumar, Ruchika Arora | L10: 570121 | O10: O-502, Jay Rajeshkumar Shah | P10: 42000 | R10: G-104, Daksha Rajeshbhai Darji | S10: 146000 | U10: C-1303, Vikas Jain / Anamika Jain | V10: 228769.7
B11: A-1102,Dharman Gopalkumar Bhatt | C11: 50000 | F11: I-804,Anish Mahendra Bhatt & Maya A.Bhatt | G11: 0 | H11: 181000 | I11: 181000 | K11: A/701,Hemantkumar Ishwarlal Bhavsar | L11: 900098 | O11: D-401, Bhartiben Mukeshbhai Halari / Dhaval Halari | P11: 42000 | R11: O-502, Jay Rajeshkumar Shah | S11: 197000 | U11: C/1304,Chetnaben Vallabhbhai Bavariya | V11: 182907.7
B12: A-1301, Aniruddha Dutta | C12: 50000 | F12: A-503; Kantibhai D.Chudasama | G12: 0 | H12: 239684 | I12: 239684 | K12: A/702,Hemantkumar Ishvarlal Bhavsar | L12: 900098 | O12: O-403,Jayesh Mansukhbhai Solanki | P12: 37000 | R12: D-401, Bhartiben Mukeshbhai Halari / Dhaval Halari | S12: 197000 | U12: D-604, Kashyap Dave | V12: 205803.7
B13: A-1304, Palak Harshadkumar Popat | C13: 50000 | F13: K-501,Vivek Goad / Raksha Sharma | G13: 215332.7 | H13: 217200 | I13: 1867.3 | K13: A-801; Ishwar S. Dubey | L13: 3165100 | O13: D-301,Rajesh Vithaldas Chokshi | P13: 42000 | R13: O-403,Jayesh Mansukhbhai Solanki | S13: 172000 | U13: D-1403,Jay Adthakkar | V13: 186587.7
B14: A-502, Brajesh Kumar / Shalini Bhardwaj | C14: 50000 | F14: P-704; Vishal Rajabhai Barad | G14: 0 | H14: 181000 | I14: 181000 | K14: A-902, Puja Chudasama | L14: 37624 | O14: J-1003,Jagdish Pankajkumar Patel | P14: 45000 | R14: D-301,Rajesh Vithaldas Chokshi | S14: 194000 | U14: F-203, Kalpesh Rohit Contractor & Nency Contractor | V14: 174417.7
... B32: C-1303, Vikas Jain / Anamika Jain | C32: 50000 | F32: K-202,Chinjal Lalitkumar Modi | G32: 0 | H32: 208500 | I32: 208500 | K32: C/1304,Chetnaben Vallabhbhai Bavariya | L32: 36732 | O32: C-1103, Sima Jigar Desai /Jigar S.Desai | P32: 45000 | R32: C-1103, Sima Jigar Desai /Jigar S.Desai | S32: 211000 | U32: H/1302,Yogesh Harikrishna Ardeshna | V32: 200908.85
B33: C-603,Umesh Shishivandan Pandya | C33: 50000 | F33: G-1003, Parth Mathurbhai Dobariya | G33: 0 | H33: 194600 | I33: 194600 | K33: C-204, Parin Rakeshkumar Bodiwala | L33: 575674 | O33: A-604., Deepakkumar, Ruchika Arora | P33: 43000 | R33: A-604., Deepakkumar, Ruchika Arora | S33: 202000
B34: D/101, Parth Madaan | C34: 50000 | F34: K-403,Mahesh Madhukar Bharambe | G34: 0 | H34: 241500 | I34: 241500 | K34: C/502, Isha Nishant Bhavsar | L34: 592654 | O34: F-1003,Garima Rajawat & Jaisingh Sisodia | P34: 42000 | R34: F-1003,Garima Rajawat & Jaisingh Sisodia | S34: 198000
B35: D/102 Disha Bhagya Dave | C35: 50000 | F35: F-503, Sanjay Bhadra | G35: 0 | H35: 210666 | I35: 210666 | K35: C/503,Rajneesh Bakshi | L35: 341319 | O35: M/502 Javankiaben Koradiya, Naresh Koradiya | P35: 2200 | R35: M/502 Javankiaben Koradiya, Naresh Koradiya | S35: 169000
B36: D/1201 Shobhit Trapasiya | C36: 50000 | F36: F-801,Ashokkumar M.Sonagara | G36: 0 | H36: 138200 | I36: 138200 | K36: C-603,Umesh Shishivandan Pandya | L36: 617108 | O36: N-1103,Sumanta Bose | P36: 40000 | R36: N-1103,Sumanta Bose | S36: 187000
B37: D-1002, Kishorsinh Anopsinh Jadeja | C37: 50000 | F37: C-1003,Rahul Pandya | G37: 0 | H37: 217650 | I37: 217650 | K37: C/702 Taraben Vasantlal Jain, Jain Amrita | L37: 825410 | O37: F-204, Jaxnikumar Naik | P37: 30400 | R37: F-204, Jaxnikumar Naik | S37: 138400
B38: D-1204, Pravin Chaudhary & Geeta Chaudhary | C38: 50000 | F38: K/802,Vipul Kulshrestha | G38: 260717.7 | H38: 261600 | I38: 882.3 | K38: C-901,Placement & Consulting (Mohan Rohit) | L38: -620436 | O38: K/203, Priteshkumar P.Upadhyay, Paresh U | P38: 46000 | R38: K/203, Priteshkumar P.Upadhyay, Paresh U | S38: 215600
B39: D-1403,Jay Adthakkar | C39: 50000 | F39: B/1302 Karan Mehta | G39: 203587.7 | H39: 205000 | I39: 1412.3 | K39: D-1002, Kishorsinh Anopsinh Jadeja | L39: 611086 | O39: P-603, Rakesh Rathod | P39: 45500 | R39: P-603, Rakesh Rathod | S39: 215500
B40: D-301,Rajesh Vithaldas Chokshi | C40: 50000 | F40: F-203, Kalpesh Rohit Contractor & Nency Contractor | G40: 174417.7 | H40: 176200 | I40: 1782.3 | K40: D/101, Parth Madaan | L40: 565798 | O40: D-604, Kashyap Dave | P40: 36500 | R40: O-804,Rahulkumar Dharecha | S40: 170000
B41: D-304,Jinish Chimanbhai Patel | C41: 50000 | F41: C-1103, Sima Jigar Desai /Jigar S.Desai | G41: 0 | H41: 256000 | I41: 256000 | K41: D/102 Disha Bhagya Dave | L41: 38664 | O41: O-804,Rahulkumar Dharecha | P41: 36500 | R41: M/1004, Divya Tailor & Anurag Chhaparal | S41: 171300
B42: D-401, Bhartiben Mukeshbhai Halari / Dhaval Halari | C42: 50000 | F42: A-604., Deepakkumar, Ruchika Arora | G42: 0 | H42: 245000 | I42: 245000 | K42: D/1201 Shobhit Trapasiya | L42: 302539 | O42: M/1004, Divya Tailor & Anurag Chhaparal | P42: 37000 | R42: P-904, Niruben Soni, Mohit Soni | S42: 196000
B43: D-604, Kashyap Dave | C43: 50000 | F43: F-1003,Garima Rajawat & Jaisingh Sisodia | G43: 0 | H43: 240000 | I43: 240000 | K43: D-1204, Pravin Chaudhary & Geeta Chaudhary | L43: 34546 | O43: P-904, Niruben Soni, Mohit Soni | P43: 42000 | R43: P-503, Shekhar Mudaliar | S43: 180000
B44: D-902, Bhavna Vijay Jadav | C44: 50000 | F44: M/502 Javankiaben Koradiya, Naresh Koradiya | G44: 0 | H44: 171200 | I44: 171200 | K44: D-1303, Bharatkumar Khemnani | L44: 990100 | O44: P-503, Shekhar Mudaliar | P44: 38700 | R44: L-502, Shalabh Kaushik | S44: 219000
... B66: F-302,Jaimin Barot | C66: 50000 | F66: E-301, Vikramkumar | G66: 0 | H66: 208000 | I66: 208000 | K66: E-602, Dipak Singhal & Anchal Singhal | L66: 36840 | O66: (as per details) | P66: 48378 | R66: K-1202, Sagar Devajibhai Ladani | S66: 172000
B67: F-304, Ripal Vikash Jain (Ripal Bhatt) | C67: 50000 | F67: G-601, Hiren Darji | G67: 0 | H67: 197585 | I67: 197585 | K67: E-603,Yogita Amit Singhal | L67: 74256 | O67: A/702,Hemantkumar Ishvarlal Bhavsar | R67: K-702,Tapan Jayeshbhai Khimani | S67: 216000
B68: F-501,Maulikbhai Gondaliya | C68: 50000 | F68: K-402,Ravinjay Tiwari | G68: 0 | H68: 259600 | I68: 259600 | K68: E-701,Sanket Govinbhi Panchal | L68: 30527 | O68: CGST ON COLLECTION | R68: N-502, Sanjaykumar Mistry | S68: 138400
B69: F-503, Sanjay Bhadra | C69: 50000 | F69: K-1201, Riya Dasgupta | G69: 0 | H69: 219500 | I69: 219500 | K69: F-1002, Jigar J.Patel | L69: -265400 | O69: SGST ON COLLECTION | R69: M-801 Tarak B. Shah, Anjana Chauhan | S69: 160000
B70: F-703, Gaurav Sanjay Kankraj | C70: 50000 | F70: I-304, Mehulsinh Ranilsinh Rajput | G70: 263667.7 | H70: 265000 | I70: 1332.3 | K70: F-1003,Garima Rajawat & Jaisingh Sisodia | L70: 39880 | O70: A/701,Hemantkumar Ishwarlal Bhavsar | P70: 38116 | R70: K-104,Amogh Chitnis | S70: 172000
B71: F-801,Ashokkumar M.Sonagara | C71: 50000 | F71: A/702,Hemantkumar Ishvarlal Bhavsar | G71: 0 | H71: 212666 | I71: 212666 | K71: F-101, Jatin Prakash Gupta | L71: 211640 | O71: E-602, Dipak Singhal & Anchal Singhal | P71: 2200 | R71: I-301 Ankit Dharmendra Jani | S71: 195000
B72: F-802 ,Hemang Bharatbhai Ahya | C72: 50000 | F72: A/701,Hemantkumar Ishwarlal Bhavsar | G72: 0 | H72: 212666 | I72: 212666 | K72: F-104, Saurav Manibind | L72: 32828 | O72: B/503 Kishor M Bhatia | P72: 42500 | R72: M-203,Lokesh Bansilal Kalal | S72: 180550
B73: F-903,Krati Shrimali | C73: 50000 | F73: E-602, Dipak Singhal & Anchal Singhal | G73: 0 | H73: 185200 | I73: 185200 | K73: F-1101, Vijay Ojha | L73: 1354456 | O73: K-1202, Sagar Devajibhai Ladani | P73: 37000 | R73: N-202, Jaydevsinh Rana, Yuvraj Rana | S73: 182000
B74: F-904, Anuj Narayan Bhatt | C74: 50000 | F74: I-1104, Aashka Vivek Prajapati | G74: 0 | H74: 227000 | I74: 227000 | K74: F/1102,Meet Yogeshbhai Sheth | L74: 32828 | O74: K-702,Tapan Jayeshbhai Khimani | P74: 46000 | R74: O-703, Rahul M. Andharia | S74: 193000
B75: G/803 Jatin Maheshchandra Gujella | C75: 50000 | F75: B/503 Kishor M Bhatia | G75: 0 | H75: 240500 | I75: 240500 | K75: F-1201, Ashima Sehgal | L75: 26992 | O75: N-502, Sanjaykumar Mistry | P75: 30244 | R75: C-1303, Vikas Jain / Anamika Jain | S75: 189200
B76: G-1003, Parth Mathurbhai Dobariya | C76: 50000 | F76: K-1202, Sagar Devajibhai Ladani | G76: 0 | H76: 209000 | I76: 209000 | K76: F-1303, Shashank Chandraman Joshi | L76: 378614 | O76: M-801 Tarak B. Shah, Anjana Chauhan | P76: 34500 | R76: K-504,Udaykumar Vipinbhai Dave | S76: 220000
B77: G-1004, Sandeep Popat | C77: 50000 | F77: K-702,Tapan Jayeshbhai Khimani | G77: 0 | H77: 262000 | I77: 262000 | K77: F-202, Nandaben J. Parmar, Priyanka A. Chauhan | L77: 31290 | O77: K-104,Amogh Chitnis | P77: 37000 | R77: K-1204, Suman Mohanty | S77: 217300
B78: G-104, Daksha Rajeshbhai Darji | C78: 50000 | F78: N-502, Sanjaykumar Mistry | G78: 0 | H78: 168644 | I78: 168644 | K78: F-203, Kalpesh Rohit Contractor & Nency Contractor | L78: 35016 | O78: I-301 Ankit Dharmendra Jani | P78: 41700 | R78: D-1403,Jay Adthakkar | S78: 154100
B79: G-1203 Ravi Vijaykumar | C79: 50000 | F79: M-801 Tarak B. Shah, Anjana Chauhan | G79: 0 | H79: 194500 | I79: 194500 | K79: F-204, Jaxnikumar Naik | L79: 28360 | O79: M-203,Lokesh Bansilal Kalal | P79: 38840 | R79: J-604,Anil Jayantilal Dave | S79: 172000
B80: G-1302, Vishal Kumar Gupta | C80: 50000 | F80: K-104,Amogh Chitnis | G80: 207617.7 | H80: 209000 | I80: 1382.3 | K80: F-301,Mukund Asati | L80: 2376960 | O80: N-202, Jaydevsinh Rana, Yuvraj Rana | P80: 39220 | R80: K-604,Bhavika & Vijay Parshotambhai Patel | S80: 216920
B81: G-204, Deepakkumar Bhanwarlal Mewara | C81: 50000 | F81: I-301 Ankit Dharmendra Jani | G81: 235187.7 | H81: 236700 | I81: 1512.3 | K81: F-302,Jaimin Barot | L81: 305068 | O81: O-703, Rahul M. Andharia | P81: 41500 | R81: F-304, Ripal Vikash Jain (Ripal Bhatt) | S81: 174000
... B90: H-202, Vinod Govindbhai Darji | C90: 50000 | F90: K-604,Bhavika & Vijay Parshotambhai Patel | G90: 0 | H90: 218920 | I90: 218920 | K90: F-802 ,Hemang Bharatbhai Ahya | L90: 43564 | O90: (as per details) | P90: 44500 | R90: D/101, Parth Madaan | S90: 163000
B91: H-204, Riya Agarwal / Mayank Singhal | C91: 50000 | F91: F-304, Ripal Vikash Jain (Ripal Bhatt) | G91: 0 | H91: 211000 | I91: 211000 | K91: F-903,Krati Shrimali | L91: 313423 | O91: I-304, Mehulsinh Ranilsinh Rajput | R91: F-903,Krati Shrimali | S91: 197767
B92: H-304, Prakashchandra Tiwari | C92: 50000 | F92: J-502,Ronak N. Parikh | G92: 0 | H92: 225000 | I92: 225000 | K92: F-904, Anuj Narayan Bhatt | L92: 313422 | O92: CGST ON COLLECTION | R92: F-904, Anuj Narayan Bhatt | S92: 197767
B93: H-502,Avisha Chintan Shah | C93: 50000 | F93: E-303, Rajendrakumar M.Jobanputra | G93: 175112.7 | H93: 176500 | I93: 1387.3 | K93: G-1003, Parth Mathurbhai Dobariya | L93: 32332 | O93: SGST ON COLLECTION | R93: G-1203 Ravi Vijaykumar | S93: 162500
B94: H-601,Rohit Kumar / Kumari Sonalisa | C94: 50000 | F94: H-204, Riya Agarwal / Mayank Singhal | G94: 0 | H94: 195000 | I94: 195000 | K94: G-1004, Sandeep Popat | L94: 28269 | O94: E-301, Vikramkumar | P94: 50000 | R94: P-201,Haum Dutt Gautam | S94: 214000
B95: H-602, Harish Parmar | C95: 50000 | F95: F-1201, Ashima Sehgal | G95: 0 | H95: 136200 | I95: 136200 | K95: G-101, Darji Amit Gunvantbhai | L95: -218700 | O95: J-502,Ronak N. Parikh | P95: 39500 | R95: D-604, Kashyap Dave | S95: 170000
B96: H-703, Pragneshkumar Thakker, | C96: 50000 | F96: H/1302,Yogesh Harikrishna Ardeshna | G96: 200908.85 | H96: 201000 | I96: 91.15 | K96: G-104, Daksha Rajeshbhai Darji | L96: 710266 | O96: E-303, Rajendrakumar M.Jobanputra | P96: 31500 | R96: C-1302,Chintankumar B. Patel | S96: 216000
B97: H-704. Pinkesh M. Mehta / Jaimini P.Mehta | C97: 50000 | F97: I-1304,Ruturaj Bhanvaidya | G97: 0 | H97: 252500 | I97: 252500 | K97: G-1101; Nikul Dashrathbhai Soni | L97: 198020 | O97: H-204, Riya Agarwal / Mayank Singhal | P97: 34500 | R97: N-304; Amarjit Kumar | S97: 165500
B98: H-902, Rajkumar Rao | C98: 50000 | F98: H-202, Vinod Govindbhai Darji | G98: 0 | H98: 198000 | I98: 198000 | K98: G-1203 Ravi Vijaykumar | L98: 548587 | O98: F-1201, Ashima Sehgal | P98: 2200 | R98: J-603,Hriday Abilas Ghoda | S98: 181000
B99: I-1004,Pruthvik Balshekhar Warrier | C99: 50000 | F99: D/101, Parth Madaan | G99: 0 | H99: 198000 | I99: 198000 | K99: G-1302, Vishal Kumar Gupta | L99: 39757 | O99: H/1302,Yogesh Harikrishna Ardeshna | P99: 43000 | R99: G-1302, Vishal Kumar Gupta | S99: 172000
B100: I-1102, Dhruv Manishbhai Shah & Bhavikaben M. | C100: 50000 | F100: F-903,Krati Shrimali | G100: 0 | H100: 199967 | I100: 199967 | K100: G-201, Mahendrabhai Shukla | L100: 3500002 | O100: I-1304,Ruturaj Bhanvaidya | P100: 44500 | R100: O-701, Harshil Vipiulbhai Chandarana | S100: 164000
B101: I-1103,Nikunjbhai Rameshbhai Kagathara | C101: 50000 | F101: F-904, Anuj Narayan Bhatt | G101: 0 | H101: 240045 | I101: 240045 | K101: G-204, Deepakkumar Bhanwarlal Mewara | L101: 34654 | O101: H-202, Vinod Govindbhai Darji | P101: 35000 | R101: L-904,Nikhil Upendra Thakkar | S101: 217000
B102: I-1104, Aashka Vivek Prajapati | C102: 50000 | F102: P-201,Haum Dutt Gautam | G102: 0 | H102: 259500 | I102: 259500 | K102: G-502, Prakash Chandra Mishra / Sauravini Mishra | L102: 1567078 | O102: D/101, Parth Madaan | P102: 35000 | R102: F-104, Saurav Manibind | S102: 163000
B103: I-1202, Pratik Ratilal Joshi | C103: 50000 | F103: G-1203 Ravi Vijaykumar | G103: 0 | H103: 197500 | I103: 197500 | K103: G-503,Sukhdevsingh | L103: 34408 | O103: F-903,Krati Shrimali | P103: 2200 | R103: A-902, Puja Chudasama | S103: 186500
B104: I-1203,Gopal Jiva/ Harjivan G / Dilip G.Jiva | C104: 50000 | F104: C-1302,Chintankumar B. Patel | G104: 0 | H104: 262000 | I104: 262000 | K104: G-601, Hiren Darji | L104: 32822 | O104: F-904, Anuj Narayan Bhatt | P104: 42278 | R104: G-802,Prakashchandra B. Joshi | S104: 171500
B105: I-1304,Ruturaj Bhanvaidya | C105: 50000 | F105: N-304; Amarjit Kumar | G105: 0 | H105: 201770 | I105: 201770 | K105: G-603, Nitin Raghunath Devle | L105: 39698 | O105: G-1203 Ravi Vijaykumar | P105: 35000 | R105: O-203, Manish Kumar Gupta | S105: 171500
... B140: K-104,Amogh Chitnis | C140: 50000 | F140: I-504,Devam Kashyapbhai Pandya | G140: 0 | H140: 209000 | I140: 209000 | K140: I-504,Devam Kashyapbhai Pandya | L140: 34654 | O140: (as per details) | P140: 30833 | R140: P-1001, Samruddhi & Sandeep Mekde | S140: 184000
B141: K-1104, Vineet Abbhi | C141: 50000 | F141: H-902, Rajkumar Rao | G141: 0 | H141: 199453 | I141: 199453 | K141: I-603,Mamtaben Champaklal Soni | L141: 75758 | O141: E-701,Sanket Govinbhi Panchal | R141: K-602, Kishor Devshibhai Vagh | S141: 210700
B142: K-1201, Riya Dasgupta | C142: 50000 | F142: O-803, Rahul M.Andharia | G142: 0 | H142: 229500 | I142: 229500 | K142: I-701, Narendra Hanumant Jog | L142: -289100 | O142: CGST ON COLLECTION | R142: M-302 Ashishkumar Ramnareshsingh Parihar | S142: 167278
B143: K-1202, Sagar Devajibhai Ladani | C143: 50000 | F143: J-1104, Hiralal Kushwaha & Roopa Kushwaha | G143: 0 | H143: 242500 | I143: 242500 | K143: I-702, Tushar Singh | L143: -260700 | O143: SGST ON COLLECTION | R143: B/101, Ankur Sanghvi | S143: 198000
B144: K-1204, Suman Mohanty | C144: 50000 | F144: N-1003, Neil Michael | G144: 0 | H144: 259420 | I144: 259420 | K144: I-703,Samir Suryakant Pallav | L144: 27964 | O144: E-701,Sanket Govinbhi Panchal | P144: 32833 | R144: L-1001, Krushnadas Manvar | S144: 207700
B145: K-1303, Unnati Manubhai Chitroda | C145: 50000 | F145: L-1101,Pratapsingh | G145: 260567.7 | H145: 261443 | I145: 875.3 | K145: I-801, Richa Sharma | L145: 43838 | O145: E-701,Sanket Govinbhi Panchal | P145: 151100 | R145: F-703, Gaurav Sanjay Kankraj | S145: 166100
B146: K-202,Chinjal Lalitkumar Modi | C146: 50000 | F146: K,503 Ishwar Harjibhai Kanjariya | G146: 260717.7 | H146: 262000 | I146: 1282.3 | K146: I-804,Anish Mahendra Bhatt & Maya A.Bhatt | L146: 518429 | O146: G-901, Govindbhai Rajabhai Dhariaparmar | P146: 35000 | R146: B-1303,Manan M.Desai /Vandana M.Desai | S146: 83035
B147: K-402,Ravinjay Tiwari | C147: 50000 | F147: L-304, Deepa Mayank Parekh | G147: 0 | H147: 263100 | I147: 263100 | K147: I-901, Shivam Thakur | L147: 0 | O147: F/1102,Meet Yogeshbhai Sheth | P147: 35200 | R147: D-304,Jinish Chimanbhai Patel | S147: 191500
B148: K-403,Mahesh Madhukar Bharambe | C148: 50000 | F148: L-401,Sunil Dineshchandra Manjrawala | G148: 0 | H148: 262500 | I148: 262500 | K148: I-902, Nilesh Odedara | L148: 39930 | O148: H-703, Pragneshkumar Thakker, | P148: 35470 | R148: C-101, Shivam Thakore | S148: 201100
B149: K-501,Vivek Goad / Raksha Sharma | C149: 50000 | F149: SH.04, Gauriben B. Makwana,Bhavin B. Dalwadi | G149: 0 | H149: 321800 | I149: 321800 | K149: J-1003,Jagdish Pankajkumar Patel | L149: 151930 | O149: O/903 Rahul / Mahendra N.Andharia | P149: 34500 | R149: H-102, Sakshi Sachin Kapoor | S149: 163000
B150: K-504,Udaykumar Vipinbhai Dave | C150: 50000 | F150: SH-305,Jitesh Maganlal Shah | G150: 0 | H150: 162880 | I150: 162880 | K150: J-1004, Dipesh Bharartbhai Pandya | L150: -46400 | O150: I-504,Devam Kashyapbhai Pandya | P150: 37000 | R150: P-1204,Lokesh Manilal Suthar | S150: 188900
B151: K-601, Harshad Jain | C151: 50000 | F151: SHOP 211 Vishnu Rao After Bu | G151: 0 | H151: 171800 | I151: 171800 | K151: J-1101, Roopesh Kushwaha / Shefali Kushwaha | L151: 333292 | O151: H-902, Rajkumar Rao | P151: 35463 | R151: C/1001 Divyeshkumar Navnitlal Panchal | S151: 208360
B152: K-602, Kishor Devshibhai Vagh | C152: 50000 | F152: P-1001, Samruddhi & Sandeep Mekde | G152: 0 | H152: 224000 | I152: 224000 | K152: J-1103, Zinkal Siddhath Kinariwala | L152: 41164 | O152: J-1104, Hiralal Kushwaha & Roopa Kushwaha | P152: 42500 | R152: A-1301, Aniruddha Dutta | S152: 50000
B153: K-604,Bhavika & Vijay Parshotambhai Patel | C153: 50000 | F153: K-602, Kishor Devshibhai Vagh | G153: 0 | H153: 255700 | I153: 255700 | K153: J-1104, Hiralal Kushwaha & Roopa Kushwaha | L153: 40312 | O153: N-1003, Neil Michael | P153: 44000 | R153: J-802, Rushabh Shah | S153: 191500
B154: K-701, Amita Kamlesh Soni | C154: 50000 | F154: E-102,Rajubhai Gohel | G154: 0 | H154: 232500 | I154: 232500 | K154: J-1201, Uma Nath Trpathi | L154: 395050 | O154: L-1101,Pratapsingh | P154: 45973 | R154: H-704. Pinkesh M. Mehta / Jaimini P.Mehta | S154: 163100
B155: K-702,Tapan Jayeshbhai Khimani | C155: 50000 | F155: M-302 Ashishkumar Ramnareshsingh Parihar | G155: 0 | H155: 203416 | I155: 203416 | K155: J-1203, Hitesh P.Lumbhani | L155: 43564 | O155: K,503 Ishwar Harjibhai Kanjariya | P155: 216000 | R155: A-502, Brajesh Kumar / Shalini Bhardwaj | S155: 189100
... B208: P-101, Rahul Ranjan | C208: 50000 | F208: P-302,Vidhyarth Shankar | G208: 0 | H208: 224900 | I208: 224900 | K208: L-304, Deepa Mayank Parekh | L208: 50868 | O208: (as per details) | P208: 39910 | R208: N-1001, Vikash Mtta | S208: 168500
B209: P-103, Raj Manishbhi Parikh | C209: 50000 | F209: K-601, Harshad Jain | G209: 0 | H209: 225000 | I209: 225000 | K209: L-401,Sunil Dineshchandra Manjrawala | L209: 183658 | O209: I-1103,Nikunjbhai Rameshbhai Kagathara | R209: H-304, Prakashchandra Tiwari | S209: 166100
B210: P-1101, Premlata & Chandra Prakash Salgia (AB) | C210: 50000 | F210: M/1304, Rajvi R.Chalishazar & Hardik N. Radia | G210: 0 | H210: 208300 | I210: 208300 | K210: L-502, Shalabh Kaushik | L210: 44060 | O210: CGST ON COLLECTION | R210: A-801; Ishwar S. Dubey | S210: 204000
B211: P-1204,Lokesh Manilal Suthar | C211: 50000 | F211: K-1104, Vineet Abbhi | G211: 0 | H211: 259500 | I211: 259500 | K211: L-504, Raguvirsingh Hardesingh Vaghela | L211: 296040 | O211: SGST ON COLLECTION | R211: N-104, Shital Kalpeshbhai Ajmera | S211: 139500
B212: P-201,Haum Dutt Gautam | C212: 50000 | F212: I-902, Nilesh Odedara | G212: 0 | H212: 239700 | I212: 239700 | K212: L-604, Akash Vnod Bhatt / Indiraben Bhatt | L212: 1089108 | O212: I-1103,Nikunjbhai Rameshbhai Kagathara | P212: 42000 | R212: F-501,Maulikbhai Gondaliya | S212: 135400
B213: P-204, Nikita Anil Bendre | C213: 50000 | F213: O-404, Dilip Narsinhbhai Ghedia | G213: 0 | H213: 201581 | I213: 201581 | K213: L-704,Yogendra Kumar Tailor | L213: 395050 | O213: O-801;Amit Kumar | P213: 34600 | R213: B-802, Alpesh Rambhai Khatri | S213: 198000
B214: P-302,Vidhyarth Shankar | C214: 50000 | F214: J/501 Mayank Agrawal | G214: 0 | H214: 239682 | I214: 239682 | K214: L-801, Kajal M. Mishra | L214: 40176 | O214: N-503, Yash Satwani / Kiran Satwani | P214: 30000 | R214: M-104, Nishith N. Shah & Rimaben Shah | S214: 193500
B215: P-304; Rupal Vishal Barad | C215: 50000 | F215: N-1001, Vikash Mtta | G215: 0 | H215: 204500 | I215: 204500 | K215: L-803, Haresh Zanzrukia | L215: 0 | O215: A-1304, Palak Harshadkumar Popat | P215: 40800 | R215: I-603,Mamtaben Champaklal Soni | S215: 174000
B216: P-402,Chandan Kumar Sharma | C216: 50000 | F216: H-304, Prakashchandra Tiwari | G216: 0 | H216: 202100 | I216: 202100 | K216: L-804, Anand Sharma | L216: 2690100 | O216: K-1002, Deepakkumar Shantilal Kamani | P216: 34000 | R216: K/303 Jaykumar Raval | S216: 195600
B217: P-503, Shekhar Mudaliar | C217: 50000 | F217: A-801; Ishwar S. Dubey | G217: 0 | H217: 247500 | I217: 247500 | K217: L-904,Nikhil Upendra Thakkar | L217: 43837 | O217: J-902,Om Vikramkumar Popat | P217: 30500 | R217: M-1104,Prabhat Soni | S217: 215600
B218: P-603, Rakesh Rathod | C218: 50000 | F218: F-501,Maulikbhai Gondaliya | G218: 0 | H218: 165100 | I218: 165100 | K218: M/1004, Divya Tailor & Anurag Chhaparal | L218: 34607 | O218: J-902,Om Vikramkumar Popat | P218: 50000 | R218: I-404,Neha Rajesh Bharti | S218: 215600
B219: P-704; Vishal Rajabhai Barad | C219: 50000 | F219: B-802, Alpesh Rambhai Khatri | G219: 0 | H219: 240000 | I219: 240000 | K219: M-104, Nishith N. Shah & Rimaben Shah | L219: 39096 | O219: J-704,Meghana Soni | P219: 2200 | R219: D-904, Parth Dipakbhai Solanki | S219: 157000
B220: P-904, Niruben Soni, Mohit Soni | C220: 50000 | F220: M-104, Nishith N. Shah & Rimaben Shah | G220: 0 | H220: 235200 | I220: 235200 | K220: M-1104,Prabhat Soni | L220: 43564 | O220: P-302,Vidhyarth Shankar | P220: 39800 | R220: K/302, Soumendrakumar Behera | S220: 219000
B221: SH.04, Gauriben B. Makwana,Bhavin B. Dalwadi | C221: 50000 | F221: I-603,Mamtaben Champaklal Soni | G221: 0 | H221: 176000 | I221: 176000 | K221: M/1304, Rajvi R.Chalishazar & Hardik N. Radia | L221: 34607 | O221: K-601, Harshad Jain | P221: 39800 | R221: D/102 Disha Bhagya Dave | S221: 191400
B222: SH-20,Pukhraj Sankalram Kumhar/Ambika Kitchen Ware | C222: 50000 | F222: D-904, Parth Dipakbhai Solanki | G222: 0 | H222: 191000 | I222: 191000 | K222: M-203,Lokesh Bansilal Kalal | L222: 552235 | O222: M/1304, Rajvi R.Chalishazar & Hardik N. Radia | P222: 37000 | R222: H/1004, Suchi Khare, Saket Khare | S222: 136400
B223: SH-305,Jitesh Maganlal Shah | C223: 50000 | F223: K/303 Jaykumar Raval | G223: 0 | H223: 237500 | I223: 237500 | K223: M-204, Vishak Raval | L223: 3267328 | O223: I-1203,Gopal Jiva/ Harjivan G / Dilip G.Jiva | P223: 42000 | R223: P-1101, Premlata & Chandra Prakash Salgia (AB) | S223: 133200
B224: SHOP 211 Vishnu Rao After Bu | C224: 50000 | F224: M-1104,Prabhat Soni | G224: 0 | H224: 261600 | I224: 261600 | K224: M-302 Ashishkumar Ramnareshsingh Parihar | L224: 33800 | O224: K-1104, Vineet Abbhi | P224: 45500 | R224: J-1004, Dipesh Bharartbhai Pandya | S224: 217300
C225: =SUM(C2:C224) | F225: I-404,Neha Rajesh Bharti | G225: 0 | H225: 217800 | I225: 217800 | K225: M-303,Shital Satyen Sheth | L225: 497245 | O225: I-902, Nilesh Odedara | P225: 42000 | R225: Shop 310 Kokila Desai After Bu | S225: 109100
F226: D/102 Disha Bhagya Dave | G226: 0 | H226: 232400 | I226: 232400 | K226: M-304, Nikhil Bhimji Padhiyar | L226: 0 | O226: O-404, Dilip Narsinhbhai Ghedia | P226: 35770 | R226: G-503,Sukhdevsingh | S226: 170300
F227: H/1004, Suchi Khare, Saket Khare | G227: 0 | H227: 138600 | I227: 138600 | K227: M-402,Bhumika Akashdeep Kadiya | L227: -218650 | O227: J/501 Mayank Agrawal | P227: 42217 | R227: I-302,Asish Mansukhlal Ajmera | S227: 171700
F228: P-1101, Premlata & Chandra Prakash Salgia (AB) | G228: 0 | H228: 162390 | I228: 162390 | K228: M-403,Bhumika Akashdeep Kadiya | L228: -168650 | O228: N-1001, Vikash Mtta | P228: 36000
F229: K-801, Viral Bhayani | G229: 0 | H229: 179000 | I229: 179000 | K229: M-404, Mahavir Bhagwanjibhai Jadav | L229: 45476 | O229: H-304, Prakashchandra Tiwari | P229: 36000
F230: N-101,Abhishek Rajguru | G230: 0 | H230: 214100 | I230: 214100 | K230: M/502 Javankiaben Koradiya, Naresh Koradiya | L230: 549803 | O230: A-801; Ishwar S. Dubey | P230: 43500
F231: J-1004, Dipesh Bharartbhai Pandya | G231: 0 | H231: 263700 | I231: 263700 | K231: M-801 Tarak B. Shah, Anjana Chauhan | L231: 32227 | O231: F-501,Maulikbhai Gondaliya | P231: 29700
F232: I-701, Narendra Hanumant Jog | G232: 0 | H232: 239100 | I232: 239100 | K232: M-803, Shital Satyen Sheth | L232: 497245 | O232: B-802, Alpesh Rambhai Khatri | P232: 42000
...

Sheet SUN REALTY ATMOS-CALC
A1: Sun Realty Atmosphere
A4: GST PAYABLE ON COMMERCIAL CONSTRUCTION FOR THE MONTH OF AUG-26
A6: Supply | B6: AMOUNT | C6: RATE | D6: CGST | E6: SGST | F6: TOTAL
A8: SUN REALTY ATMOSPHERE RESIDENTIAL | B8: ='SUN REALTY ATMOS-MEMBERS COLL'!V66 | C8: 0.01 | D8: =+B8*C8/2 | E8: =+D8 | F8: =+D8+E8
A9: Less : Refund | B9: =+-'SUN REALTY ATMOS-MEMBERS COLL'!M66 | C9: 0.01 | D9: =+B9*C9/2 | E9: =+D9 | F9: =+D9+E9
A10: Less : Refund (GST PAID @1% INSTEAD OF 18%)
A11: Less: F-1101, Vijay Ojha [ Tax on the same has been already paid in mar'25, hence reversed] | C11: 0.01 | D11: =+B11*C11/2 | E11: =+D11 | F11: =+D11+E11
A12: AS PER RECO | C12: 0.01 | D12: =+B12*C12/2 | E12: =D12 | F12: =+D12+E12
C13: 0.01 | E13: =D13 | F13: =D13+E13
A15: TOTAL @ 1% | B15: =SUM(B8:B13) | D15: =SUM(D8:D13) | E15: =SUM(E8:E13) | F15: =SUM(F8:F13)
A17: Add:- PLC Amount Received | C17: 0.18 | D17: =B17*C17/2 | E17: =B17*C17/2 | F17: =+D17+E17
B18: 0 | C18: 0.18 | D18: =B18*C18/2 | E18: =B18*C18/2 | F18: =+D18+E18
C19: 0.18 | D19: =B19*C19/2 | E19: =B19*C19/2 | F19: =+D19+E19
A20: TOTAL @ 18% | B20: =SUM(B17:B19) | D20: =SUM(D17:D19) | E20: =SUM(E17:E19) | F20: =SUM(F17:F19)
A22: SUN REALTY ATMOSPHERE RESIDENTIAL ( Sale Deed More Than 45 Lakhs ) | B22: =+'SUN REALTY ATMOS-MEMBERS COLL'!V78 | C22: 0.05 | D22: =+B22*C22/2 | E22: =+D22 | F22: =+D22+E22
A23: Less : Refund @5% | B23: =-'SUN REALTY ATMOS-MEMBERS COLL'!I78 | C23: 0.05 | D23: =B23*C23/2 | E23: =B23*C23/2 | F23: =+D23+E23
A24: TOTAL @ 5% | B24: =SUM(B22:B23) | D24: =SUM(D22:D23) | E24: =SUM(E22:E23) | F24: =SUM(F22:F23)
A26: SUN REALTY ATMOSPHERE COMMERCIAL | B26: ='SUN REALTY ATMOS-MEMBERS COLL'!V104+B82 | C26: 0.05 | D26: =B26*C26/2 | E26: =+D26 | F26: =+D26+E26
A27: Less : Refund | B27: =-'SUN REALTY ATMOS-MEMBERS COLL'!M104-'SUN REALTY ATMOS-MEMBERS COLL'!I104 | C27: 0.05 | D27: =B27*C27/2 | E27: =B27*C27/2 | F27: =+D27+E27
C28: 0.05
C29: 0.05 | D29: =B29*C29/2 | E29: =B29*C29/2 | F29: =+D29+E29
A30: TOTAL @ 5% | B30: =SUM(B26:B29) | D30: =SUM(D26:D29) | E30: =SUM(E26:E29) | F30: =SUM(F26:F29)
A32: TOTAL | B32: =+B15+B20+B24+B30 | D32: =+D15+D20+D24+D30 | E32: =+E15+E20+E24+E30 | F32: =+F15+F20+F24+F30
A34: After BU sale deed Exempt sale | B34: 0
A37: Supply | B37: AMOUNT | C37: RATE | D37: CGST | E37: SGST | F37: TOTAL
A38: TAXABLE VALUE @18% | C38: 0.18 | D38: =B38*C38/2 | E38: =+D38 | F38: =+D38+E38
A39: TAXABLE VALUE @5% | C39: 0.05 | D39: =B39*C39/2 | E39: =+D39 | F39: =+D39+E39
A40: TAXABLE VALUE @1% | C40: 0.01 | D40: =B40*C40/2 | E40: =+D40 | F40: =+D40+E40
A41: TOTAL | B41: =SUM(B38:B40) | D41: =SUM(D38:D40) | E41: =SUM(E38:E40) | F41: =+D41+E41 | H41: =8608-3304
A43: GST PAYABLE UNDER RCM FOR THE MONTH OF AUG-26
A45: Service | B45: AMOUNT | C45: RATE | D45: CGST | E45: SGST | F45: TOTAL
A47: SUN REALTY ATMOSPHERE
A48: Advocate fees | C48: 0.18 | D48: =+B48*9/100 | E48: =+D48 | F48: =+D48+E48
A49: Carting and Transportation (Gayatri Sales Corp & Ashokji Vanzara, mahesh v zamada) | B49: 0 | C49: 0.05 | D49: =+B49*0.025 | E49: =+D49 | F49: =+D49+E49
A50: Security Services | B50: 0 | C50: 0.18 | D50: =+B50*9% | E50: =+B50*9% | F50: =SUM(D50:E50)
A51: Royalty Expenses | B51: 0 | C51: 0.18 | D51: =+B51*9% | E51: =+B51*9% | F51: =SUM(D51:E51)
A53: TOTAL | B53: =SUM(B47:B52) | D53: =SUM(D47:D52) | E53: =SUM(E47:E52) | F53: =SUM(F47:F52)
A55: INELIGIBLE CREDIT FOR THE MONTH OF AUG-26
A57: PARTICULARS | B57: CGST | C57: SGST | D57: IGST
A59: ITC FOR THE AUG-26 | B59: 0 | C59: =B59 | D59: 0
A60: Add: Ineligible ITC (whole year adjustment)
A61: Add: Ineligible ITC For RCM | B61: =+D53 | C61: =+E53
A62: Total ineligible CENVAT | B62: =SUM(B59:B61) | C62: =SUM(C59:C61) | D62: =SUM(D59:D59)
A63: TOTAL | B63: =SUM(B62:B62) | C63: =SUM(C62:C62) | D63: =SUM(D62:D62)
A66: GST Payable for the month of AUG-26
A68: PARTICULARS | B68: CGST | C68: SGST | D68: TOTAL
A70: =+A8 | B70: =+D32 | C70: =+E32 | D70: =+F32
A72: TOTAL PAYABLE FOR RESIDENTIAL INCLUDING IGST | B72: =+B70+B71 | C72: =+C70+C71 | D72: =+D70+D71
A74: GST UNDER RCM
A75: SUN ATMOSPHERE | B75: =D49+D50+D48+D51 | C75: =B75 | D75: =+B75+C75
A76: SUN OFFICE | D76: =+B76+C76
A77: GST Payable | B77: =+B72+B75+B76 | C77: =+C72+C75+C76 | D77: =+D72+D75+D76
A78: Net GST Payable | B78: =+B77 | C78: =+C77 | D78: =+D77
A92: =+'SUN REALTY ATMOS-MEMBERS COLL'!B112

Sheet SUN REALTY FOOTPRINT- MEMBERS
A1: Sun Realty
A4: CALCULATION For the month of AUG-26
A6: MEMBERS COLLECTION
A7: Flat No. | B7: Name of Owner | C7: CR SIDE | D7: Receipt of Registration Fees/JV / REFUNDABLE(Cr) | E7: Payment of Reg Fees on Behalf of Client / JV REFUNDABLE (Dr) | F7: Receipt of Stamp Duty/JV (Cr) | G7: Payment of Stamp Duty/JV (Dr) | H7: cheque withdrawn | I7: REFUND OF SAME PEROID WITH GST | J7: REFUND WITHOUT GST | L7: AEC,AUDA JV | M7: NET RECEIPT | N7: cgst
K8: Payment for Cancellation of unit /Reg fee/Stamp Duty
A9: A/0104 | B9: A-104,Gautam Prakash Narayan , Ragini Gautam | C9: 864614.7 | E9: =+D9 | F9: 255702.7 | G9: =+F9 | M9: =C9-D9-F9-H9 | N9: =M9*0.5/100
A10: A/0301 | B10: A-301, Savitaben Mohanbhai Maheriya | C10: 455446 | E10: =+D10 | G10: =F10 | H10: 0 | M10: =C10-D10-F10-H10 | N10: =M10*0.5/100
A11: A/0401 | B11: A/401, Nishaben Pragnesh Modi | C11: 179286.7 | E11: =+D11 | F11: 179286.7 | G11: =F11 | M11: =C11-D11-F11-H11 | N11: =M11*0.5/100
A12: A/0501 | B12: A/501, Ashviniben Rameshbhai Kanzariya | C12: 171735.7 | E12: =+D12 | F12: 171735.7 | G12: =F12 | M12: =C12-D12-F12-H12 | N12: =M12*0.5/100
A13: A/0602 | B13: A-602, Pratik Dipak Shah | C13: 42884.75 | E13: =+D13 | F13: 42885 | G13: =F13 | M13: =C13-D13-F13-H13 | N13: =M13*0.5/100
A14: A/0603 | B14: A-603, Mohitkumar J.Agravat / Anjali M.Agravat | C14: 489952 | E14: =+D14 | G14: =F14 | M14: =C14-D14-F14-H14 | N14: =M14*0.5/100
A15: A/0902 | B15: A-902, Yogina Tripathi /Sanjay Tripathi | C15: 1980198 | E15: =+D15 | G15: =F15 | M15: =C15-D15-F15-H15 | N15: =M15*0.5/100
A16: A/1001 | B16: A/1001 Reena Dadlani | C16: 264096 | E16: =+D16 | F16: =239096+25000 | G16: 239096 | M16: =C16-D16-F16-H16 | N16: =M16*0.5/100
A17: A/1304 | B17: A1304, Mohit Raja | C17: 792080 | E17: =+D17 | G17: =F17 | M17: =C17-D17-F17-H17 | N17: =M17*0.5/100
A18: B/0203 | B18: B-203, Shubham Alkeshbhai Gohel | C18: 434908 | E18: =+D18 | G18: =F18 | M18: =C18-D18-F18-H18 | N18: =M18*0.5/100
A19: B/0504 | B19: B/504, Prakashnath Devnath Jogi | C19: 311477 | D19: =25000+43715 | E19: =+D19 | F19: 201955 | G19: =+F19 | M19: =C19-D19-F19-H19 | N19: =M19*0.5/100
A20: B/0601 | B20: B-601, Umeshkumar Hargovanbhai Kadiya | C20: 1010615.7 | E20: =+D20 | F20: 264963.7 | G20: =F20 | M20: =C20-D20-F20-H20 | N20: =M20*0.5/100
A21: C/0101 | B21: C-101, Sangita Pankaj Sharma | C21: 242535 | D21: =2500+25000 | E21: =+D21 | F21: =184310 | G21: =F21 | M21: =C21-D21-F21-H21 | N21: =M21*0.5/100
A22: C/0401 | B22: C-401,Manoj Dayaram Khanchandani | C22: 638164 | E22: =+D22 | G22: =F22 | M22: =C22-D22-F22-H22 | N22: =M22*0.5/100
A23: C/0402 | B23: C402,Mukeshkumar, Mamta | C23: 236257.7 | D23: 40968.85 | E23: =+D23 | F23: 195288.85 | G23: =F23 | M23: =C23-D23-F23-H23 | N23: =M23*0.5/100
A24: C/0403 | B24: C-403,Ravi D.Labana & Dashrathbhai P. Labana | C24: 20792 | E24: =+D24 | G24: =F24 | M24: =C24-D24-F24-H24 | N24: =M24*0.5/100
A25: C/0601 | B25: C-601,Hiral DInesh Madhu /Manan K.Shah | C25: 475248 | E25: =+D25 | G25: =F25 | M25: =C25-D25-F25-H25 | N25: =M25*0.5/100
A26: C/0604 | B26: C-604, Ganesh Mahto | C26: 218940.7 | D26: 218940.7 | E26: =+D26 | G26: =F26 | M26: =C26-D26-F26-H26 | N26: =M26*0.5/100
A27: C/0704 | B27: C704, Dhanjani Honey / Hemani Mayur Nileshbhai | C27: 588388 | E27: =+D27 | G27: =F27 | M27: =C27-D27-F27-H27 | N27: =M27*0.5/100
A28: C/0803 | B28: C-803, Bhargav Amrishbhai Ubhadiya | C28: 495050 | E28: =+D28 | G28: =F28 | M28: =C28-D28-F28-H28 | N28: =M28*0.5/100
A29: C/0804 | B29: C-804, Shilpi Neeraj Sharma, Neeraj Shamra | C29: 27094.75 | D29: 27094.75 | E29: =+D29 | G29: =F29 | M29: =C29-D29-F29-H29 | N29: =M29*0.5/100
A30: C/0901 | B30: C/901, Rajeshkumar Pandya | C30: 490243 | D30: =25000+42352 | E30: =+D30 | F30: 195277 | G30: =F30 | I30: 113807 | M30: =C30-D30-F30-H30 | N30: =M30*0.5/100
A31: C/1003 | B31: C-1003,Kanika J.Mahadevwala | C31: 35174.75 | D31: 35174.75 | E31: =+D31 | G31: =F31 | M31: =C31-D31-F31-H31 | N31: =M31*0.5/100
A32: C/1101 | B32: C-1101, Harikrishna Madhu | C32: 222092.7 | D32: 222092.7 | E32: =+D32 | G32: =F32 | M32: =C32-D32-F32-H32 | N32: =M32*0.5/100
A33: C/1302 | B33: C-1302, Ishita Purohit | C33: 579208 | E33: =+D33 | G33: =F33 | M33: =C33-D33-F33-H33 | N33: =M33*0.5/100
A34: C/1403 | B34: C-1403, Rekhaben Hiteshkumar Agrawal | C34: 184377.7 | D34: 184377.7 | E34: =+D34 | G34: =F34 | M34: =C34-D34-F34-H34 | N34: =M34*0.5/100
A35: D/0301 | B35: D-301, Arunkumar Kamat & Puja Kumari | C35: 241183.7 | D35: 241183.7 | E35: =+D35 | G35: =F35 | M35: =C35-D35-F35-H35 | N35: =M35*0.5/100
A36: D/0302 | B36: D-302,Ashokkumar Kamat | C36: 235141.7 | D36: 40778.85 | E36: =+D36 | F36: 194362.85 | G36: =F36 | M36: =C36-D36-F36-H36 | N36: =M36*0.5/100
A37: D/0303 | B37: D-303, Sanjaykumar R. Patel & Sunitaben S.Patel | C37: 2189128.7 | D37: =169955.7+31116 | E37: =+D37 | F37: 140216 | G37: =F37 | I37: 613901 | M37: =C37-D37-F37-H37 | N37: =M37*0.5/100
A38: D/0304 | B38: D-304, Anju Barua | C38: 1014.75 | D38: 1014.75 | E38: =+D38 | G38: =F38 | M38: =C38-D38-F38-H38 | N38: =M38*0.5/100
A39: D/0402 | B39: D-402, Dharmendra Kumar | C39: 204465.7 | D39: 35578.85 | E39: =+D39 | F39: 168886.85 | G39: =F39 | M39: =C39-D39-F39-H39 | N39: =M39*0.5/100
A40: D/0501 | B40: D/501-West Wing Infra.P.L. Kalpeshbhai | C40: 202543.7 | D40: 202543.7 | E40: =+D40 | G40: =F40 | M40: =C40-D40-F40-H40 | N40: =M40*0.5/100
A41: D/0601 | B41: D-601,-West Wing Infra. P.L. Neetaben Prajapati | C41: 204077.7 | D41: 204077.7 | E41: =+D41 | G41: =F41 | M41: =C41-D41-F41-H41 | N41: =M41*0.5/100
A42: D-0602 | B42: D-602, Meena Bohra | C42: 205370 | D42: =2500+25000 | E42: =+D42 | F42: 177870 | G42: =F42 | M42: =C42-D42-F42-H42 | N42: =M42*0.5/100
A43: D/0703 | B43: D-703, Harsh P. Bhatt & Vrushti H. Bhatt | E43: =+D43 | G43: =F43 | M43: =C43-D43-F43-H43 | N43: =M43*0.5/100
A44: D/0902 | B44: D-902, Jigna Thakkar, Jigarbhai B. Thakkar | C44: 409900 | E44: =+D44 | G44: =F44 | M44: =C44-D44-F44-H44 | N44: =M44*0.5/100
A45: E/0403 | B45: E/403 Mohini J. Patel | C45: 230411.7 | D45: =39978.85 | E45: =+D45 | F45: 190432.85 | G45: =F45 | M45: =C45-D45-F45-H45 | N45: =M45*0.5/100
A46: E/0502 | B46: E-502, Roshni Jayeshbhai Thakkar | C46: 167697.7 | D46: 167697.7 | E46: =+D46 | G46: =F46 | M46: =C46-D46-F46-H46 | N46: =M46*0.5/100
A47: E/0503 | B47: E-503,Dharmeshkumar K.& Nilam D.Mehta | E47: =+D47 | G47: =F47 | M47: =C47-D47-F47-H47 | N47: =M47*0.5/100
A48: E/0601 | B48: E-601, Priyanka Jain | C48: 632260 | D48: =2500 | E48: =+D48 | F48: =168163 | G48: =F48 | M48: =C48-D48-F48-H48 | N48: =M48*0.5/100
A49: E/0801 | B49: E-801,Neetika Sharma / Deepak Sharma | C49: 513843 | E49: =+D49 | G49: =F49 | M49: =C49-D49-F49-H49 | N49: =M49*0.5/100
A50: E/0803 | B50: E-803, Riddhi Kamlesh Prajapati | C50: 438739 | E50: =+D50 | G50: =F50 | M50: =C50-D50-F50-H50 | N50: =M50*0.5/100
A51: E/1202 | B51: E-1202, Vinit Krishnakumar Shah | C51: 892792 | E51: =+D51 | G51: =F51 | I51: 446396 | M51: =C51-D51-F51-H51 | N51: =M51*0.5/100
A52: E-1204 | B52: E-1204, Jagrutiben Bipinkumar Chauhan | C52: 271277 | D52: =2500+25000 | E52: =+D52 | F52: =202799 | G52: =F52 | M52: =C52-D52-F52-H52 | N52: =M52*0.5/100
A53: E/1301 | B53: E-1301,Anjanadevi Labana | C53: 423746.7 | D53: =25000+2500+1108.85 | E53: =+D53 | F53: =179434+179446.85 | G53: =F53 | I53: 36257 | M53: =C53-D53-F53-H53 | N53: =M53*0.5/100
A54: E/1302 | B54: E-1302, Ram Janki Sureshbhai | C54: 1273836.7 | D54: =1108.85 | E54: =+D54 | F54: =203525.85 | G54: =F54 | M54: =C54-D54-F54-H54 | N54: =M54*0.5/100
A55: E/1304 | B55: E-1304, Shilpa Devi W/o Vishnukumar Labana | C55: 383960 | E55: =+D55 | G55: =F55 | M55: =C55-D55-F55-H55 | N55: =M55*0.5/100
A56: F/0102 | B56: F-102, Akta Viral Mehta (Akta Ajmera) | C56: 152700 | E56: =+D56 | G56: =F56 | M56: =C56-D56-F56-H56 | N56: =M56*0.5/100
A57: F/0202 | B57: F-202,Ami Kameshkumar Sheth | C57: 241596.7 | D57: 241596.7 | E57: =+D57 | G57: =F57 | M57: =C57-D57-F57-H57 | N57: =M57*0.5/100
A58: F/0301 | B58: F/301, Sureshbhai C. Kanani | C58: 269045.7 | D58: =233385.7 | E58: =+D58 | G58: =F58 | M58: =C58-D58-F58-H58 | N58: =M58*0.5/100
A59: F/0302 | B59: F-302, Dipika Bhavin Parrmar | C59: 298338 | D59: =25000+25000 | E59: 25000 | F59: 211511 | G59: =F59 | I59: 36827 | M59: =C59-D59-F59-H59 | N59: =M59*0.5/100
A60: F/0304 | B60: F/304 Monali H. Soni | C60: 1248369.7 | D60: =2500+25000+1108.85 | E60: =+D60 | F60: =171292+171302.85 | G60: =F60 | M60: =C60-D60-F60-H60 | N60: =M60*0.5/100
A61: F/0402 | B61: F-402, Ashok Kumar Mehta (Padmavati Sales Agency) | C61: 241670 | D61: =25000+38800 | E61: =+D61 | F61: =177870 | G61: =+F61 | M61: =C61-D61-F61-H61 | N61: =M61*0.5/100
A62: F/0502 | B62: F-502, Priyank Jain | C62: 774603.7 | D62: =221693.7 | E62: =+D62 | M62: =C62-D62-F62-H62 | N62: =M62*0.5/100
A63: F/0504 | B63: F-504, Yashvi Sarav & Sarav Harshadrai Parekh | C63: 137702 | E63: =+D63 | G63: =F63 | M63: =C63-D63-F63-H63 | N63: =M63*0.5/100
A64: F/0904 | B64: F/904,Gitaben Kantesariya, Mitkumar Kantesariya | C64: 197705.7 | D64: 1108.85 | E64: =+D64 | F64: 196596.85 | G64: =F64 | M64: =C64-D64-F64-H64 | N64: =M64*0.5/100
A65: F/1203 | B65: F-1203, Taraben Rameshbhai Mewada | C65: 1172294.7 | D65: 201997.7 | E65: =+D65 | M65: =C65-D65-F65-H65 | N65: =M65*0.5/100
A66: F/1301 | B66: F/1301, Ruchita Hemal Modi | C66: 195226.7 | D66: 1108.85 | E66: =+D66 | F66: 194117.85 | G66: =+F66 | M66: =C66-D66-F66-H66 | N66: =M66*0.5/100
A67: F/1303 | B67: F-1303, Amanpreet Singh Sethi | C67: 246174.7 | D67: 246174.7 | E67: =+D67 | G67: =+F67 | M67: =C67-D67-F67-H67 | N67: =M67*0.5/100
A68: G/0101 | B68: G/101,Kiran Kapure / Hemal Jadav ( CANCELLED) | E68: =+D68 | G68: =+F68 | M68: =C68-D68-F68-H68 | N68: =M68*0.5/100
A69: G/0101 | B69: G/101, Paridhi Jain, Nitesh Jani | C69: 788148.7 | D69: 220456.7 | E69: =+D69 | M69: =C69-D69-F69-H69 | N69: =M69*0.5/100
A70: G/0105 | B70: G/105 Ruchin Mittal & Siddharth Mittal | C70: 510964.7 | D70: 1108.85 | E70: =+D70 | F70: 212825.85 | G70: =+F70 | M70: =C70-D70-F70-H70 | N70: =M70*0.5/100
A71: G/0205 | B71: G-205, Alpeshkumar Prabhashankar Joshi | C71: 257426 | E71: =+D71 | G71: =+F71 | M71: =C71-D71-F71-H71 | N71: =M71*0.5/100
A72: G/0303 | B72: G-303, Kalpesh Dalpatbhai Gediya | C72: 586899.7 | D72: 231453.7 | E72: =+D72 | M72: =C72-D72-F72-H72 | N72: =M72*0.5/100
A73: G/0401 | B73: G-401,Dhanki Malay Chandravadan | C73: 631230.7 | D73: 263057.7 | E73: =+D73 | M73: =C73-D73-F73-H73 | N73: =M73*0.5/100
A74: G/0402 | B74: G/402, Manishaben Vijaykumar Sheth & Jainam Sheth | C74: 184896.7 | D74: 1108.85 | E74: =+D74 | F74: 183787.85 | G74: =+F74 | M74: =C74-D74-F74-H74 | N74: =M74*0.5/100
A75: G/0502 | B75: G-502,Brijesh Patel | C75: 346534 | E75: =+D75 | M75: =C75-D75-F75-H75 | N75: =M75*0.5/100
A76: G/0602 | B76: G/602,Harshadkumar G.Patel & Avniben H. Patel | C76: 208015.7 | D76: 36178.85 | E76: =+D76 | F76: 171836.85 | G76: =+F76 | M76: =C76-D76-F76-H76 | N76: =M76*0.5/100
A77: G/1001 | B77: G/1001, Alwani Bhavana Gurmukhdas & Reshma Alwani | C77: 178247.7 | D77: 178247.7 | E77: =+D77 | M77: =C77-D77-F77-H77 | N77: =M77*0.5/100
A78: G/1205 | B78: G-1205, Rohit Kamaljeetsingh Makhija | C78: 714363.7 | D78: 46038.85 | E78: =+D78 | F78: 220150.85 | G78: =+F78 | M78: =C78-D78-F78-H78 | N78: =M78*0.5/100
A79: H/0104 | B79: H/104 Sumit Sharma | C79: 885956 | D79: =43068+25000 | E79: =+D79 | F79: =211035 | G79: =F79 | M79: =C79-D79-F79-H79 | N79: =M79*0.5/100
A80: H/0105 | B80: H/105, Harshadbhai Vinodbhai Makwana | C80: 243017.7 | D80: 243017.7 | E80: =+D80 | G80: =+F80 | M80: =C80-D80-F80-H80 | N80: =M80*0.5/100
A81: H/0205 | B81: H/205,Popatlal Labana / Rajani Labana | C81: 155795.7 | D81: 1108.85 | E81: =+D81 | F81: 154686.85 | G81: =+F81 | M81: =C81-D81-F81-H81 | N81: =M81*0.5/100
A82: H/0305 | B82: H,305, Lakshmi Shreejith | C82: 213934.7 | D82: 213934.7 | E82: =+D82 | G82: =+F82 | M82: =C82-D82-F82-H82 | N82: =M82*0.5/100
A83: H/0403 | B83: H-403, Hiral Trivedi, Paras G. Trivedi | C83: 213934.7 | D83: 213934.7 | E83: =+D83 | M83: =C83-D83-F83-H83 | N83: =M83*0.5/100
A84: H/0506 | B84: H-506, Savita Sadia,Ranjeet Jetha Sadia | C84: 356436 | E84: =+D84 | M84: =C84-D84-F84-H84 | N84: =M84*0.5/100
A85: H/0605 | B85: H-605, Brijeshkumar Maurya & Sweta Daga | C85: 712872 | E85: =+D85 | G85: =+F85 | M85: =C85-D85-F85-H85 | N85: =M85*0.5/100
A86: H/0606 | B86: H-606, Indrasingh Rathore, Kailash Kunwar | C86: 1584156 | E86: =+D86 | I86: 792078 | M86: =C86-D86-F86-H86 | N86: =M86*0.5/100
A87: H/1006 | B87: H-1006, Kinjal(Dhara) Shah, Bhavesh Shah | C87: 245171.7 | D87: 42478.85 | E87: =+D87 | F87: 202692.85 | G87: =+F87 | M87: =C87-D87-F87-H87 | N87: =M87*0.5/100
A88: H/1103 | B88: H/1103 Amit Agarwal | C88: 266012.7 | D88: 46008.85 | E88: =+D88 | F88: 220003.85 | G88: =+F88 | M88: =C88-D88-F88-H88 | N88: =M88*0.5/100
A89: H/1106 | B89: H-1106, Lavnishbhai Maganbhai Ankoliya | C89: 197130.7 | D89: 34338.85 | E89: =+D89 | F89: 162791.85 | G89: =+F89 | M89: =C89-D89-F89-H89 | N89: =M89*0.5/100
A90: I/0103 | B90: I-103, Bhanavi Mishra & Ankur Mishra | C90: 426564.7 | D90: =33613+25000 | E90: =+D90 | F90: =152454+184691.7 | G90: =+F90 | M90: =C90-D90-F90-H90 | N90: =M90*0.5/100
A91: I/0405 | B91: I-405, Remigius F Dias | C91: 31694.75 | D91: 31694.75 | E91: =+D91 | M91: =C91-D91-F91-H91 | N91: =M91*0.5/100
A92: I/0605 | B92: I-605, Dhananjay Nandi | C92: 292422 | D92: =25000+47402 | E92: =+D92 | F92: =220020 | G92: =+F92 | M92: =C92-D92-F92-H92 | N92: =M92*0.5/100
A93: I/0805 | B93: I-805, Manjulaben Lungariya, Rayan Lunagariya | C93: 735686 | D93: =2500+25000 | E93: =+D93 | F93: =219456 | G93: =+F93 | M93: =C93-D93-F93-H93 | N93: =M93*0.5/100
A94: I/0905 | B94: I-905, Swati Chintan Mehta & Chintan Harin Mehta | C94: 429412 | E94: =+D94 | M94: =C94-D94-F94-H94 | N94: =M94*0.5/100
A95: I/1205 | B95: I-1205, Rakesh Dogra & Rashu Rakesh Gogra | C95: 265870.7 | D95: 265870.7 | E95: =+D95 | M95: =C95-D95-F95-H95 | N95: =M95*0.5/100
A96: J/0104 | B96: J-104, Anuradha Sharma | C96: 2354833.7 | D96: =2500+25000+1108.85 | E96: =+D96 | F96: =211035+211046.85 | G96: =+F96 | M96: =C96-D96-F96-H96 | N96: =M96*0.5/100
A97: J/0202 | B97: J-202, Dinesh HemnanI | C97: 701760.7 | D97: 250176.7 | E97: =+D97 | M97: =C97-D97-F97-H97 | N97: =M97*0.5/100
A98: J/0406 | B98: J/406 Jagat Thakkar | C98: 990099 | E98: =+D98 | M98: =C98-D98-F98-H98 | N98: =M98*0.5/100
A99: J/0701 | B99: J-701, Jaykumar Bharatkumar Thakkar | C99: 220504.7 | D99: 220504.7 | E99: =+D99 | M99: =C99-D99-F99-H99 | N99: =M99*0.5/100
A100: J/0902 | B100: J-902, Riddhi Jivanbhai Boricha | C100: 396040 | E100: =+D100 | G100: =+F100 | M100: =C100-D100-F100-H100 | N100: =M100*0.5/100
A101: J/0904 | B101: J-904, Priyanka Jadeja | C101: 396040 | E101: =+D101 | M101: =C101-D101-F101-H101 | N101: =M101*0.5/100
A102: J/0906 | B102: J-906, Rajesh Shashikant Barot & Dhwani Barot | C102: 422772 | E102: =+D102 | M102: =C102-D102-F102-H102 | N102: =M102*0.5/100
B103: Suspense A/c of Members'Collection | C103: 684880 | E103: =+D103 | G103: =+F103 | M103: =C103-D103-F103-H103 | N103: =M103*0.5/100
...

Sheet FOOTPRINT- CALCULATION
A1: Sun Realty Footprint
A2: GST PAYABLE ON COMMERCIAL CONSTRUCTION FOR THE MONTH OF AUG'26
A4: Supply | B4: AMOUNT | C4: RATE | D4: CGST | E4: SGST | F4: TOTAL
A6: SUN REALTY Footprint RESIDENTIAL | B6: ='SUN REALTY FOOTPRINT- MEMBERS'!M218 | C6: 0.01 | D6: =B6*0.5% | E6: =B6*0.5/100 | F6: =+D6+E6
A7: Less : Refund | B7: =-'SUN REALTY FOOTPRINT- MEMBERS'!I218 | C7: 0.01 | D7: =B7*0.5% | E7: =D7 | F7: =+D7+E7
A8: Less: Entry RECTIFIED IN BOOKS OF APRIL-26 F-401, Shubham S/o Gajendra Kumar Mishra | B8: -2800 | C8: 0.01 | D8: =B8*0.5% | E8: =D8 | F8: =+D8+E8 | H8: =38921
A9: LESS : REFUND/PAYMENT ENTRY DELETED FROM BOOKS OF APR-26 D-503,Hansaben Kanakray Rathod_cancelled | B9: 420792 | C9: 0.01 | D9: =B9*0.5% | E9: =D9 | F9: =+D9+E9 | H9: 36121
H10: =+H8-H9
A11: SUN REALTY Footprint COMMERCIAL | B11: =+'SUN REALTY FOOTPRINT- MEMBERS'!M230 | C11: 0.05 | D11: =B11*C11/2 | E11: =B11*C11/2 | F11: =+D11+E11
A12: Less : Refund | B12: =-'SUN REALTY FOOTPRINT- MEMBERS'!I230 | C12: 0.05 | D12: =B12*C12/2 | E12: =B12*C12/2 | F12: =+D12+E12
A14: TOTAL | B14: =SUM(B6:B13) | D14: =SUM(D6:D13) | E14: =SUM(E6:E13) | F14: =SUM(F6:F13)
A15: B2C
A16: Cancellation Charges Income | C16: 0.18 | D16: =B16*C16/2 | E16: =B16*C16/2 | F16: =+D16+E16
A17: After BU sale deed Exempt sale | B17: 84631993 | C17: 0
A18: TOTAL | B18: =+B16+B15+B17 | D18: =+D16+D15+D17 | E18: =+E16+E15+E17 | F18: =+F16+F15+F17
A19: NET TOTAL | B19: =+B14+B18 | D19: =+D14+D18 | E19: =+E14+E18 | F19: =+F14+F18
A21: GST PAYABLE UNDER RCM FOR THE MONTH OF AUG-26
A22: .
A23: Service | B23: AMOUNT | C23: RATE | D23: CGST | E23: SGST | F23: TOTAL
A25: SUN REALTY Footprint
A26: Advocate fees | B26: 0 | C26: 0.18 | D26: =+B26*9/100 | E26: =+D26 | F26: =+D26+E26
A27: Carting and Transportation (Gayatri Sales Corp) | C27: 0.05 | D27: =+B27*0.025 | E27: =+D27 | F27: =+D27+E27
A28: Security Services | C28: 0.18 | D28: =+B28*9% | E28: =+B28*9% | F28: =SUM(D28:E28)
A29: Sponsor Ship Exp | C29: 0.18 | D29: =+B29*9% | E29: =+B29*9% | F29: =SUM(D29:E29)
A31: TOTAL | B31: =SUM(B25:B30) | D31: =SUM(D25:D30) | E31: =SUM(E25:E30) | F31: =SUM(F25:F30)
A33: INELIGIBLE CREDIT FOR THE MONTH OF AUG -26
A35: PARTICULARS | B35: CGST | C35: SGST | D35: IGST
A37: ITC FOR THE AUG-26 | B37: =739575.92 | C37: =+B37
A38: Add: Ineligible ITC | C38: =+B38
A39: Add: Ineligible ITC FOR RCM | B39: =+D31 | C39: =+E31
A40: Total ineligible CENVAYT | B40: =SUM(B37:B39) | C40: =SUM(C37:C39) | D40: =SUM(D37:D39)
A41: TOTAL | B41: =SUM(B40:B40) | C41: =SUM(C40:C40) | D41: =SUM(D40:D40)
A44: GST Payable for the month of AUG'26
A46: PARTICULARS | B46: CGST | C46: SGST | D46: TOTAL
A48: =+A6 | B48: =+D19 | C48: =+E19 | D48: =+F19
A50: TOTAL PAYABLE FOR RESIDENTIAL INCLUDING IGST | B50: =+B48+B49 | C50: =+C48+C49 | D50: =+D48+D49
A52: GST UNDER RCM
A53: SUN Footprint | B53: =D27+D28+D26+D29 | C53: =B53 | D53: =+B53+C53
A54: SUN OFFICE | D54: =+B54+C54
A55: GST Payable | B55: =+B50+B53+B54 | C55: =+C50+C53+C54 | D55: =+D50+D53+D54
A56: Net GST Payable | B56: =+B55 | C56: =+C55 | D56: =+D55
A62: =+'SUN REALTY ATMOS-MEMBERS COLL'!B112
O160: =9957

Sheet SUN PARK WEST- MEMBER COLL.
A1: Sun Realty
A4: CALCULATION For the month of AUG-26
A6: MEMBERS COLLECTION
A7: Flat No. | B7: Name of Owner | C7: CR SIDE | D7: Receipt of Registration Fees/JV (Cr) | E7: Payment of Reg Fees on Behalf of Client / JV (Dr) | F7: Receipt of Stamp Duty/JV (Cr) | G7: Payment of Stamp Duty/JV (Dr) | H7: REFUND OF SAME PEROID WITH GST | I7: CHEQUE RETURN | J7: REFUND WITHOUT GST | K7: NET RECEIPT | L7: GST
A9: A/0201 | B9: A-201,Pareshkumar B.Prajapati | C9: 427256.75 | D9: 1514.75 | E9: =+D9 | K9: =C9-D9-F9-I9 | L9: =+K9*1%/2
A10: A/0301 | B10: A-301, Mrs.Ramla Sahu | C10: 396040 | K10: =C10-D10-F10 | L10: =+K10*1%/2
A11: A/0302_x000D_ | B11: A-302, Vishal Vaidhya & Bhakti Vaidhya | C11: 148515 | K11: =C11-D11-F11 | L11: =+K11*1%/2
A12: A/0401_x000D_ | B12: A-401, Dimpalkumar Jayendraprasad Dave | C12: 257426 | K12: =C12-D12-F12 | L12: =+K12*1%/2
A13: A/0501 | B13: A-501, Alpaben Raj | C13: 1981714.8 | D13: 1514.75 | E13: =+D13 | K13: =C13-D13-F13 | L13: =+K13*1%/2
A14: A/0503 | B14: A/503, Shilpa Indoria | C14: 272278 | E14: =+D14 | K14: =C14-D14-F14 | L14: =+K14*1%/2
A15: A/0702 | B15: A-702, Rajvi Pankit Shah | C15: 356436 | E15: =+D15 | K15: =C15-D15-F15 | L15: =+K15*1%/2
A16: A/0903_x000D_ | B16: A/ 903, Hardik Meravan | C16: 293070 | E16: =+D16 | K16: =C16-D16-F16 | L16: =+K16*1%/2
A17: A/1003_x000D_ | B17: A-1003, Vishal Dobriya | C17: 556436 | E17: =+D17 | K17: =C17-D17-F17 | L17: =+K17*1%/2
A18: A/1004 | B18: A-1004, Urmila Navin Gala | C18: 538614 | K18: =C18-D18-F18 | L18: =+K18*1%/2
A19: A/1103_x000D_ | B19: A-1103, Jeet Gandhi | C19: 297030 | E19: =+D19 | K19: =C19-D19-F19 | L19: =+K19*1%/2
A20: A/1203_x000D_ | B20: A/1203 Ashok G. Kagathara | C20: 331683 | K20: =C20-D20-F20 | L20: =+K20*1%/2
A21: A/1303 | B21: A-1303, Ankur Gordhanbhai Patel | C21: 331684 | K21: =C21-D21-F21 | L21: =+K21*1%/2
A22: B/0101_x000D_ | B22: B/101, Dhairya Samirbhai Pandya | C22: 371288 | K22: =C22-D22-F22 | L22: =+K22*1%/2
A23: B/0602_x000D_ | B23: B-602,Vimala Kushwaha | C23: 396040 | I23: 198020 | K23: =C23-D23-F23 | L23: =+K23*1%/2
A24: B/0902 | B24: B/902 Himanshu Gupta / Nidhi Gupta | C24: 278712 | K24: =C24-D24-F24 | L24: =+K24*1%/2
A25: B/1001_x000D_ | B25: B-1001,Thakor Rohitji | C25: 1485149 | I25: 990100 | K25: =C25-D25-F25 | L25: =+K25*1%/2
A26: B/1101_x000D_ | B26: B-1101. Savitriben Thakor | C26: 1942574 | K26: =C26-D26-F26 | L26: =+K26*1%/2
A27: C/0501 | B27: C-501, Audesh Mansaram Vishvakarma | C27: 297030 | K27: =C27-D27-F27-I27 | L27: =+K27*1%/2
A28: D/0201 | B28: D-201, Riddhi Bhavya Kothari | C28: 940594 | K28: =C28-D28-F28-I28 | L28: =+K28*1%/2
A29: D/0202 | B29: D/202 Palak Atulkumar Turakhia | C29: 466000 | K29: =C29-D29-F29 | L29: =+K29*1%/2
A30: D/0302 | B30: D/302 Nirav Ramjibhai Mehta | C30: 212872 | K30: =C30-D30-F30 | L30: =+K30*1%/2
A31: D/0502_x000D_ | B31: D/502, Varshaben,Nikunj, Rajeshbhai S. Modi | C31: 247524 | K31: =C31-D31-F31 | L31: =+K31*1%/2
A32: D/0601_x000D_ | B32: D/601 Mayank Ramani | C32: 435644 | K32: =C32-D32-F32 | L32: =+K32*1%/2
A33: D/0701_x000D_ | B33: D-701, Rameshchanra Somji Barot | C33: 489627 | K33: =C33-D33-F33 | L33: =+K33*1%/2
A34: D/0704_x000D_ | B34: D/704 Janya Meghrajani, Anshu Meghrajani | C34: 227722 | K34: =C34-D34-F34 | L34: =+K34*1%/2
A35: D/0803_x000D_ | B35: D-803, Aradhana D. & Dhaval Pandit | C35: 247525 | K35: =C35-D35-F35 | L35: =+K35*1%/2
A36: D/0804 | B36: D-804, Krunal Shah | C36: 401683 | K36: =C36-D36-F36 | L36: =+K36*1%/2
A37: D/0901_x000D_ | B37: D-901,Anandkumar Prakashbhai Vaishnani | C37: 202970 | E37: =+D37 | G37: =F37 | K37: =C37-D37-F37 | L37: =+K37*1%/2
A38: D/0903_x000D_ | B38: D-903, Ravi Virani | C38: 1023763 | G38: =F38 | K38: =C38-D38-F38 | L38: =+K38*1%/2
A39: D/1002_x000D_ | B39: D-1002, Mrugesh Pankajkumar Sheth | C39: 410892 | G39: =F39 | K39: =C39-D39-F39 | L39: =+K39*1%/2
A40: D/1003 | B40: D-1003, Suresh C Jagani & Sonalben S. Jagnani | C40: 99010 | K40: =C40-D40-F40-I40 | L40: =+K40*1%/2
A41: D/1102 | B41: D-1102, Urmi Shail Shah | C41: 128712 | K41: =C41-D41-F41 | L41: =+K41*1%/2
A42: D/1103 | B42: D-1103, Smitkumar R. Vachhani | C42: 223267 | K42: =C42-D42-F42 | L42: =+K42*1%/2
A43: D/1202 | B43: D-1202, Kiritbhai Muljibhai Bhut | C43: 235644 | G43: =F43 | K43: =C43-D43-F43 | L43: =+K43*1%/2
A44: D/1303_x000D_ | B44: D/1303, Hiteshkumar S. Shah & Avaniben H.Shah | C44: 269306 | K44: =C44-D44-F44 | L44: =+K44*1%/2
A45: D/1403 | B45: D/1403, Dharti Satishbhai Bhinde | C45: 272278 | E45: =+D45 | K45: =C45-D45-F45 | L45: =+K45*1%/2
A46: D/1404 | B46: D-1404, Dharini U.Kadia & Rushabh Shah | C46: 297030 | E46: =+D46 | G46: =F46 | K46: =C46-D46-F46 | L46: =+K46*1%/2
A47: E/0302_x000D_ | B47: E-302, Pranav Chauhan / Hiren Chauhan | C47: 396040 | G47: =F47 | K47: =C47-D47-F47 | L47: =+K47*1%/2
A48: E/1001 | B48: E-1001,Chitukumar Ashvinbhai Bhanderi | C48: 831684 | E48: =+D48 | K48: =C48-D48-F48 | L48: =+K48*1%/2
A49: E/1002_x000D_ | B49: E--1002, Palak Prafulbhai Parikh | C49: 237624 | K49: =C49-D49-F49 | L49: =+K49*1%/2
A50: E/1101 | B50: E-1101,Amit A & Tarulata A.Thakkar | C50: 279356 | K50: =C50-D50-F50 | L50: =+K50*1%/2
A51: E/1102_x000D_ | B51: E/1102, Bhavesh D.Bavasia (Patel) | C51: 439604 | K51: =C51-D51-F51 | L51: =+K51*1%/2
A52: E/1301 | B52: E-1301, Kupali Harsh Patel | C52: 1792080 | K52: =C52-D52-F52 | L52: =+K52*1%/2
A53: E/-901 | B53: E-901 Yuvraj Dineshbhai Parmar | C53: 1252476 | K53: =C53-D53-F53 | L53: =+K53*1%/2
A54: F/0301_x000D_ | B54: F/301 Ajay Kantilal Patel | C54: 339998 | K54: =C54-D54-F54 | L54: =+K54*1%/2
A55: F/0404 | B55: F-404,Anand Sonagara | C55: 297030 | K55: =C55-D55-F55 | L55: =+K55*1%/2
A56: F/0501_x000D_ | B56: F-501, Hemalkumar Vaidya | C56: 246138 | E56: =D56 | G56: =F56 | K56: =C56-D56-F56 | L56: =+K56*1%/2
A57: F/1001_x000D_ | B57: F/1001, Ramabhai Pujabhai & Shantaben P.Patel | C57: 712872 | I57: 356436 | K57: =C57-D57-F57 | L57: =+K57*1%/2
A58: F/1101_x000D_ | B58: F/1101 Aashish M. Borana | C58: 287128 | K58: =C58-D58-F58 | L58: =+K58*1%/2
A59: E/401 | B59: E/401 Sagar Hiteshkumar Maniar | C59: 435644 | K59: =C59-D59-F59 | L59: =+K59*1%/2
K60: =C60-D60-F60 | L60: =+K60*1%/2
K61: =C61-D61-F61 | L61: =+K61*1%/2
K62: =C62-D62-F62 | L62: =+K62*1%/2
E72: =D72 | G72: =F72 | K72: =C72-D72-F72 | L72: =+K72*1%/2
E73: =D73 | G73: =F73 | K73: =C73-D73-F73 | L73: =+K73*1%/2
A74: Total | C74: =SUM(C9:C73) | D74: =SUM(D9:D73) | E74: =SUM(E9:E73) | F74: =SUM(F9:F73) | G74: =SUM(G9:G73) | H74: =SUM(H9:H73) | I74: =SUM(I9:I73) | J74: =SUM(J9:J73) | ... L74: =SUM(L9:L73)
A76: FLATE MEMBERS COLLECTION @ 5%
A77: Flat No. | B77: Name of Owner | C77: CR SIDE | D77: Receipt of Registration Fees | E77: Payment of Reg Fees on Behalf of Client | F77: Receipt of Stamp Duty/JV (Cr) | G77: Payment of Stamp Duty/JV (Cr) | H77: REFUND OF SAME PEROID | J77: REFUND WITHOUT GST | K77: NET RECEIPT
E79: =+D79 | K79: =C79-D79-F79 | L79: =+K79*5%/2
E80: =D80 | G80: =F80 | K80: =C80-D80-F80 | L80: =+K80*5%/2
E81: =+D81 | K81: =C81-D81-F81 | L81: =K81*2.5/100
K82: =C82-D82-F82 | L82: =K82*2.5/100
K83: =C83-D83-F83
E84: =+D84 | K84: =C84-D84 | L84: =K84*2.5/100
A85: Total | C85: =SUM(C79:C84) | D85: =SUM(D79:D84) | E85: =SUM(E79:E84) | F85: =SUM(F79:F84) | G85: =SUM(G79:G84) | H85: =SUM(H79:H84) | J85: =SUM(J79:J84) | K85: =SUM(K79:K84)
A89: SHOP MEMBERS COLLECTION
A90: shop no. | B90: Name of Owner | C90: CR SIDE | D90: Receipt of Registration Fees | E90: Payment of Reg Fees on Behalf of Client | F90: Receipt of Stamp Duty/JV (Cr) | G90: Payment of Stamp Duty/JV (Cr) | H90: REFUND OF SAME PEROID | J90: REFUND WITHOUT GST | K90: NET RECEIPT
G92: =F92 | K92: =C92-D92-F92 | L92: =K92*2.5/100
E93: =D93 | G93: =F93 | K93: =C93-D93-F93 | L93: =K93*2.5/100
E94: =+D94 | K94: =C94-D94-F94 | L94: =K94*2.5/100
E95: =+D95 | K95: =C95-D95-F95 | L95: =K95*2.5/100
E96: =+D96 | K96: =C96-D96-F96 | L96: =K96*2.5/100
A97: Total | C97: =SUM(C92:C96) | D97: =SUM(D92:D96) | E97: =SUM(E92:E96) | H97: =SUM(H92:H96) | J97: =SUM(J92:J96) | K97: =SUM(K92:K96)
B99: Total Credit Side | C99: =+C74+C97+C85
B100: Total Debit Side | C100: =+H74+E74+D97+H97+E85
A102: =+'SUN REALTY-CALC'!A119

Sheet SUN PARK WEST
A1: Sun Realty -SUN PARK WEST
A2: GST PAYABLE ON COMMERCIAL CONSTRUCTION FOR THE MONTH OF AUG'26
A4: Supply | B4: AMOUNT | C4: RATE | D4: CGST | E4: SGST | F4: TOTAL
H5: FILED GSTR-1 | I5: TAXABLE VALUE | J5: CGST | K5: SGST
A6: SUN REALTY -SUN PARK WEST RESIDENTIAL | B6: =+'SUN PARK WEST- MEMBER COLL.'!K74 | C6: 0.01 | D6: =B6*0.5% | E6: =B6*0.5/100 | F6: =+D6+E6 | H6: 46113 | I6: 198020
A7: SUSPNESE A/C PAID @1% [ Deleted From Books of Apr-26] | B7: =+-I11 | C7: 0.01 | D7: =B7*0.5% | E7: =B7*0.5/100 | F7: =+D7+E7
A8: Less : Refund/Chq Return | B8: =-'SUN PARK WEST- MEMBER COLL.'!H74-'SUN PARK WEST- MEMBER COLL.'!I74 | C8: 0.01 | D8: =B8*0.5% | E8: =D8 | F8: =+D8+E8
A10: SUN REALTY -SUN PARK WEST RESIDENTIAL | B10: =+'SUN PARK WEST- MEMBER COLL.'!K85 | C10: 0.05 | D10: =B10*C10/2 | E10: =B10*C10/2 | F10: =+D10+E10
A11: SUSPENSE TRANSFER TO MEMBERS A/C@5% [ AS PER GST RECO] | B11: =+I19-I26 | C11: 0.05 | D11: =B11*C11/2 | E11: =B11*C11/2 | F11: =+D11+E11 | I11: =SUM(I6:I10) | J11: =SUM(J6:J10) | K11: =SUM(K6:K10)
A12: Less : Refund/Chq Return | B12: =-'SUN PARK WEST- MEMBER COLL.'!H85 | C12: 0.05 | D12: =B12*C12/2 | E12: =B12*C12/2 | F12: =+D12+E12
H13: AS PER BOOKS | I13: TAXABLE VALUE | J13: CGST | K13: SGST
A14: SUN REALTY -SUN PARK WEST COMMERCIAL | B14: =+'SUN PARK WEST- MEMBER COLL.'!K97 | C14: 0.05 | D14: =B14*C14/2 | E14: =B14*C14/2 | F14: =+D14+E14
A15: Less : Refund/Chq Return | B15: =-'SUN PARK WEST- MEMBER COLL.'!H97 | C15: 0.05 | D15: =B15*C15/2 | E15: =B15*C15/2 | F15: =+D15+E15
A17: TOTAL | B17: =SUM(B6:B15) | D17: =SUM(D6:D15) | E17: =SUM(E6:E15) | F17: =SUM(F6:F15)
A19: GST PAYABLE UNDER RCM FOR THE MONTH OF AUG'26 | I19: =SUM(I14:I18) | J19: =SUM(J14:J18) | K19: =SUM(K14:K18)
A20: .
A21: Service | B21: AMOUNT | C21: RATE | D21: CGST | E21: SGST | F21: TOTAL | H21: TAXABLE VALUE CHANGE IN BOOKS AFTER FILING GSTR-1 OF AUG-25
H22: FILED GSTR-1 | I22: TAXABLE VALUE | J22: CGST | K22: SGST
A23: SUN REALTY-SUN PARK WEST
A24: Advocate fees | B24: 0 | C24: 0.18 | D24: =+B24*9/100 | E24: =+D24 | F24: =+D24+E24 | H24: AS PER BOOKS
A25: Carting and Transportation (Gayatri Sales Corp)/ ASHOK P VANJARA | B25: 0 | C25: 0.05 | D25: =+B25*0.025 | E25: =+D25 | F25: =+D25+E25
A26: Security Services | B26: 18000 | C26: 0.18 | D26: =+B26*9% | E26: =+B26*9% | F26: =SUM(D26:E26) | H26: EXCESS GST PAID | I26: =I23-I25 | J26: =J23-J25 | K26: =K23-K25
A27: Sponsorship Exp | C27: 0.18 | D27: =+B27*9% | E27: =+B27*9% | F27: =SUM(D27:E27)
A28: Royalty Exp. | C28: 0.18 | D28: =+B28*9% | E28: =+B28*9% | F28: =SUM(D28:E28)
A29: TOTAL | B29: =SUM(B23:B28) | D29: =SUM(D23:D28) | E29: =SUM(E23:E28) | F29: =SUM(F23:F28)
A31: INELIGIBLE CREDIT FOR THE MONTH OF AUG'26
A33: PARTICULARS | B33: CGST | C33: SGST | D33: IGST
A35: ITC FOR THE AUG-26 | C35: =+B35 | D35: 0
A36: Direct Exp. | B36: =353435.84 | C36: =+B36
A37: Indirect Exp. | B37: 540 | C37: =+B37 | D37: 0
A38: Add: Ineligible ITC | C38: =+B38
A39: Add: Ineligible ITC FOR RCM | B39: =+D29 | C39: =+E29
A40: Total ineligible CENVAYT | B40: =SUM(B35:B39) | C40: =SUM(C35:C39) | D40: =SUM(D35:D39)
A41: TOTAL | B41: =SUM(B40:B40) | C41: =SUM(C40:C40) | D41: =SUM(D40:D40)
A44: GST Payable for the month of AUG'26
A46: PARTICULARS | B46: CGST | C46: SGST | D46: TOTAL
A48: =+A6 | B48: =+D17 | C48: =+E17 | D48: =+F17
A50: TOTAL PAYABLE FOR RESIDENTIAL INCLUDING IGST | B50: =+B48+B49 | C50: =+C48+C49 | D50: =+D48+D49
A52: GST UNDER RCM
A53: SUN Footprint | B53: =+D29 | C53: =B53 | D53: =+B53+C53
A54: SUN OFFICE | D54: =+B54+C54
A55: GST Payable | B55: =+B50+B53+B54 | C55: =+C50+C53+C54 | D55: =+D50+D53+D54
A56: Net GST Payable | B56: =+B55 | C56: =+C55 | D56: =+D55
A59: As per Note | C59: Taxable Amount | D59: CGST | E59: SGST
H78: =127214-1238
M98: =7957235-6059

Sheet SUN SILVER SPRING-MEMBER COLL
A1: Sun Realty -SUN SILVER SPRING
A4: CALCULATION For the month of APR-25 TO DEC-25
A5: FLATE MEMBERS COLLECTION @ 5%
A6: Flat No. | B6: Name of Owner | C6: CR SIDE | D6: Receipt of Registration Fees | E6: Payment of Reg Fees on Behalf of Client | F6: Receipt of Stamp Duty/JV (Cr) | G6: Payment of Stamp Duty/JV (Cr) | H6: REFUND OF SAME PEROID | J6: REFUND WITHOUT GST | K6: NET RECEIPT
L7: GST
K8: =C8-D8-F8 | L8: =K8*2.5/100
K9: =C9-D9-F9 | L9: =K9*2.5/100
K10: =C10-D10-F10 | L10: =K10*2.5/100
K11: =C11-D11-F11 | L11: =K11*2.5/100
K12: =C12-D12-F12 | L12: =K12*2.5/100
K13: =C13-D13-F13 | L13: =K13*2.5/100
K14: =C14-D14-F14 | L14: =K14*2.5/100
K15: =C15-D15-F15 | L15: =K15*2.5/100
K16: =C16-D16-F16 | L16: =K16*2.5/100
K17: =C17-D17-F17 | L17: =K17*2.5/100
K18: =C18-D18-F18 | L18: =K18*2.5/100
K19: =C19-D19-F19 | L19: =K19*2.5/100
K20: =C20-D20 | L20: =K20*2.5/100
A21: Total | C21: =SUM(C8:C20) | D21: =SUM(D8:D20) | E21: =SUM(E8:E20) | F21: =SUM(F8:F20) | G21: =SUM(G8:G20) | H21: =SUM(H8:H20) | J21: =SUM(J8:J20) | K21: =SUM(K8:K20)

Sheet SUN SILVER SPRING
A1: Sun Realty -SUN SILVER SPRING
A2: GST PAYABLE ON COMMERCIAL CONSTRUCTION FOR THE MONTH OF AUG-26
A4: Supply | B4: AMOUNT | C4: RATE | D4: CGST | E4: SGST | F4: TOTAL
A7: SUN REALTY -SUN SILVER SPRING RESIDENTIAL | B7: =+'SUN SILVER SPRING-MEMBER COLL'!K21 | C7: 0.05 | D7: =B7*C7/2 | E7: =B7*C7/2 | F7: =+D7+E7
B8: 0 | C8: 0.05 | D8: =B8*C8/2 | E8: =B8*C8/2 | F8: =+D8+E8
A9: Less : Refund | B9: =-'SUN SILVER SPRING-MEMBER COLL'!H21 | C9: 0.05 | D9: =B9*C9/2 | E9: =B9*C9/2 | F9: =+D9+E9
A11: SUN REALTY -SUN PARK WEST COMMERCIAL | C11: 0.05 | D11: =B11*C11/2 | E11: =B11*C11/2 | F11: =+D11+E11
A12: Less : Refund | C12: 0.05 | D12: =B12*C12/2 | E12: =B12*C12/2 | F12: =+D12+E12
A14: TOTAL | B14: =SUM(B6:B12) | D14: =SUM(D6:D12) | E14: =SUM(E6:E12) | F14: =SUM(F6:F12)
A16: GST PAYABLE UNDER RCM FOR THE MONTH OF AUG-26
A17: .
A18: Service | B18: AMOUNT | C18: RATE | D18: CGST | E18: SGST | F18: TOTAL
A20: SUN REALTY-SUN SILVER SPRING
A21: Advocate fees | B21: 0 | C21: 0.18 | D21: =+B21*9/100 | E21: =+D21 | F21: =+D21+E21
A22: Carting and Transportation (Gayatri Sales Corp)/ SHAKTI TRANSPORT | C22: 0.05 | D22: =+B22*0.025 | E22: =+D22 | F22: =+D22+E22
A23: Security Services (AUG-25 TO AUG-26) | C23: 0.18 | D23: =+B23*9% | E23: =+B23*9% | F23: =SUM(D23:E23)
A24: Sponsorship Exp | C24: 0.18 | D24: =+B24*9% | E24: =+B24*9% | F24: =SUM(D24:E24)
A25: Royalty Exp. | C25: 0.18 | D25: =+B25*9% | E25: =+B25*9% | F25: =SUM(D25:E25)
A26: TOTAL | B26: =SUM(B20:B25) | D26: =SUM(D20:D25) | E26: =SUM(E20:E25) | F26: =SUM(F20:F25)
A28: INELIGIBLE CREDIT FOR THE MONTH OF AUG-26
A30: PARTICULARS | B30: CGST | C30: SGST | D30: IGST
A32: ITC FOR THE AUG-26
A33: Direct Exp. | B33: 30599.11 | C33: =+B33 | D33: 0
A34: Indirect Exp. | B34: 0 | C34: =+B34 | D34: 0
A35: Add: Ineligible ITC | C35: =+B35
A36: Add: Ineligible ITC FOR RCM | B36: =+D26 | C36: =+E26
A37: Total ineligible CENVAYT | B37: =SUM(B32:B36) | C37: =SUM(C32:C36) | D37: =SUM(D32:D36)
A38: TOTAL | B38: =SUM(B37:B37) | C38: =SUM(C37:C37) | D38: =SUM(D37:D37)
A41: GST Payable for the month of AUG-26
A43: PARTICULARS | B43: CGST | C43: SGST | D43: TOTAL
A45: =+A7 | B45: =+D14 | C45: =+E14 | D45: =+F14
A47: TOTAL PAYABLE FOR RESIDENTIAL INCLUDING IGST | B47: =+B45+B46 | C47: =+C45+C46 | D47: =+D45+D46
A49: GST UNDER RCM
A50: SUN SILVER SPRING | B50: =+D26 | C50: =B50 | D50: =+B50+C50
A51: SUN OFFICE | D51: =+B51+C51
A52: GST Payable | B52: =+B47+B50+B51 | C52: =+C47+C50+C51 | D52: =+D47+D50+D51
A53: Net GST Payable | B53: =+B52 | C53: =+C52 | D53: =+D52
A56: As per Note | C56: Taxable Amount | D56: CGST | E56: SGST

Sheet LEKHAMBHA- Member coll
A1: Sun Realty
A4: CALCULATION For the month ofJUN-25
A6: FLATE MEMBERS COLLECTION @ 5%
A7: Flat No. | B7: Name of Owner | C7: CR SIDE | D7: Receipt of Registration Fees/JV (Cr) | E7: Payment of Reg Fees on Behalf of Client / JV (Dr) | F7: Receipt of Stamp Duty/JV (Cr) | G7: Payment of Stamp Duty/JV (Cr) | J7: REFUND OF SAME PEROID | K7: REFUND WITHOUT GST | L7: AEC,AUDA JV | M7: NET RECEIPT
H8: cheque return | I8: cancellation of plot
E9: =D9 | G9: =F9 | L9: 0 | M9: =C9-D9-F9 | N9: =M9*2.5%
M10: =C10-D10-F10 | N10: =M10*2.5%
M11: =C11-D11-F11 | N11: =M11*2.5%
M12: =C12-D12-F12 | N12: =M12*2.5%
M13: =C13-D13-F13 | N13: =M13*2.5%
M14: =C14-D14-F14-H14 | N14: =M14*2.5%
M15: =C15-D15-F15-H15 | N15: =M15*2.5%
M16: =C16-D16-F16-H16-I16 | N16: =M16*2.5%
M17: =C17-D17-F17-H17 | N17: =M17*2.5%
M18: =C18-D18-F18-H18 | N18: =M18*2.5%
M19: =C19-D19-F19-H19 | N19: =M19*2.5%
M20: =C20-D20-F20-H20 | N20: =M20*2.5%
M21: =C21-D21-F21-H21 | N21: =M21*2.5%
M22: =C22-D22-F22-H22 | N22: =M22*2.5%
M23: =C23-D23-F23-H23 | N23: =M23*2.5%
M24: =C24-D24-F24-H24 | N24: =M24*2.5%
M25: =C25-D25-F25-H25 | N25: =M25*2.5%
M26: =C26-D26-F26-H26 | N26: =M26*2.5%
M27: =C27-D27-F27-H27 | N27: =M27*2.5%
M28: =C28-D28-F28-H28 | N28: =M28*2.5%
M29: =C29-D29-F29-H29 | N29: =M29*2.5%
E30: =+D30 | G30: =+F30 | M30: =C30-D30-F30-H30 | N30: =M30*2.5%
A32: Total | C32: =SUM(C9:C30) | D32: =SUM(D9:D30) | E32: =SUM(E9:E30) | F32: =SUM(F9:F30) | G32: =SUM(G9:G30) | J32: =SUM(J9:J30) | K32: =SUM(K9:K30) | L32: =SUM(L9:L30) | M32: =SUM(M9:M30)
A35: SHOP MEMBERS COLLECTION
A36: Flat No. | B36: Name of Owner | C36: CR SIDE | D36: Receipt of Registration Fees | E36: Payment of Reg Fees on Behalf of Client | F36: Receipt of Stamp Duty/JV (Cr) | G36: Payment of Stamp Duty/JV (Cr) | J36: REFUND OF SAME PEROID | K36: REFUND WITHOUT GST | L36: AEC,AUDA JV | M36: NET RECEIPT
E38: =D38 | G38: =F38 | M38: =C38-D38-F38
E39: =D39 | G39: =F39 | M39: =C39-D39-F39 | N39: =M39*2.5/100
E40: =D40 | G40: =F40 | M40: =C40-D40-F40 | N40: =M40*2.5/100
E41: =+D41 | M41: =C41-D41-F41 | N41: =M41*2.5/100
E42: =+D42 | M42: =C42-D42-F42 | N42: =M42*2.5/100
E43: =+D43 | M43: =C43-D43-F43 | N43: =M43*2.5/100
E44: =+D44 | M44: =C44-D44 | N44: =M44*2.5/100
A45: Total | C45: =SUM(C38:C44) | D45: =SUM(D38:D44) | E45: =SUM(E38:E44) | J45: =SUM(J38:J44) | K45: =SUM(K38:K44) | L45: =SUM(L38:L44) | M45: =SUM(M38:M44)

Sheet LEKHAMBHA
A1: Sun Realty -LEKHAMBHA
A2: GST PAYABLE ON COMMERCIAL CONSTRUCTION FOR THE MONTH OFJUN-25
A4: Supply | B4: AMOUNT | C4: RATE | D4: CGST | E4: SGST | F4: TOTAL
A6: SUN REALTY -SUN SILVER SPRINGS RESIDENTIAL | B6: ='LEKHAMBHA- Member coll'!M32 | C6: 0.05 | D6: =B6*C6/2 | E6: =B6*C6/2 | F6: =+D6+E6
A7: Less : Refund | B7: =-'LEKHAMBHA- Member coll'!J32 | C7: 0.05 | D7: =B7*C7/2 | E7: =B7*C7/2 | F7: =+D7+E7
A9: SUN REALTY -SUN SILVER SPRINGS COMMERCIAL | B9: =+'LEKHAMBHA- Member coll'!M45 | C9: 0.05 | D9: =B9*C9/2 | E9: =B9*C9/2 | F9: =+D9+E9
A10: Less : Refund | B10: =+'LEKHAMBHA- Member coll'!J45 | C10: 0.05 | D10: =B10*C10/2 | E10: =B10*C10/2 | F10: =+D10+E10
A13: TOTAL | B13: =SUM(B6:B11) | D13: =SUM(D6:D12) | E13: =SUM(E6:E12) | F13: =SUM(F6:F12)
A15: GST PAYABLE UNDER RCM FOR THE MONTH OFJUN-25
A16: .
A17: Service | B17: AMOUNT | C17: RATE | D17: CGST | E17: SGST | F17: TOTAL
A19: SUN REALTY -SUN SILVER SPRINGS
A20: Advocate fees | B20: 0 | C20: 0.18 | D20: =+B20*9/100 | E20: =+D20 | F20: =+D20+E20
A21: Carting and Transportation (Gayatri Sales Corp)/ ASHOK P VANJARA | B21: 0 | C21: 0.05 | D21: =+B21*0.025 | E21: =+D21 | F21: =+D21+E21
A22: Security Services | B22: 0 | C22: 0.18 | D22: =+B22*9% | E22: =+B22*9% | F22: =SUM(D22:E22)
A23: Sponsorship Exp | C23: 0.18 | D23: =+B23*9% | E23: =+B23*9% | F23: =SUM(D23:E23)
A24: Royalty Exp. | C24: 0.18 | D24: =+B24*9% | E24: =+B24*9% | F24: =SUM(D24:E24)
A25: TOTAL | B25: =SUM(B19:B24) | D25: =SUM(D19:D24) | E25: =SUM(E19:E24) | F25: =SUM(F19:F24)
A27: INELIGIBLE CREDIT FOR THE MONTH OFJUN-25
A29: PARTICULARS | B29: CGST | C29: SGST | D29: IGST
A31: ITC FOR THEJUN-25 | B31: 0 | C31: =+B31 | D31: 0
A32: Direct Exp. | B32: 0 | C32: =+B32
A33: Indirect Exp. | B33: 0 | C33: =+B33
A34: Add: Ineligible ITC (whole year adjustment) | C34: =+B34
A35: Add: Ineligible ITC FOR RCM | B35: =+D25 | C35: =+E25
A36: Total ineligible CENVAYT | B36: =SUM(B31:B35) | C36: =SUM(C31:C35) | D36: =SUM(D31:D31)
A37: TOTAL | B37: =SUM(B36:B36) | C37: =SUM(C36:C36) | D37: =SUM(D36:D36)
A40: GST Payable for the month ofJUN-25
A42: PARTICULARS | B42: CGST | C42: SGST | D42: TOTAL
A44: =+A6 | B44: =+D13 | C44: =+E13 | D44: =+F13
A46: TOTAL PAYABLE FOR RESIDENTIAL INCLUDING IGST | B46: =+B44+B45 | C46: =+C44+C45 | D46: =+D44+D45
A48: GST UNDER RCM
B49: =+D25 | C49: =B49 | D49: =+B49+C49
A50: SUN OFFICE | D50: =+B50+C50
A51: GST Payable | B51: =+B46+B49+B50 | C51: =+C46+C49+C50 | D51: =+D46+D49+D50
A52: Net GST Payable | B52: =+B51 | C52: =+C51 | D52: =+D51

Sheet FINAL CALC
A3: Sun Realty
A4: GST PAYABLE ON COMMERCIAL CONSTRUCTION FOR THE MONTH OF AUG-26
A6: Supply | B6: AMOUNT | C6: LAND VALUE (1/3) | D6: TAXABLE VALUE (2/3) | E6: RATE | F6: CGST | G6: SGST | H6: TOTAL
A8: SUN GRAVITAS advance | B8: =+'SUN REALTY-CALC'!B19 | C8: =+'SUN REALTY-CALC'!C19 | D8: =+'SUN REALTY-CALC'!D19 | E8: 0.18 | F8: =+'SUN REALTY-CALC'!F19 | G8: =+'SUN REALTY-CALC'!G19 | H8: =+'SUN REALTY-CALC'!H19
A9: SUN GRAVITAS Payable due to Adjustment of Advances against Sale Deed Executed | B9: ='SUN REALTY-CALC'!B12 | D9: =+'SUN REALTY-CALC'!D16 | E9: 0.18 | F9: =+'SUN REALTY-CALC'!F12 | G9: =+F9 | H9: =+F9+G9
A10: SUN GRAVITAS Exempt Income | B10: =+'SUN REALTY-CALC'!B26+'SUN REALTY-CALC'!B27
A11: Extra work Income (B2C) | B11: =+'SUN REALTY-CALC'!D24 | D11: =+B11 | E11: 0.18 | F11: =+'SUN REALTY-CALC'!F24 | G11: =+F11 | H11: =+F11+G11
A12: Advance adjusted for same | B12: =+'SUN REALTY-CALC'!D25 | D12: =+B12 | E12: 0.18 | F12: =+'SUN REALTY-CALC'!F25 | G12: =+F12 | H12: =+F12+G12
A13: Cancellation Charges Income (B2C) | B13: =+'SUN REALTY-CALC'!D21 | D13: =+'SUN REALTY-CALC'!D22 | E13: 0.18 | F13: =D13*E13/2 | G13: =+F13 | H13: =+F13+G13 | XFD13: =+'SUN REALTY-CALC'!XFD28
A14: Advance adjusted for same | B14: =+'SUN REALTY-CALC'!D23 | D14: =+B14 | E14: 0.18 | F14: =D14*E14/2 | G14: =+F14 | H14: =+F14+G14
A16: SUN REALTY ATMOSPHERE RESIDENTIAL | B16: =+'SUN REALTY ATMOS-CALC'!B15 | D16: =+B16 | E16: 0.01 | F16: =D16*E16/2 | G16: =+F16 | H16: =G16+F16
A17: SUN REALTY ATMOSPHERE RESIDENTIAL More Than 5% | B17: =+'SUN REALTY ATMOS-CALC'!B24 | D17: =B17 | E17: 0.05 | F17: =D17*E17/2 | G17: =+F17 | H17: =G17+F17
A18: SUN REALTY ATMOSPHERE COMMERCIAL | B18: =+'SUN REALTY ATMOS-CALC'!B30 | D18: =+'SUN REALTY ATMOS-CALC'!B26+'SUN REALTY ATMOS-CALC'!B27 | E18: 0.05 | F18: =D18*E18/2 | G18: =+F18 | H18: =G18+F18
A19: SUN REALTY ATMOSPHERE COMMERCIAL PLC | B19: =+'SUN REALTY ATMOS-CALC'!B25+'SUN REALTY ATMOS-CALC'!B20 | D19: =+B19 | E19: 0.18 | F19: =D19*E19/2 | G19: =+F19 | H19: =G19+F19
A20: Cancellation Charges Income (B2C) | B20: 0 | D20: =B20 | E20: 0.18 | F20: =D20*E20/2 | G20: =+F20 | H20: =G20+F20
A21: SUN Atmoshphere Exempt Income | B21: =+'SUN REALTY ATMOS-CALC'!B34
A23: SUN REALTY FOOTPRINT RESIDENTIAL | B23: =+'FOOTPRINT- CALCULATION'!B6+'FOOTPRINT- CALCULATION'!B7+'FOOTPRINT- CALCULATION'!B8 | D23: =B23 | E23: 0.01 | F23: =B23*E23/2 | G23: =+F23 | H23: =G23+F23
A24: SUN REALTY FOOTPRINT COMMERCIAL | B24: ='FOOTPRINT- CALCULATION'!B11+'FOOTPRINT- CALCULATION'!B12 | D24: =B24 | E24: 0.05 | F24: ='FOOTPRINT- CALCULATION'!D11+'FOOTPRINT- CALCULATION'!D12 | G24: =+F24 | H24: =G24+F24
A25: Cancellation Charges Income (B2C) | B25: =+D25 | D25: =+'FOOTPRINT- CALCULATION'!B16 | E25: 0.18 | F25: =D25*E25/2 | G25: =+'FOOTPRINT- CALCULATION'!E16 | H25: =+'FOOTPRINT- CALCULATION'!F16
A26: SUN Footprint Exempt Income | B26: =+'FOOTPRINT- CALCULATION'!B17
A28: SUN REALTY - SUN PARK WEST RESIDENTIAL | B28: =+'SUN PARK WEST'!B6+'SUN PARK WEST'!B8+'SUN PARK WEST'!B9+'SUN PARK WEST'!B7 | D28: =B28 | E28: 0.01 | F28: =D28*E28/2 | G28: =+F28 | H28: =+G28+F28
A29: SUN REALTY - SUN PARK WEST RESIDENTIAL More than 45 lacs | B29: =+'SUN PARK WEST'!B10+'SUN PARK WEST'!B12+'SUN PARK WEST'!B11 | D29: =+B29 | E29: 0.05 | F29: =D29*E29/2 | G29: =+F29 | H29: =+G29+F29
A30: SUN REALTY -SUN PARK WEST COMMERCIAL | B30: =+'SUN PARK WEST'!B14+'SUN PARK WEST'!B15 | D30: =+B30 | E30: 0.05 | F30: =D30*E30/2 | G30: =+F30 | H30: =+G30+F30
A32: SUN REALTY -SUN SILVER SPRINGS RESIDENTIAL | B32: =+'SUN SILVER SPRING'!B7+'SUN SILVER SPRING'!B8+'SUN SILVER SPRING'!B9 | D32: =+B32 | E32: 0.05 | F32: =D32*E32/2 | G32: =+F32 | H32: =+G32+F32
A33: SUN REALTY -SUN SILVER SPRINGS COMMERCIAL | B33: =+'SUN SILVER SPRING'!B11+'SUN SILVER SPRING'!B12 | D33: =+B33 | E33: 0.05 | F33: =D33*E33/2 | G33: =+F33 | H33: =+G33+F33
A35: TOTAL | B35: =SUM(B8:B33) | C35: =SUM(C8:C33) | D35: =SUM(D8:D33) | E35: =E8+E16+E18+E24+E23 | F35: =SUM(F8:F33) | G35: =SUM(G8:G33) | H35: =SUM(H8:H33)
B36: TAXABLE VALUE (2/3) | C36: CGST | D36: SGST
A37: 0.18 | B37: =+D8+D9+D19 | C37: =B37*A37/2 | D37: =+C37
A38: 0.01 | B38: =+D16+D23+D28 | C38: =B38*A38/2 | D38: =+C38
A39: 0.05 | B39: =+D17+D18+D24+D29+D30+D32+D33 | C39: =B39*A39/2 | D39: =+C39
A40: 18%(DIRECT B2C) | B40: =+D11+D13+D25 | C40: =+F11+F13+F25 | D40: =+G11+G13+G25
A41: Non GST income | B41: =+C8
A42: exempt income | B42: =+B10+B21+B26
A45: Supply | B45: GSTIN | D45: AMOUNT | E45: RATE | F45: CGST | G45: SGST | H45: TOTAL
A48: Rent income-Meglyn Technologies Pvt Ltd (SAC-)] ( To be Confirm is there any income )-997212 | B48: 24AAJCM9952F1Z6 | D48: =+'SUN REALTY-CALC'!D38 | E48: 0.18 | F48: =+D48*E48/2 | G48: =+D48*E48/2 | H48: =+SUM(F48:G48)
D50: =+SUM(D47:D49) | F50: =+SUM(F47:F49) | G50: =+SUM(G47:G49) | H50: =+SUM(H47:H49)
A52: GST PAYABLE UNDER RCM FOR THE MONTH OF AUG-26
A53: .
A54: Service | B54: AMOUNT | C54: RATE | D54: CGST | E54: SGST | F54: TOTAL
A56: SUN GRAVITAS | B56: ='SUN REALTY-CALC'!B55 | D56: ='SUN REALTY-CALC'!D55 | E56: ='SUN REALTY-CALC'!E55 | F56: ='SUN REALTY-CALC'!F55
A58: SUN REALTY ATMOSPHERE | B58: ='SUN REALTY ATMOS-CALC'!B53 | D58: ='SUN REALTY ATMOS-CALC'!D53 | E58: ='SUN REALTY ATMOS-CALC'!E53 | F58: ='SUN REALTY ATMOS-CALC'!F53
A60: SUN REALTY FOOTPRINT | B60: ='FOOTPRINT- CALCULATION'!B31 | D60: ='FOOTPRINT- CALCULATION'!D31 | E60: ='FOOTPRINT- CALCULATION'!E31 | F60: =D60+E60
A62: SUN REALTY - SUN PARK WEST | B62: =+'SUN PARK WEST'!B29 | D62: =+'SUN PARK WEST'!D29 | E62: =+'SUN PARK WEST'!E29 | F62: =D62+E62
A64: SUN REALTY - SUN SILVER SPRING | B64: =+'SUN SILVER SPRING'!B26 | D64: =+'SUN SILVER SPRING'!D26 | E64: =+'SUN SILVER SPRING'!E26 | F64: =D64+E64
A66: TOTAL | B66: =+B56+B58+B60+B62+B64 | D66: =+D56+D58+D60+D62+D64 | E66: =+E56+E58+E60+E62+E64 | F66: =+F56+F58+F60+F62+F64
A68: INPUT TAX CREDIT FOR THE MONTH OF AUG-26
A70: PARTICULARS | B70: CGST | C70: SGST | D70: IGST
A72: Opening Balance | B72: =+'SUN REALTY-CALC'!B61 | C72: =B72 | D72: 0
A73: Add : ITC FOR THE AUG-26 | B73: =+'SUN REALTY-CALC'!B62 | C73: =+B73 | D73: =+'SUN REALTY-CALC'!D62
A74: Add : ITC of Backdated entries in month of Decil 2022 which are also reflected in GSTR2B of same month | B74: ='SUN REALTY-CALC'!B64 | C74: =B74
A75: Add : ITC of RCM of AUG-26 | B75: ='SUN REALTY-CALC'!B63 | C75: =+B75 | D75: ='SUN REALTY-CALC'!D63
A76: Add : ITC of Common Office | B76: 0 | C76: 0 | D76: ='SUN REALTY-CALC'!D65
A77: ='SUN REALTY-CALC'!A66 | B77: ='SUN REALTY-CALC'!B66 | C77: ='SUN REALTY-CALC'!C66
A78: ='SUN REALTY-CALC'!A67 | B78: ='SUN REALTY-CALC'!B67 | C78: ='SUN REALTY-CALC'!C67
A79: Less: ITC wrongly availed of Sun Realty Atmosphere | B79: 0 | C79: =B79
A80: Add:ITC of Bills which are in GSTR-2B but not in Books (Dec) | B80: ='SUN REALTY-CALC'!B68 | C80: =B80 | D80: ='SUN REALTY-CALC'!D68
A81: Add:ITC of Bills which are in GSTR-2B but not in Books (Dec) | B81: ='SUN REALTY-CALC'!B69 | C81: =B81
A82: Less: Praportionate Reversal of ITC of Sun Realty Office (Atmosphere Portion) | B82: 0 | C82: =B82
A83: Less: Praportionate Reversal of ITC of Sun Realty Gravitas due to BU in the ration of sold Unsold | C83: =+B83
A84: Total CENVAT available | B84: =SUM(B72:B83) | C84: =SUM(C72:C83) | D84: =SUM(D72:D83)
A85: Less : ITC OF IGST Utilized for AUG-26 | B85: =+'SUN REALTY-CALC'!B82 | C85: =B85 | D85: =SUM(B85:C85)
A86: Less : ITC Utilised FOR the AUG-26 | B86: ='SUN REALTY-CALC'!B74 | C86: =+B86 | D86: 0
A87: Less. ITC Revesal for Gravitas as per Rule 42 & 43 ( Ineligible ITC 53.5448%) | B87: =-'SUN REALTY-CALC'!B102 | C87: =-'SUN REALTY-CALC'!C102 | D87: =-'SUN REALTY-CALC'!D102
A88: Less. Common Credit Of Corporate Office To Be C/F upto March'23 | B88: =-B76 | C88: =-C76
A89: Closing Balance | B89: =SUM(B84:B88)-B85 | C89: =SUM(C84:C88)-C85 | D89: =SUM(D84:D87)
A91: INELIGIBLE CREDIT FOR THE MONTH OF AUG-26 | G91: cgst/sgst | H91: igst
F92: RCM OF ALL PROJECTS | G92: =+'SUN REALTY-CALC'!D55+'SUN REALTY ATMOS-CALC'!D53+'FOOTPRINT- CALCULATION'!D31+'SUN PARK WEST'!D29+'SUN SILVER SPRING'!D26 | H92: 0
A93: PARTICULARS | B93: CGST | C93: SGST | D93: IGST | F93: gravitas | G93: =+'SUN REALTY-CALC'!B62 | H93: =+D73+D77
F94: atmoshphere | G94: =+'SUN REALTY ATMOS-CALC'!B59 | H94: =+'SUN REALTY ATMOS-CALC'!D62
A95: ITC FOR THE AUG-26 Including RCM ( Atmoshphere ,Footprint & SUN PARK WEST) | B95: =+'SUN REALTY ATMOS-CALC'!B62+'FOOTPRINT- CALCULATION'!B40+'SUN PARK WEST'!B40+'SUN SILVER SPRING'!B37 | C95: =B95 | D95: ='SUN REALTY ATMOS-CALC'!D59 | F95: footprint | G95: =+'FOOTPRINT- CALCULATION'!B37 | H95: =+'FOOTPRINT- CALCULATION'!D40
A96: Total ineligible CENVAYT | B96: =B95 | C96: =SUM(C95:C95) | D96: =SUM(D95:D95) | F96: sun park west | G96: =+'SUN PARK WEST'!B36+'SUN PARK WEST'!B37 | H96: =+'SUN PARK WEST'!$D$40
A97: TOTAL | F97: sun silver spring | G97: =+'SUN SILVER SPRING'!B33+'SUN SILVER SPRING'!B34 | H97: =+'SUN SILVER SPRING'!D33+'SUN SILVER SPRING'!D34
F98: TOTAL | G98: =SUM(G92:G97) | H98: =SUM(H93:H96)
H99: =+H92
A100: GST Payable for the month of AUG-26 | F100: NET ITC AVAILABLE | G100: =+'SUN REALTY-CALC'!B101 | H100: =+'SUN REALTY-CALC'!D101
F101: reversal | G101: =+G98-G100 | H101: =+H98-H100
A102: PARTICULARS | B102: CGST | C102: SGST | D102: TOTAL
A104: =+A8 | B104: =SUM(F8:F14) | C104: =SUM(G8:G14) | D104: =SUM(B104:C104)-1
A105: LESS.: CENVAT CREDIT UTILIZED | B105: =+'SUN REALTY-CALC'!B82 | C105: =+B105 | D105: =SUM(B105:C105)
A106: LESS.: CENVAT CREDIT UTILIZED | B106: =+'SUN REALTY-CALC'!B83 | C106: =+B106 | D106: =SUM(B106:C106)
A107: TOTAL PAYABLE FOR RESIDENTIAL | B107: =SUM(B104:B106) | C107: =SUM(C104:C106) | D107: =SUM(D104:D106)
A109: SUN REALTY ATMOSPHERE | B109: =SUM(F16:F20) | C109: =SUM(G16:G20) | D109: =B109+C109
A111: SUN REALTY FOOTPRINT | B111: =SUM(F23:F25) | C111: =SUM(G23:G25) | D111: =B111+C111+1
A113: SUN REALTY SUN PARK WEST | B113: =SUM(F28:F30) | C113: =SUM(G28:G30) | D113: =+C113+B113+1
A115: SUN REALTY -SUN SILVER SPRINGS | B115: =SUM(F32:F33) | C115: =SUM(G32:G33) | D115: =+C115+B115-1
A117: GST Paid on RENT Income | B117: =+F50 | C117: =+B117 | D117: =+C117+B117
A119: GST UNDER RCM
A120: SUN GRAVITAS | B120: =D56 | C120: =B120 | D120: =+B120+C120
A121: SUN REALTY ATMOSPHERE | B121: =D58 | C121: =B121 | D121: =+B121+C121
A122: SUN REALTY FOOTPRINT | B122: ='FOOTPRINT- CALCULATION'!D31 | C122: =B122 | D122: =B122+C122-1
A123: SUN REALTY - SUN PARK WEST | B123: =+D62 | C123: =+E62 | D123: =+C123+B123
A124: SUN REALTY - SUN SILVER SPRING | B124: =+D64 | C124: =+E64 | D124: =+C124+B124
A125: Late Fees | B125: 0 | C125: 0 | D125: =B125+C125
A126: Interest | B126: =+F168 | C126: =+B126 | D126: =B126+C126
A127: GST Payable | B127: =SUM(B107:B126) | C127: =SUM(C107:C126) | D127: =SUM(D107:D126)
A128: GST LATE FEES | B128: 0 | C128: 0 | D128: =+B128+C128
A129: Net GST Payable | B129: =+B127+B128 | C129: =B129 | D129: =B129+C129
A132: Summary of Payment Project Wise
A133: Project Gravitas | B133: CGST | C133: SGST | D133: TOTAL
A134: Regular | B134: =+B107 | C134: =+C107 | D134: =+D107+1
...

Sheet ENTRIES-SUN REALTY
A2: MONTHLY ENTRIES FOR M/s. SUN REALTY-GRAVITAS
A3: 46265
A5: Sr. No. | B5: Date | C5: Particulars | D5: Amt(Rs.) | E5: Amt(Rs.)
D6: Dr. | E6: Cr.
A8: 1 | B8: 46265 | C8: CGST on collection A/c Dr | D8: =+'FINAL CALC'!B104
C9: SGST on collection A/c Dr | D9: =+D8
C10: To CGST payable A/c | E10: =+D8
C11: To SGST payable A/c | E11: =+D9
C12: (Being gst collected transferred to gst payable
C13: for the month of Apr-26)
A15: 2 | B15: =+B8 | C15: CGST Receivable RCM A/c Dr | D15: ='SUN REALTY-CALC'!D55
C16: SGST Receivable RCM A/c Dr | D16: ='SUN REALTY-CALC'!E55
C17: To CGST payable A/c | E17: =+D15
C18: To SGST payable A/c | E18: =+D16
C19: (Being GST payable under RCM transferred to
C20: GST payabel A/C for the month of Apr-26)
A22: 3 | B22: =+B15 | C22: CGST Receivable A/c Dr | D22: ='FINAL CALC'!B120
C23: SGST Receivable A/c Dr | D23: ='FINAL CALC'!C120
C24: To CGST Receivable RCM A/c | E24: =D22
C25: To SGST Receivable RCM A/c | E25: =D23
C26: (Being Credit of RCM transferred to Receivable
C27: A/c for the month of Apr-26)
A29: 4 | B29: =+B22 | C29: CGST payable A/c Dr. | D29: =-'FINAL CALC'!B106
C30: SGST payable A/c Dr. | D30: =-'FINAL CALC'!C106
C31: To CGST Receivable A/c | E31: =-'FINAL CALC'!B86
C32: To SGST Receivable A/c | E32: =+E31
C33: To IGST Receivable A/c | E33: =-'FINAL CALC'!D85
C34: (Being Set off taken for the month of Apr-26)
A36: 5 | B36: 46285 | C36: CGST payable A/c Dr. | D36: =+'FINAL CALC'!B107+'FINAL CALC'!B120
C37: SGST payable A/c Dr. | D37: =+D36
C38: GST Interest A/C. Dr. | D38: =+'FINAL CALC'!D126
C39: GST late fees A/C. Dr. | D39: =+'FINAL CALC'!D125
C40: To BANK. A/c | E40: =+SUM(D36:D39)
C41: (Being amount of GST PAID)
A44: 6 | B44: =+B29 | C44: GST Exp A/c Dr | D44: =-'FINAL CALC'!B87-'FINAL CALC'!C87-'FINAL CALC'!D87
C45: TO CGST Receivable A/c | E45: =-'FINAL CALC'!B87
C46: TO SGST Receivable A/c | E46: =-'FINAL CALC'!C87
C47: TO IGST Receivable A/c | E47: =-'FINAL CALC'!D87
C48: ( Being Credit is reversed under Rule 42 & 43 ineligible credit )
A50: 7 | B50: =+B44 | C50: CGST Receivable A/c Dr | D50: ='SUN REALTY-CALC'!B66
C51: SGST Receivable A/c Dr | D51: ='SUN REALTY-CALC'!C66
C52: IGST Receivable A/c Dr | D52: ='FINAL CALC'!D77
C53: To Provisional CGST Receivable A/c | E53: =D50
C54: To Provisional SGST Receivable A/c | E54: =D51
C55: To Provisional IGST Receivable A/c | E55: =D52
C56: (Being ITC of previous month ,reflacted in Current month ,
C57: GSTR-2B availed)
A59: 8 | B59: =B50 | C59: Provisional CGST Receivable A/c | D59: =+E70 | E59: 0
C60: Provisional SGST Receivable A/c | D60: =+D59
C61: To CGST Receivable A/c | E61: =D59
C62: To SGST Receivable A/c | E62: =D60
C63: (Being Invoices which are not reflacted in GSTR-2B, transffered
C64: to Provisional A/c.(HET Enterprise)
A67: Ref.1
B68: DATE | C68: PARTICULARS | D68: VOUCHER NO. | E68: CGST/SGST AMOUNT
E70: =SUM(E69:E69)

Sheet Books-sun realty-JULY'22
A1: SUN REALTY
A2: CGST Receivable
A3: Ledger Account
A6: 1-Jul-2022 to 31-Jul-2022
A7: Date | C7: Vch Type | D7: Vch No. | E7: Debit | F7: Credit
A8: 44749 | B8: Aasha Entrerprise | C8: Purchase | D8: 384 | E8: 14345
A9: 44753 | B9: Aasha Entrerprise | C9: Purchase | D9: 399 | E9: 1623
A10: 44755 | B10: Aasha Entrerprise | C10: Purchase | D10: 415 | E10: 3867
A11: 44749 | B11: Bhumi Corporation | C11: Purchase | D11: 2509/2022-23 | E11: 13651
A12: 44743 | B12: Blazenet Limited | C12: Journal | D12: 220 | E12: 844
A13: 44771 | B13: Compu Brain | C13: Journal | D13: 382 | E13: 423
A14: 44771 | B14: Compu Brain | C14: Journal | D14: 383 | E14: 423
A15: 44771 | B15: Compu Brain | C15: Journal | D15: 384 | E15: 2200
A16: 44771 | B16: Compu Brain | C16: Journal | D16: 385 | E16: 2429
A17: 44771 | B17: Compu Brain | C17: Journal | D17: 386 | E17: 2053
A18: 44743 | B18: Cosmos Manpower Pvt Ltd | C18: Journal | D18: 221 | E18: 2970
A19: 44748 | B19: Delta Enterprise | C19: Purchase | D19: DE/41/22-23 | E19: 13275
A20: 44743 | B20: Dhruv Enterprise | C20: Journal | D20: 227 | E20: 4298 | F20: common credit
A21: 44754 | B21: Drishti Electricals | C21: Purchase | D21: GST/1315/22-23 | E21: 12238
A22: 44767 | B22: Drishti Electricals | C22: Purchase | D22: GST/1467/22-23 | E22: 669 | F22: TRANS TO PROV REC
A23: 44770 | B23: Drishti Electricals | C23: Purchase | D23: GST/1522/22-23 | E23: 450
A24: 44748 | B24: Future Sales Private Limited | C24: Purchase | D24: 2541/ 22-23 | E24: 1022
A25: 44751 | B25: Future Sales Private Limited | C25: Purchase | D25: 2627/ 22-23 | E25: 1238
A26: 44762 | B26: Future Sales Private Limited | C26: Purchase | D26: 2838/ 22-23 | E26: 1991
A27: 44747 | B27: Future Solutions - New Office | C27: Journal | D27: 232 | E27: 6737
A28: 44747 | B28: Future Solutions - New Office | C28: Journal | D28: 233 | E28: 28326
A29: 44743 | B29: Gayatri Sales Corporation | C29: Purchase | D29: T/ 507 | E29: 114
A30: 44745 | B30: Gayatri Sales Corporation | C30: Purchase | D30: T/ 523 | E30: 4415
A31: 44747 | B31: Gayatri Sales Corporation | C31: Purchase | D31: T/ 531 | E31: 953
A32: 44747 | B32: Gayatri Sales Corporation | C32: Purchase | D32: T/ 535 | E32: 3177
A33: 44747 | B33: Gayatri Sales Corporation | C33: Purchase | D33: T/ 536 | E33: 293
A34: 44747 | B34: Gayatri Sales Corporation | C34: Purchase | D34: T/ 537 | E34: 2126
... A46: 44767 | B46: Hare Krushna Concrete Solution | C46: Purchase | D46: HKL/2223/ 1209 | E46: 866
A47: 44743 | B47: Harshadkumar Govindbhai Patel | C47: Journal | D47: 210 | E47: 7814 | F47: Office Rent
A48: 44743 | B48: Ido Design Solutions | C48: Journal | D48: 218 | E48: 7200
A49: 44743 | B49: Infinity Business Solutions | C49: Journal | D49: 229 | E49: 1440 | F49: TRANS TO PROV REC
A50: 44743 | B50: Khushboo Xerox | C50: Journal | D50: 228 | E50: 1660
A51: 44755 | B51: Khushboo Xerox | C51: Journal | D51: 275 | E51: 4500 | F51: TRANS TO PROV REC
A52: 44751 | B52: M.R. Hardware | C52: Purchase | D52: MR/22-23/0039 | E52: 149
A53: 44764 | B53: M.R. Hardware | C53: Purchase | D53: MR/22-23/0044 | E53: 901
A54: 44743 | B54: Naimish N. Shah & Co. - Bills | C54: Journal | D54: 223 | E54: 1350
A55: 44744 | B55: Nice Ceramics | C55: Purchase | D55: 462 | E55: 479 | F55: TRANS TO PROV REC
A56: 44746 | B56: Nice Ceramics | C56: Purchase | D56: 469 | E56: 1350 | F56: TRANS TO PROV REC
A57: 44750 | B57: Nice Ceramics | C57: Purchase | D57: 488 | E57: 7208 | F57: TRANS TO PROV REC
A58: 44756 | B58: Nice Ceramics | C58: Purchase | D58: 506 | E58: 5508 | F58: TRANS TO PROV REC
A59: 44768 | B59: Nice Ceramics | C59: Purchase | D59: 561 | E59: 1371 | F59: TRANS TO PROV REC
A60: 44770 | B60: Nice Ceramics | C60: Purchase | D60: 570 | E60: 3608 | F60: TRANS TO PROV REC
A61: 44771 | B61: Nice Ceramics | C61: Purchase | D61: 574 | E61: 45 | F61: TRANS TO PROV REC
A62: 44743 | B62: Patel Sanjaykumar G. | C62: Journal | D62: 212 | E62: 7814 | F62: Office Rent
A63: 44746 | B63: Radiant Industries | C63: Purchase | D63: GST-0695 /22-23 | E63: 1716
A64: 44751 | B64: Radiant Industries | C64: Purchase | D64: GST-0727 /22-23 | E64: 1144
A65: 44754 | B65: Radiant Industries | C65: Purchase | D65: GST-0737 /22-23 | E65: 1144
A66: 44770 | B66: Radiant Industries | C66: Purchase | D66: GST-0838 /22-23 | E66: 2288
A67: 44763 | B67: Savaria Marble and Granite | C67: Purchase | D67: 34 | E67: 1540
A68: 44770 | B68: Savaria Marble and Granite | C68: Purchase | D68: 41 | E68: 1084
A69: 44748 | B69: Shiv Electromac | C69: Purchase | D69: 043/2022-2023 | E69: 14176 | F69: TRANS TO PROV REC
A70: 44755 | B70: Shiv Electromac | C70: Purchase | D70: 044/2022-2023 | E70: 17040 | F70: TRANS TO PROV REC
A71: 44746 | B71: Shree Ram Steel Stores | C71: Purchase | D71: 0415 | E71: 349
A72: 44750 | B72: Shree Ram Steel Stores | C72: Purchase | D72: 0436 | E72: 456
A73: 44756 | B73: Shree Ram Steel Stores | C73: Purchase | D73: 0455 | E73: 2175
A74: 44770 | B74: Shree Ram Steel Stores | C74: Purchase | D74: 0500 | E74: 4731
A75: 44751 | B75: Surya Agency | C75: Purchase | D75: 1007 | E75: 332
A76: 44752 | B76: Surya Agency | C76: Purchase | D76: 1020 | E76: 2217
A77: 44753 | B77: Surya Agency | C77: Purchase | D77: 1027 | E77: 1451
A78: 44743 | B78: Surya Sales Corporartion | C78: Purchase | D78: 12 | E78: 19068
A79: 44743 | B79: Vimal Ranachhodbhai Patel | C79: Journal | D79: 214 | E79: 7814 | F79: Office Rent
A80: 44743 | B80: Vishal Ranachhodbhai Patel | C80: Journal | D80: 216 | E80: 7814 | F80: Office Rent

Sheet Provisional Creditor -JULY'22
B1: from provisional Closing balance | F1: COMMON CREDIT
B2: Credit avail
B3: Bill of footprint
B4: bill of Atmosphere
B5: Not to avail
A6: NO COLOR | B6: CREDIT TO BE AVAIL ON PROVISIONAL BASIS
A7: Goods and Services Tax - GSTR-2B
A10: Taxable inward supplies received from registered persons
A11: GSTIN of supplier | B11: Trade/Legal name | C11: Invoice Details | G11: Place of supply | H11: Supply Attract Reverse Charge | I11: Rate(%) | J11: Taxable Value (₹) | K11: Tax Amount | O11: GSTR-1/IFF/GSTR-5 Period | P11: GSTR-1/IFF/GSTR-5 Filing Date | Q11: ITC Availability | R11: Reason | S11: Applicable % of Tax Rate | T11: Source | U11: IRN | V11: IRN Date
C12: Invoice number | D12: Invoice type | E12: Invoice Date | F12: Invoice Value(₹) | K12: Integrated Tax(₹) | L12: Central Tax(₹) | M12: State/UT Tax(₹) | N12: Cess(₹)
K13: =SUBTOTAL(9,K14:K103) | L13: =SUBTOTAL(9,L14:L103) | M13: =SUBTOTAL(9,M14:M103)
A14: 24AAOFA5311J1ZL | B14: AASHA ENTERPRISE | C14: 384 | D14: Regular | E14: 07/07/2022 | F14: 188083 | G14: Gujarat | H14: No | I14: 18 | J14: 159392 | K14: 0 | L14: 14345.28 | M14: 14345.28 | N14: 0 | O14: Jul'22 | P14: 05/08/2022 | Q14: Yes | S14: 100%
A15: 24AAOFA5311J1ZL | B15: AASHA ENTERPRISE | C15: 399 | D15: Regular | E15: 11/07/2022 | F15: 21276 | G15: Gujarat | H15: No | I15: 18 | J15: 18030.4 | K15: 0 | L15: 1622.74 | M15: 1622.74 | N15: 0 | O15: Jul'22 | P15: 05/08/2022 | Q15: Yes | S15: 100%
A16: 24AAOFA5311J1ZL | B16: AASHA ENTERPRISE | C16: 415 | D16: Regular | E16: 13/07/2022 | F16: 50706 | G16: Gujarat | H16: No | I16: 18 | J16: 42971.2 | K16: 0 | L16: 3867.41 | M16: 3867.41 | N16: 0 | O16: Jul'22 | P16: 05/08/2022 | Q16: Yes | S16: 100%
A17: 24ABIFA4856B1ZQ | B17: ALIGN ANIMATION LLP | C17: ALIGN/20 | D17: Regular | E17: 19/07/2022 | F17: 100890 | G17: Gujarat | H17: No | I17: 18 | J17: 85500 | K17: 0 | L17: 7695 | M17: 7695 | N17: 0 | O17: Jul'22 | P17: 04/08/2022 | Q17: Yes | S17: 100%
A18: 24AAACB2894G1ZT | B18: BHARTI AIRTEL LTD. | C18: HT2324I000347888 | D18: Regular | E18: 09/07/2022 | F18: 1263.25 | G18: Gujarat | H18: No | I18: 18 | J18: 1070.53 | K18: 0 | L18: 96.36 | M18: 96.36 | N18: 0 | O18: Jul'22 | P18: 10/08/2022 | Q18: Yes | S18: 100% | T18: E-Invoice | U18: 5a6a558a5c936c6882a4fdc05d1c91eeee37a0d431bf9c3a3ea084228f31c237 | V18: 09/07/2022
A19: 24AAGFB1937P1Z8 | B19: BHUMI CORPORATION | C19: 2509/2022-23 | D19: Regular | E19: 07/07/2022 | F19: 178987 | G19: Gujarat | H19: No | I19: 18 | J19: 151684 | K19: 0 | L19: 13652 | M19: 13652 | N19: 0 | O19: Jul'22 | P19: 10/08/2022 | Q19: Yes | S19: 100%
A20: 24AAACB8732B1Z6 | B20: BLAZENET LIMITED | C20: AH/2223/07/0262 | D20: Regular | E20: 01/07/2022 | F20: 11063 | G20: Gujarat | H20: No | I20: 18 | J20: 9375 | K20: 0 | L20: 843.75 | M20: 843.75 | N20: 0 | O20: Jul'22 | P20: 10/08/2022 | Q20: Yes | S20: 100% | T20: E-Invoice | U20: 37b76ab40a6f1fda18576fa4305cf063cdbeb4127e17975c1838e0440958b1d6 | V20: 29/07/2022
A21: 24AAGFC5091H1ZJ | B21: COMPUBRAIN | C21: 513 | D21: Regular | E21: 29/07/2022 | F21: 5546 | G21: Gujarat | H21: No | I21: 18 | J21: 4700 | K21: 0 | L21: 423 | M21: 423 | N21: 0 | O21: Jul'22 | P21: 13/08/2022 | Q21: Yes | S21: 100%
A22: 24AAGFC5091H1ZJ | B22: COMPUBRAIN | C22: 515 | D22: Regular | E22: 29/07/2022 | F22: 5546 | G22: Gujarat | H22: No | I22: 18 | J22: 4700 | K22: 0 | L22: 423 | M22: 423 | N22: 0 | O22: Jul'22 | P22: 13/08/2022 | Q22: Yes | S22: 100%
A23: 24AAGFC5091H1ZJ | B23: COMPUBRAIN | C23: 517 | D23: Regular | E23: 29/07/2022 | F23: 43989 | G23: Gujarat | H23: No | I23: 18 | J23: 37279 | K23: 0 | L23: 3355.11 | M23: 3355.11 | N23: 0 | O23: Jul'22 | P23: 13/08/2022 | Q23: Yes | S23: 100%
A24: 24AAGFC5091H1ZJ | B24: COMPUBRAIN | C24: 519 | D24: Regular | E24: 29/07/2022 | F24: 28851 | G24: Gujarat | H24: No | I24: 18 | J24: 24450 | K24: 0 | L24: 2200.5 | M24: 2200.5 | N24: 0 | O24: Jul'22 | P24: 13/08/2022 | Q24: Yes | S24: 100%
A25: 24AAGFC5091H1ZJ | B25: COMPUBRAIN | C25: 521 | D25: Regular | E25: 29/07/2022 | F25: 28902 | G25: Gujarat | H25: No | I25: 18 | J25: 24493 | K25: 0 | L25: 2204.37 | M25: 2204.37 | N25: 0 | O25: Jul'22 | P25: 13/08/2022 | Q25: Yes | S25: 100%
A26: 24AAGFC5091H1ZJ | B26: COMPUBRAIN | C26: 523 | D26: Regular | E26: 29/07/2022 | F26: 23600 | G26: Gujarat | H26: No | I26: 18 | J26: 20000 | K26: 0 | L26: 1800 | M26: 1800 | N26: 0 | O26: Jul'22 | P26: 13/08/2022 | Q26: Yes | S26: 100%
A27: 24AAGFC5091H1ZJ | B27: COMPUBRAIN | C27: 525 | D27: Regular | E27: 29/07/2022 | F27: 31854 | G27: Gujarat | H27: No | I27: 18 | J27: 26995 | K27: 0 | L27: 2429.55 | M27: 2429.55 | N27: 0 | O27: Jul'22 | P27: 13/08/2022 | Q27: Yes | S27: 100%
A28: 24AAGFC5091H1ZJ | B28: COMPUBRAIN | C28: 527 | D28: Regular | E28: 29/07/2022 | F28: 26918 | G28: Gujarat | H28: No | I28: 18 | J28: 22812 | K28: 0 | L28: 2053.08 | M28: 2053.08 | N28: 0 | O28: Jul'22 | P28: 13/08/2022 | Q28: Yes | S28: 100%
A29: 24AAECC2564J1ZQ | B29: COSMOS MANPOWER PVT.LTD | C29: 376 | D29: Regular | E29: 01/07/2022 | F29: 38940 | G29: Gujarat | H29: No | I29: 18 | J29: 33000 | K29: 0 | L29: 2970 | M29: 2970 | N29: 0 | O29: Jul'22 | P29: 11/08/2022 | Q29: Yes | S29: 100%
A30: 24ABPPD5269E2ZN | B30: DEE FURNISHINGS | C30: 0917 | D30: Regular | E30: 15/07/2022 | F30: 819 | G30: Gujarat | H30: No | I30: 5 | J30: 780 | K30: 0 | L30: 19.5 | M30: 19.5 | N30: 0 | O30: Jul'22 | P30: 10/08/2022 | Q30: Yes | S30: 100%
A31: 24ATUPV0858Q2ZH | B31: DELTA ENTERPRISE | C31: DE/41/22-23 | D31: Regular | E31: 06/07/2022 | F31: 174050 | G31: Gujarat | H31: No | I31: 18 | J31: 147500 | K31: 0 | L31: 13275 | M31: 13275 | N31: 0 | O31: Jul'22 | P31: 05/08/2022 | Q31: Yes | S31: 100%
A32: 24AAKFD7969H1ZZ | B32: DHRUV ENTERPRISE | C32: DE-22-23-0107 | D32: Regular | E32: 01/07/2022 | F32: 91754 | G32: Gujarat | H32: No | I32: 18 | J32: 77758 | K32: 0 | L32: 6998.22 | M32: 6998.22 | N32: 0 | O32: Jul'22 | P32: 13/08/2022 | Q32: Yes | S32: 100%
... A35: 24AGWPP5800H2Z3 | B35: DRISHTI ELECTRICALS | C35: GST/1522/22-23 | D35: Regular | E35: 28/07/2022 | F35: 5900 | G35: Gujarat | H35: No | I35: 18 | J35: 5000 | K35: 0 | L35: 450 | M35: 450 | N35: 0 | O35: Jul'22 | P35: 09/08/2022 | Q35: Yes | S35: 100%
A36: 06AABCF5150G1ZZ | B36: FACEBOOK INDIA ONLINE SERVICES PRIVATE LIMITED | C36: ADS190-102034829 | D36: Regular | E36: 01/07/2022 | F36: 2.55 | G36: Gujarat | H36: No | I36: 18 | J36: 2.16 | K36: 0.39 | L36: 0 | M36: 0 | N36: 0 | O36: Jul'22 | P36: 10/08/2022 | Q36: Yes | S36: 100% | T36: E-Invoice | U36: 9e48a8b5d26c11e91f96fe60422dde42c23b1652cb7d8f407a09f225ad595a1d | V36: 02/07/2022
A37: 06AABCF5150G1ZZ | B37: FACEBOOK INDIA ONLINE SERVICES PRIVATE LIMITED | C37: ADS190-102036337 | D37: Regular | E37: 02/07/2022 | F37: 1032.21 | G37: Gujarat | H37: No | I37: 18 | J37: 874.75 | K37: 157.46 | L37: 0 | M37: 0 | N37: 0 | O37: Jul'22 | P37: 10/08/2022 | Q37: Yes | S37: 100% | T37: E-Invoice | U37: 6a913141fd697bc2ef7a3c02b7008a9adc3f8c92fd64d284cef4e6827a93608f | V37: 03/07/2022
A38: 06AABCF5150G1ZZ | B38: FACEBOOK INDIA ONLINE SERVICES PRIVATE LIMITED | C38: ADS190-102037672 | D38: Regular | E38: 03/07/2022 | F38: 917.17 | G38: Gujarat | H38: No | I38: 18 | J38: 777.26 | K38: 139.91 | L38: 0 | M38: 0 | N38: 0 | O38: Jul'22 | P38: 10/08/2022 | Q38: Yes | S38: 100% | T38: E-Invoice | U38: 9ef7b367a3a4a32012fd1813acafc32feda9059156176c0329ea7842486e6277 | V38: 04/07/2022
A39: 06AABCF5150G1ZZ | B39: FACEBOOK INDIA ONLINE SERVICES PRIVATE LIMITED | C39: ADS190-102039166 | D39: Regular | E39: 04/07/2022 | F39: 592.81 | G39: Gujarat | H39: No | I39: 18 | J39: 502.38 | K39: 90.43 | L39: 0 | M39: 0 | N39: 0 | O39: Jul'22 | P39: 10/08/2022 | Q39: Yes | S39: 100% | T39: E-Invoice | U39: f33a92b1a19b2a682d33e83602162df932a156cb0d60054fba8f618cf8fcf291 | V39: 05/07/2022
A40: 06AABCF5150G1ZZ | B40: FACEBOOK INDIA ONLINE SERVICES PRIVATE LIMITED | C40: ADS190-102040722 | D40: Regular | E40: 05/07/2022 | F40: 0.63 | G40: Gujarat | H40: No | I40: 18 | J40: 0.53 | K40: 0.1 | L40: 0 | M40: 0 | N40: 0 | O40: Jul'22 | P40: 10/08/2022 | Q40: Yes | S40: 100% | T40: E-Invoice | U40: f9bec7f67fbb13c733a3a1ba53bfbe2f024df01121d2b89ef48c96d796de85a6 | V40: 06/07/2022
A41: 24AABCF3670M1ZJ | B41: FUTURE SALES PRIVATE LIMITED | C41: 2541/22-23 | D41: Regular | E41: 06/07/2022 | F41: 13396 | G41: Gujarat | H41: No | I41: 18 | J41: 11352.4 | K41: 0 | L41: 1021.72 | M41: 1021.72 | N41: 0 | O41: Jul'22 | P41: 08/08/2022 | Q41: Yes | S41: 100% | T41: E-Invoice | U41: f24637692bf265d4728f7967eac22a3aabfee7df213265dcfe318c141167a805 | V41: 06/07/2022
A42: 24AABCF3670M1ZJ | B42: FUTURE SALES PRIVATE LIMITED | C42: 2627/22-23 | D42: Regular | E42: 09/07/2022 | F42: 16226 | G42: Gujarat | H42: No | I42: 18 | J42: 13750.8 | K42: 0 | L42: 1237.57 | M42: 1237.57 | N42: 0 | O42: Jul'22 | P42: 08/08/2022 | Q42: Yes | S42: 100% | T42: E-Invoice | U42: a07c850d05dda81c7efe7f22e5c2c771d3656050a44098112e9941b0a99c7ad1 | V42: 09/07/2022
A43: 24AABCF3670M1ZJ | B43: FUTURE SALES PRIVATE LIMITED | C43: 2838/22-23 | D43: Regular | E43: 20/07/2022 | F43: 26104 | G43: Gujarat | H43: No | I43: 18 | J43: 22122 | K43: 0 | L43: 1990.98 | M43: 1990.98 | N43: 0 | O43: Jul'22 | P43: 08/08/2022 | Q43: Yes | S43: 100% | T43: E-Invoice | U43: f6bb2a2f8d0a93b4a1b2a792c9114ad38adb790fec63e5614af96cfb4d8bf514 | V43: 20/07/2022
A44: 24AACFF3888R1ZQ | B44: FUTURE SOLUTIONS | C44: OT/22-23/114 | D44: Regular | E44: 05/07/2022 | F44: 61600 | G44: Gujarat | H44: No | I44: 28 | J44: 48125 | K44: 0 | L44: 6737.5 | M44: 6737.5 | N44: 0 | O44: Jul'22 | P44: 09/08/2022 | Q44: Yes | S44: 100%
A45: 24AACFF3888R1ZQ | B45: FUTURE SOLUTIONS | C45: PR/DN/22-23/86 | D45: Regular | E45: 05/07/2022 | F45: 258985 | G45: Gujarat | H45: No | I45: 28 | J45: 202332 | K45: 0 | L45: 28326.48 | M45: 28326.48 | N45: 0 | O45: Jul'22 | P45: 09/08/2022 | Q45: Yes | S45: 100%
A46: 24AADFG8128J1ZD | B46: GAYATRI SALES CORPORATION | C46: T/507 | D46: Regular | E46: 01/07/2022 | F46: 4800 | G46: Gujarat | H46: No | I46: 5 | J46: 4571.42 | K46: 0 | L46: 114.29 | M46: 114.29 | N46: 0 | O46: Jul'22 | P46: 10/08/2022 | Q46: Yes | S46: 100%
A47: 24AADFG8128J1ZD | B47: GAYATRI SALES CORPORATION | C47: T/523 | D47: Regular | E47: 03/07/2022 | F47: 58830 | G47: Gujarat | H47: No | I47: 5 | J47: 952.38 | K47: 0 | L47: 23.81 | M47: 23.81 | N47: 0 | O47: Jul'22 | P47: 10/08/2022 | Q47: Yes | S47: 100%
A48: 24AADFG8128J1ZD | B48: GAYATRI SALES CORPORATION | C48: T/523 | D48: Regular | E48: 03/07/2022 | F48: 58830 | G48: Gujarat | H48: No | I48: 18 | J48: 48796.62 | K48: 0 | L48: 4391.7 | M48: 4391.7 | N48: 0 | O48: Jul'22 | P48: 10/08/2022 | Q48: Yes | S48: 100%
A49: 24AADFG8128J1ZD | B49: GAYATRI SALES CORPORATION | C49: T/531 | D49: Regular | E49: 05/07/2022 | F49: 12740 | G49: Gujarat | H49: No | I49: 18 | J49: 10584.74 | K49: 0 | L49: 952.63 | M49: 952.63 | N49: 0 | O49: Jul'22 | P49: 10/08/2022 | Q49: Yes | S49: 100%
A50: 24AADFG8128J1ZD | B50: GAYATRI SALES CORPORATION | C50: T/535 | D50: Regular | E50: 05/07/2022 | F50: 41900 | G50: Gujarat | H50: No | I50: 18 | J50: 35296.62 | K50: 0 | L50: 3176.7 | M50: 3176.7 | N50: 0 | O50: Jul'22 | P50: 10/08/2022 | Q50: Yes | S50: 100%
A51: 24AADFG8128J1ZD | B51: GAYATRI SALES CORPORATION | C51: T/536 | D51: Regular | E51: 05/07/2022 | F51: 3840 | G51: Gujarat | H51: No | I51: 18 | J51: 3254.24 | K51: 0 | L51: 292.88 | M51: 292.88 | N51: 0 | O51: Jul'22 | P51: 10/08/2022 | Q51: Yes | S51: 100%
A52: 24AADFG8128J1ZD | B52: GAYATRI SALES CORPORATION | C52: T/537 | D52: Regular | E52: 05/07/2022 | F52: 28120 | G52: Gujarat | H52: No | I52: 18 | J52: 23618.64 | K52: 0 | L52: 2125.68 | M52: 2125.68 | N52: 0 | O52: Jul'22 | P52: 10/08/2022 | Q52: Yes | S52: 100%
A53: 24AADFG8128J1ZD | B53: GAYATRI SALES CORPORATION | C53: T/557 | D53: Regular | E53: 09/07/2022 | F53: 39350 | G53: Gujarat | H53: No | I53: 18 | J53: 33135.6 | K53: 0 | L53: 2982.2 | M53: 2982.2 | N53: 0 | O53: Jul'22 | P53: 10/08/2022 | Q53: Yes | S53: 100%
A54: 24AADFG8128J1ZD | B54: GAYATRI SALES CORPORATION | C54: T/558 | D54: Regular | E54: 09/07/2022 | F54: 7400 | G54: Gujarat | H54: No | I54: 5 | J54: 571.42 | K54: 0 | L54: 14.29 | M54: 14.29 | N54: 0 | O54: Jul'22 | P54: 10/08/2022 | Q54: Yes | S54: 100%
A55: 24AADFG8128J1ZD | B55: GAYATRI SALES CORPORATION | C55: T/558 | D55: Regular | E55: 09/07/2022 | F55: 7400 | G55: Gujarat | H55: No | I55: 18 | J55: 5762.72 | K55: 0 | L55: 518.64 | M55: 518.64 | N55: 0 | O55: Jul'22 | P55: 10/08/2022 | Q55: Yes | S55: 100%
... A68: 24AAATG1858Q1ZA | B68: GUJARAT ENERGY DEVELOPMENT AGENCY | C68: ER/2022-23/1619 | D68: Regular | E68: 23/06/2022 | F68: 15340 | G68: Gujarat | H68: No | I68: 18 | J68: 13000 | K68: 0 | L68: 1170 | M68: 1170 | N68: 0 | O68: Jun'22 | P68: 12/07/2022 | Q68: Yes | S68: 100%
A69: 24AAJFH1553N1Z7 | B69: HARE KRUSHNA CONCRETE SOLUTIONS | C69: HKL/2223/1209 | D69: Regular | E69: 25/07/2022 | F69: 11355 | G69: Gujarat | H69: No | I69: 18 | J69: 9622.89 | K69: 0 | L69: 866.06 | M69: 866.06 | N69: 0 | O69: Jul'22 | P69: 10/08/2022 | Q69: Yes | S69: 100% | T69: E-Invoice | U69: ce50ed91e8e60efd1fa3b39fa4734a2609bd83869b7de2887eececef5acdb42e | V69: 30/07/2022
A70: 24AADCH8918G1ZJ | B70: Hitech Projects Private Limited | C70: 9JULSALE2223 | D70: Regular | E70: 21/07/2022 | F70: 52659374 | G70: Gujarat | H70: No | I70: 12 | J70: 47017298 | K70: 0 | L70: 2821037.9 | M70: 2821037.9 | N70: 0 | O70: Jul'22 | P70: 10/08/2022 | Q70: Yes | S70: 100%
A71: 24AABFI7353M1Z6 | B71: IDO DESIGN SOLUTIONS | C71: SUN/ABD/722/32 | D71: Regular | E71: 01/07/2022 | F71: 94400 | G71: Gujarat | H71: No | I71: 18 | J71: 80000 | K71: 0 | L71: 7200 | M71: 7200 | N71: 0 | O71: Jul'22 | P71: 09/08/2022 | Q71: Yes | S71: 100%
A72: 24AUHPP7714P1Z0 | B72: KHUSHBOO XEROX | C72: 36 | D72: Regular | E72: 11/04/2022 | F72: 15511 | G72: Gujarat | H72: No | I72: 18 | J72: 13145 | K72: 0 | L72: 1183.05 | M72: 1183.05 | N72: 0 | O72: Jun'22 | P72: 14/07/2022 | Q72: Yes | S72: 100%
A73: 24AUHPP7714P1Z0 | B73: KHUSHBOO XEROX | C73: 86 | D73: Regular | E73: 14/05/2022 | F73: 21766 | G73: Gujarat | H73: No | I73: 18 | J73: 18446 | K73: 0 | L73: 1660.14 | M73: 1660.14 | N73: 0 | O73: Jun'22 | P73: 14/07/2022 | Q73: Yes | S73: 100%
A74: 24BAHPJ8038H2ZN | B74: LOTUS SECURITY & PVT. FORCE | C74: 51 | D74: Regular | E74: 01/06/2022 | F74: 22420 | G74: Gujarat | H74: Yes | I74: 18 | J74: 19000 | K74: 0 | L74: 1710 | M74: 1710 | N74: 0 | O74: Jun'22 | P74: 13/07/2022 | Q74: Yes | S74: 100%
A75: 24BAHPJ8038H2ZN | B75: LOTUS SECURITY & PVT. FORCE | C75: 52 | D75: Regular | E75: 01/06/2022 | F75: 35400 | G75: Gujarat | H75: Yes | I75: 18 | J75: 30000 | K75: 0 | L75: 2700 | M75: 2700 | N75: 0 | O75: Jun'22 | P75: 13/07/2022 | Q75: Yes | S75: 100%
A76: 24ABGFM5709H1ZA | B76: M.R.HARDWARE | C76: MR22-23039 | D76: Regular | E76: 09/07/2022 | F76: 1960 | G76: Gujarat | H76: No | I76: 18 | J76: 1660.8 | K76: 0 | L76: 149.47 | M76: 149.47 | N76: 0 | O76: Jul'22 | P76: 08/08/2022 | Q76: Yes | S76: 100%
A77: 24ABGFM5709H1ZA | B77: M.R.HARDWARE | C77: MR22-23044 | D77: Regular | E77: 22/07/2022 | F77: 11812 | G77: Gujarat | H77: No | I77: 18 | J77: 10010 | K77: 0 | L77: 900.9 | M77: 900.9 | N77: 0 | O77: Jul'22 | P77: 08/08/2022 | Q77: Yes | S77: 100%
A78: 24ABJFM6472E1Z7 | B78: MAMATA AIRWINGS | C78: D00001602 | D78: Regular | E78: 14/07/2022 | F78: 13750 | G78: Gujarat | H78: No | I78: 18 | J78: 230.5 | K78: 0 | L78: 20.75 | M78: 20.75 | N78: 0 | O78: Jul'22 | P78: 09/08/2022 | Q78: Yes | S78: 100%
A79: 24ABJFM6472E1Z7 | B79: MAMATA AIRWINGS | C79: H00000165 | D79: Regular | E79: 05/07/2022 | F79: 32500 | G79: Gujarat | H79: No | I79: 18 | J79: 1978.82 | K79: 0 | L79: 178.09 | M79: 178.09 | N79: 0 | O79: Jul'22 | P79: 09/08/2022 | Q79: Yes | S79: 100%
A80: 24ABJFM6472E1Z7 | B80: MAMATA AIRWINGS | C80: I00000565 | D80: Regular | E80: 22/07/2022 | F80: 341500 | G80: Gujarat | H80: No | I80: 18 | J80: 1771.19 | K80: 0 | L80: 159.41 | M80: 159.41 | N80: 0 | O80: Jul'22 | P80: 09/08/2022 | Q80: Yes | S80: 100%
A81: 24AKYPS8781J1ZZ | B81: NAIMISH N. SHAH & CO. | C81: GST/0421/2022-23 | D81: Regular | E81: 01/07/2022 | F81: 11800 | G81: Gujarat | H81: No | I81: 18 | J81: 10000 | K81: 0 | L81: 900 | M81: 900 | N81: 0 | O81: Jul'22 | P81: 09/08/2022 | Q81: Yes | S81: 100%
... A100: 24BRTPS9096P1ZB | B100: SURYA SALES CORPORATION | C100: 12 | D100: Regular | E100: 01/07/2022 | F100: 250000 | G100: Gujarat | H100: No | I100: 18 | J100: 211864 | K100: 0 | L100: 19067.76 | M100: 19067.76 | N100: 0 | O100: Jul'22 | P100: 09/08/2022 | Q100: Yes | S100: 100%
A101: 24AAACB2100P1Z3 | B101: Vodafone Idea Limited | C101: GJI0607204555649 | D101: Regular | E101: 22/07/2022 | F101: 1571.76 | G101: Gujarat | H101: No | I101: 18 | J101: 1332 | K101: 0 | L101: 119.88 | M101: 119.88 | N101: 0 | O101: Jul'22 | P101: 09/08/2022 | Q101: Yes | S101: 100% | T101: E-Invoice | U101: c9b84b3d4e0f974dbb12b69eae22de2db8b3b132c706c640775c15c3bcfbecab | V101: 22/07/2022
A102: 24AAACB2100P1Z3 | B102: Vodafone Idea Limited | C102: GJSO050722404174 | D102: Regular | E102: 15/07/2022 | F102: 1058.46 | G102: Gujarat | H102: No | I102: 18 | J102: 897 | K102: 0 | L102: 80.73 | M102: 80.73 | N102: 0 | O102: Jul'22 | P102: 09/08/2022 | Q102: Yes | S102: 100% | T102: E-Invoice | U102: 1e6e86bcee5169f4c0daba59f05d1845b7f01e575f029bf36da4627ae98316f9 | V102: 15/07/2022
A103: 24AAACB2100P1Z3 | B103: Vodafone Idea Limited | C103: GJSO050722414122 | D103: Regular | E103: 22/07/2022 | F103: 473.96 | G103: Gujarat | H103: No | I103: 18 | J103: 401.66 | K103: 0 | L103: 36.15 | M103: 36.15 | N103: 0 | O103: Jul'22 | P103: 09/08/2022 | Q103: Yes | S103: 100% | T103: E-Invoice | U103: 84cc5c81db2fd80317a7b6879c0b811a3b61be6b57db8f3b8c0be853a0da3605 | V103: 22/07/2022

Sheet ENTRIES-ATMOSPHERE
A2: MONTHLY ENTRIES FOR M/s. SUN REALTY-ATMOSPHERE
A3: =+'ENTRIES-SUN REALTY'!A3:E3
A5: Sr. No. | B5: Date | C5: Particulars | D5: Amt(Rs.) | E5: Amt(Rs.)
D6: Dr. | E6: Cr.
A8: 1 | B8: =+'ENTRIES-SUN REALTY'!B15 | C8: CGST on collection A/c Dr | D8: ='SUN REALTY ATMOS-CALC'!D32
C9: SGST on collection A/c Dr | D9: ='SUN REALTY ATMOS-CALC'!E32
C10: To CGST payable A/c | E10: =D8
C11: To SGST payable A/c | E11: =D9
C12: (Being gst collected transferred to gst payable
C13: for the month of Apr-26)
A15: 2 | B15: =+B8 | C15: CGST Receivable RCM A/c Dr | D15: ='SUN REALTY ATMOS-CALC'!D53
C16: SGST Receivable RCM A/c Dr | D16: ='SUN REALTY ATMOS-CALC'!E53
C17: To CGST payable A/c | E17: =+D15
C18: To SGST payable A/c | E18: =+D16
C19: (Being GST payable under RCM transferred to
C20: GST payabel A/C for the month of Apr-26)
A22: 3 | B22: =+B15 | C22: CGST Exp A/c Dr | D22: =E24
C23: SGST Exp A/c Dr | D23: =E25
C24: To CGST Receivable RCM A/c | E24: =D15
C25: To SGST Receivable RCM A/c | E25: =D16
C26: (Being Credit of RCM transferred to Exp
C27: A/c for the month of Apr-26)
A30: 4 | B30: =+'ENTRIES-SUN REALTY'!B36 | C30: CGST payable A/c Dr. | D30: ='SUN REALTY ATMOS-CALC'!B77
C31: SGST payable A/c Dr. | D31: ='SUN REALTY ATMOS-CALC'!C77
C32: GST Late Payment Int A/c Dr. | D32: 0
C33: To BANK A/c | E33: =+D30+D31+D32-1
C34: (Being amount of GST PAID)

Sheet ENTRIES-FOOTPRINT
A2: MONTHLY ENTRIES FOR M/s. SUN REALTY-FOOTPRINT
A3: =+'ENTRIES-ATMOSPHERE'!A3:E3
A5: Sr. No. | B5: Date | C5: Particulars | D5: Amt(Rs.) | E5: Amt(Rs.)
D6: Dr. | E6: Cr.
A8: 1 | B8: =+'ENTRIES-ATMOSPHERE'!B8 | C8: CGST on collection A/c Dr | D8: ='FOOTPRINT- CALCULATION'!D14
C9: SGST on collection A/c Dr | D9: ='FOOTPRINT- CALCULATION'!E14
C10: To CGST payable A/c | E10: =D8
C11: To SGST payable A/c | E11: =D9
C12: (Being gst collected transferred to gst payable
C13: for the month of Apr-26)
A15: 2 | B15: =+B8 | C15: CGST Receivable RCM A/c Dr | D15: ='FOOTPRINT- CALCULATION'!D31
C16: SGST Receivable RCM A/c Dr | D16: ='FOOTPRINT- CALCULATION'!E31
C17: To CGST payable A/c | E17: =+D15
C18: To SGST payable A/c | E18: =+D16
C19: (Being GST payable under RCM transferred to
C20: GST payabel A/C for the month of Apr-26)
A22: 3 | B22: =+B15 | C22: CGST Exp A/c Dr | D22: =E24
C23: SGST Exp A/c Dr | D23: =E25
C24: To CGST Receivable RCM A/c | E24: =D15
C25: To SGST Receivable RCM A/c | E25: =D16
C26: (Being Credit of RCM transferred to Exp
C27: A/c for the month of Apr-26)
A30: 4 | B30: =+'ENTRIES-ATMOSPHERE'!B30 | C30: CGST payable A/c Dr. | D30: =+'FINAL CALC'!B144
C31: SGST payable A/c Dr. | D31: =+D30
C32: GST Late Payment Int A/c Dr. | D32: 0
C33: To BANK A/c | E33: =+D30+D31+D32
C34: (Being amount of GST PAID)

Sheet ENTRIES-SUN PARK WEST
A2: MONTHLY ENTRIES FOR M/s. SUN REALTY- SUN PARK WEST
A3: =+'ENTRIES-FOOTPRINT'!A3:E3
A5: Sr. No. | B5: Date | C5: Particulars | D5: Amt(Rs.) | E5: Amt(Rs.)
D6: Dr. | E6: Cr.
A8: 1 | B8: =+'ENTRIES-ATMOSPHERE'!B8 | C8: CGST on collection A/c Dr | D8: =+'SUN PARK WEST'!D17
C9: SGST on collection A/c Dr | D9: =+'SUN PARK WEST'!E17
C10: To CGST payable A/c | E10: =D8
C11: To SGST payable A/c | E11: =D9
C12: (Being gst collected transferred to gst payable
C13: for the month of Apr-26)
A15: 2 | B15: =+B8 | C15: CGST Receivable RCM A/c Dr | D15: =+'SUN PARK WEST'!D29
C16: SGST Receivable RCM A/c Dr | D16: =+'SUN PARK WEST'!E29
C17: To CGST payable A/c | E17: =+D15
C18: To SGST payable A/c | E18: =+D16
C19: (Being GST payable under RCM transferred to
C20: GST payabel A/C for the month of Apr-26)
A22: 3 | B22: =+B15 | C22: CGST Exp A/c Dr | D22: =E24
C23: SGST Exp A/c Dr | D23: =E25
C24: To CGST Receivable RCM A/c | E24: =D15
C25: To SGST Receivable RCM A/c | E25: =D16
C26: (Being Credit of RCM transferred to Exp
C27: A/c for the month of Apr-26)
A30: 4 | B30: =+'ENTRIES-ATMOSPHERE'!B30 | C30: CGST payable A/c Dr. | D30: =+'FINAL CALC'!B148
C31: SGST payable A/c Dr. | D31: =+D30
C32: GST Late Payment Int A/c Dr. | D32: 0
C33: To BANK A/c | E33: =SUM(D30:D32)
C34: (Being amount of GST PAID)

Sheet Entries- Sun Silver Springs
A2: MONTHLY ENTRIES FOR M/s. SUN REALTY- SUN SILVER SPRINGS
A3: =+'ENTRIES-FOOTPRINT'!A3:E3
A5: Sr. No. | B5: Date | C5: Particulars | D5: Amt(Rs.) | E5: Amt(Rs.)
D6: Dr. | E6: Cr.
A8: 1 | B8: =+'ENTRIES-ATMOSPHERE'!B8 | C8: CGST on collection A/c Dr | D8: =+'FINAL CALC'!B115
C9: SGST on collection A/c Dr | D9: =+D8
C10: To CGST payable A/c | E10: =D8
C11: To SGST payable A/c | E11: =D9
C12: (Being gst collected transferred to gst payable
C13: for the month of Apr-26)
A15: 2 | B15: =+B8 | C15: CGST Receivable RCM A/c Dr | D15: =+'FINAL CALC'!B124
C16: SGST Receivable RCM A/c Dr | D16: =+D15
C17: To CGST payable A/c | E17: =+D15
C18: To SGST payable A/c | E18: =+D16
C19: (Being GST payable under RCM transferred to
C20: GST payabel A/C for the month of Apr-26)
A22: 3 | B22: =+B15 | C22: CGST Exp A/c Dr | D22: =E24
C23: SGST Exp A/c Dr | D23: =E25
C24: To CGST Receivable RCM A/c | E24: =D15
C25: To SGST Receivable RCM A/c | E25: =D16
C26: (Being Credit of RCM transferred to Exp
C27: A/c for the month of Apr-26)
A30: 4 | B30: =+'ENTRIES-ATMOSPHERE'!B30 | C30: CGST payable A/c Dr. | D30: =+'FINAL CALC'!B152
C31: SGST payable A/c Dr. | D31: =+D30
C32: GST Late Payment Int A/c Dr. | D32: =+'FINAL CALC'!B126+'FINAL CALC'!C126
C33: To BANK A/c | E33: =SUM(D30:D32)
C34: (Being amount of GST PAID)

Sheet PROV Receivable-APRIL
A1: SUN REALTY
A2: CGST Receivable
A3: Ledger Account
A4: BACK DATED ENTRIES OF APRIL 2022
A6: 1-Apr-2022 to 30-Apr-2022
A7: Date | B7: Particulars | D7: Vch Type | E7: Vch No. | F7: Debit | G7: Credit
A8: 44652 | B8: Cr | C8: Opening Balance | F8: 3073811
A9: 44681 | B9: Cr | C9: Compu Brain | D9: Journal | E9: 55 | F9: 219 | H9: AVAILED IN MAY 2022 AS BACK DATEDLY ENTERED IN TALLY
A10: 44681 | B10: Cr | C10: Compu Brain | D10: Journal | E10: 51 | F10: 270 | H10: AVAILED IN MAY 2022 AS BACK DATEDLY ENTERED IN TALLY
A11: 44681 | B11: Cr | C11: Compu Brain | D11: Journal | E11: 52 | F11: 423 | H11: AVAILED IN MAY 2022 AS BACK DATEDLY ENTERED IN TALLY
A12: 44681 | B12: Cr | C12: Compu Brain | D12: Journal | E12: 53 | F12: 423 | H12: AVAILED IN MAY 2022 AS BACK DATEDLY ENTERED IN TALLY
A13: 44662 | B13: Cr | C13: Khushboo Xerox | D13: Journal | E13: 17 | F13: 1183 | H13: TO BE TRANS TO PROV RECIEVABLE
A14: 44681 | B14: Cr | C14: Compu Brain | D14: Journal | E14: 54 | F14: 2200 | H14: AVAILED IN MAY 2022 AS BACK DATEDLY ENTERED IN TALLY
A15: 44652 | B15: Cr | C15: Harshadkumar Govindbhai Patel | D15: Journal | E15: 9 | F15: 7814 | H15: TO BE TRANS TO PROV RECIEVABLE
A16: 44652 | B16: Cr | C16: Patel Sanjaykumar G. | D16: Journal | E16: 10 | F16: 7814 | H16: TO BE TRANS TO PROV RECIEVABLE
A17: 44652 | B17: Cr | C17: Vimal Ranachhodbhai Patel | D17: Journal | E17: 11 | F17: 7814 | H17: TO BE TRANS TO PROV RECIEVABLE
A18: 44652 | B18: Cr | C18: Vishal Ranachhodbhai Patel | D18: Journal | E18: 12 | F18: 7814 | H18: TO BE TRANS TO PROV RECIEVABLE
A19: 3109785
B20: Dr | C20: Closing Balance | G20: 3109785
A21: 3109785 | G21: 3109785

Sheet 2B RECO - APRIL
A1: PROVISIONAL CLOSING BALANVCE AS ON 31-03-2022
A3: Month | B3: NAME | C3: DATE | D3: TAXABLE AMOUNT | E3: CGST | F3: SGST | G3: STATUS
A4: Opening | B4: Property Panther | C4: 07/2021-22 | D4: 54080 | E4: 4867 | F4: 4867
A5: Opening | B5: Epic Infratech | C5: SG-06 | D5: 847458 | E5: 76271 | F5: 76271
A6: Opening | B6: Surbhi Enterprise | C6: 100 | D6: 12500 | E6: 1125 | F6: 1125 | G6: TO BE AVAILED IN MAY COZ REFLECTED IN APRIL 2B (TRANS TO REC FROM PROV REC)
A7: Jan | B7: Khushboo Xerox | C7: 354 | D7: 13328 | E7: 1199 | F7: =+E7
A8: Jan | B8: Gayatri Debit Note | D8: 0 | E8: -222 | F8: -222 | G8: To be reversed in MAY (TRANS TO REC FROM PROV REC)
A9: March | B9: Hare Krushna Concrete Solution | C9: HKL/2122/3934 | D9: 55728 | E9: 5016 | F9: =E9 | G9: TO BE AVAILED IN MAY COZ REFLECTED IN APRIL 2B (TRANS TO REC FROM PROV REC)
A10: March | B10: Hare Krushna Concrete Solution | C10: HKL/2122/3917 | D10: 57471 | E10: =5172 | F10: =E10 | G10: TO BE AVAILED IN MAY COZ REFLECTED IN APRIL 2B (TRANS TO REC FROM PROV REC)
A11: March | B11: Bajaj Allianz General Insurance Co Ltd | C11: 799 | D11: 12237 | E11: =1101 | F11: =E11
A12: TOTAL | E12: =SUM(E4:E11) | F12: =SUM(F4:F11)
A14: ENTRIES IN GSTR 2B NOT REFLECTED IN TALLY FOR THE MONTH OF APRIL 2022
A16: GSTIN of supplier | B16: Trade/Legal name of the Supplier | C16: Invoice number | D16: Invoice Date | E16: Invoice Value (₹) | F16: Taxable Value (₹) | G16: Central Tax (₹) | H16: State/UT tax (₹) | I16: GSTR-1/IFF/GSTR-5 Filing Date
A17: 24AABCB2075J1ZW | B17: BIRLA CORPORATION LIMITED | C17: 1318128408 | D17: 22-04-2022 | E17: 34000 | F17: 26562.5 | G17: 3718.75 | H17: 3718.75 | I17: 10-May-22 | L17: AVAILED IN MAY 2022(TO BE TRANS TO PROV CREDITORS)
A18: 24AABCB2075J1ZW | B18: BIRLA CORPORATION LIMITED | C18: 1318128464 | D18: 23-04-2022 | E18: 42500 | F18: 33203.12 | G18: 4648.44 | H18: 4648.44 | I18: 10-May-22 | L18: AVAILED IN MAY 2022(TO BE TRANS TO PROV CREDITORS)
A19: 24AAGFC5091H1ZJ | B19: COMPUBRAIN | C19: 134 | D19: 30-04-2022 | E19: 32450 | F19: 27500 | G19: 2475 | H19: 2475 | I19: 13-May-22 | L19: NOT TO AVAIL AS CREDIT OF ATMOSPHERE
A20: 24AAGFC5091H1ZJ | B20: COMPUBRAIN | C20: 135 | D20: 30-04-2022 | E20: 37977 | F20: 32184 | G20: 2896.56 | H20: 2896.56 | I20: 13-May-22
A21: 24AAGFC5091H1ZJ | B21: COMPUBRAIN | C21: 136 | D21: 30-04-2022 | E21: 28851 | F21: 24450 | G21: 2200.5 | H21: 2200.5 | I21: 13-May-22
A22: 24AAGFC5091H1ZJ | B22: COMPUBRAIN | C22: 137 | D22: 30-04-2022 | E22: 3540 | F22: 3000 | G22: 270 | H22: 270 | I22: 13-May-22
A23: 24AAGFC5091H1ZJ | B23: COMPUBRAIN | C23: 138 | D23: 30-04-2022 | E23: 5546 | F23: 4700 | G23: 423 | H23: 423 | I23: 13-May-22
A24: 24AAGFC5091H1ZJ | B24: COMPUBRAIN | C24: 139 | D24: 30-04-2022 | E24: 5546 | F24: 4700 | G24: 423 | H24: 423 | I24: 13-May-22
A25: 24AAGFC5091H1ZJ | B25: COMPUBRAIN | C25: 140 | D25: 30-04-2022 | E25: 2870 | F25: 2432 | G25: 218.88 | H25: 218.88 | I25: 13-May-22
A26: 24AOEPP6397M1Z8 | B26: PRATHAM AGENCIES | C26: 14 | D26: 26-04-2022 | E26: 86240 | F26: 77000 | G26: 4620 | H26: 4620 | I26: 09-May-22 | L26: AVAILED IN MAY 2022(TO BE TRANS TO PROV CREDITORS)
A27: 24AGAPP3048H1ZM | B27: SURYA AGENCY | C27: 252 | D27: 29-04-2022 | E27: 425 | F27: 360 | G27: 32.4 | H27: 32.4 | I27: 05-May-22 | L27: AVAILED IN MAY 2022(TO BE TRANS TO PROV CREDITORS)
A28: 24AAGCV5438A1ZL | B28: VITAL SPACE MANAGEMENT PRIVATE LIMITED | C28: 1 | D28: 05-04-2022 | E28: 83320 | F28: 70610 | G28: 6354.9 | H28: 6354.9 | I28: 09-May-22 | L28: AVAILED IN MAY 2022(TO BE TRANS TO PROV CREDITORS)
A29: 24AAJFH1553N1Z7 | B29: HARE KRUSHNA CONCRETE SOLUTIONS | C29: HKL/2122/3917 | D29: 11/03/2022 | E29: 67815 | F29: 57470.33 | G29: 5172.33 | H29: 5172.33 | I29: 12/04/2022
A30: 24AAJFH1553N1Z7 | B30: HARE KRUSHNA CONCRETE SOLUTIONS | C30: HKL/2122/3934 | D30: 12/03/2022 | E30: 65760 | F30: 55728.8 | G30: 5015.59 | H30: 5015.59 | I30: 12/04/2022
A31: 24AQJPB0661M1ZY | B31: S S Bhansali and Co | C31: 2021-22-246 | D31: 07/01/2022 | E31: 38350 | F31: 32500 | G31: 2925 | H31: 2925 | I31: 19/04/2022 | L31: NOT TO AVAIL AS CREDIT OF ATMOSPHERE
A32: 24AQJPB0661M1ZY | B32: S S Bhansali and Co | C32: 2021-22-359 | D32: 16/02/2022 | E32: 11800 | F32: 10000 | G32: 900 | H32: 900 | I32: 19/04/2022
A33: 24AKUPD2154N1ZV | B33: SURBHI ENTERPRISE | C33: 141 | D33: 22/01/2022 | E33: 7375 | F33: 6250 | G33: 562.5 | H33: 562.5 | I33: 22/04/2022
A34: 24AKUPD2154N1ZV | B34: SURBHI ENTERPRISE | C34: 145 | D34: 26/01/2022 | E34: 7375 | F34: 6250 | G34: 562.5 | H34: 562.5 | I34: 22/04/2022
